Workbook

Sheet README
A1: Food Delivery Data Cleaning Workbook
A2: SYNTHETIC practice data (generated for learning) - modelled on Indian food-delivery apps like Swiggy / Zomato. Not real company data.
A4: Sheet | B4: What it contains / what you do there
A5: Data_Dictionary | B5: Meaning of every column in simple English.
A6: Raw_Data | B6: Columns A-N = the messy raw data exactly as received (never edit these). Green columns O-AH = helper formulas that FLAG problems and show the CLEAN version of each field.
A7: Map_Tables | B7: Lookup tables used to standardise city, payment method and restaurant names (like a "translation dictionary").
A8: Cleaned_Data | B8: The final cleaned dataset (values only, except Net_Amount which is a formula). This is what you import into MySQL and Power BI.
A9: Cleaning_Log | B9: Rows before/after, why rows were removed, missing-value report and decisions. All numbers are live formulas.
A10: Outlier_Check | B10: IQR (box-plot) method to find unusual order values and delivery times.
A11: Summary | B11: Formula-based summary tables (same result a PivotTable gives). Build the real PivotTable yourself using the steps in the Excel guide.
A12: Formula_Lab | B12: One working example of each formula you were asked to learn: IF, IFERROR, COUNTIF(S), SUMIF(S), lookup, TRIM.
A14: Colour legend
A15: Dark blue header | B15: Original raw / final data columns
A16: Green header | B16: Helper formula columns (flags and cleaned values)
A17: Yellow cell | B17: An input cell you can change and watch the formula react
A18: Red / orange cell (Raw_Data) | B18: Conditional formatting: red = missing/duplicate/drop, orange = missing delivery time or rating on a delivered order, yellow = invalid value
A20: Business rule for sales | B20: Net_Amount = Quantity x Unit_Price - Discount_Amount. SALES count only orders with Order_Status = Delivered. Cancelled orders are never counted as sales.
A21: Date note | B21: Slash dates in raw data are DD/MM/YYYY (Indian format).

Sheet Data_Dictionary
A1: Data Dictionary
A2: What each column means (simple English)
A4: Column | B4: Data type | C4: Meaning
A5: order_id | B5: Text | C5: Unique ID of one order, e.g. ORD10001. Every order must appear only once.
A6: order_date | B6: Date | C6: Day the customer placed the order (2025). Raw file has 3 different date styles.
A7: order_time | B7: Text HH:MM | C7: Time of day the order was placed (24-hour clock). Used for peak-hour analysis.
A8: customer_id | B8: Text | C8: Unique ID of the customer, e.g. C0123. Used to find repeat customers.
A9: restaurant_name | B9: Text | C9: Restaurant that cooked the food (fictional names).
A10: city | B10: Text | C10: City where the order was delivered (8 Indian cities).
A11: cuisine | B11: Text | C11: Type of food: North Indian, South Indian, Biryani, Chinese, Pizza, Burgers, Street Food, Desserts, Healthy Food.
A12: quantity | B12: Whole number | C12: Number of items in the order. Valid range used here: 1 to 10.
A13: unit_price | B13: Number (Rs) | C13: Price of one item in Indian Rupees. Valid range used here: Rs 1 to Rs 1,500.
A14: discount_amount | B14: Number (Rs) | C14: Total discount (coupon/offer) on the whole order in Rs. Cannot be more than Quantity x Unit Price.
A15: net_amount | B15: Number (Rs) | C15: Cleaned file only. What the customer pays for food = Quantity x Unit Price - Discount. Delivery/tax fees are not included.
... A19: customer_rating | B19: Whole number 1-5 | C19: Star rating given after delivery. Blank if cancelled or customer did not rate.

Sheet Map_Tables
A1: Lookup (mapping) tables
A2: Key = any spelling found in raw data. Lookup is NOT case sensitive, and TRIM removes extra spaces first.
A3: City (raw spelling) | B3: City (standard) | D3: Payment (raw spelling) | E3: Payment (standard) | G3: Restaurant (raw spelling) | H3: Restaurant (standard) | I3: Restaurant city | J3: Cuisine
A4: bangalore | B4: Bengaluru | D4: upi | E4: UPI | G4: Spice Junction | H4: Spice Junction | I4: Bengaluru | J4: North Indian
A5: bengaluru | B5: Bengaluru | D5: credit card | E5: Credit Card | G5: Dosa Darbar | H5: Dosa Darbar | I5: Bengaluru | J5: South Indian
A6: blr | B6: Bengaluru | D6: cc | E6: Credit Card | G6: Nawabi Biryani House | H6: Nawabi Biryani House | I6: Bengaluru | J6: Biryani
A7: mumbai | B7: Mumbai | D7: debit card | E7: Debit Card | G7: Wok & Roll | H7: Wok & Roll | I7: Bengaluru | J7: Chinese
A8: bombay | B8: Mumbai | D8: dc | E8: Debit Card | G8: Wok and Roll | H8: Wok & Roll | I8: Bengaluru | J8: Chinese
A9: delhi | B9: Delhi | D9: cod | E9: Cash on Delivery | G9: Curry Leaf Kitchen | H9: Curry Leaf Kitchen | I9: Mumbai | J9: North Indian
A10: new delhi | B10: Delhi | D10: cash on delivery | E10: Cash on Delivery | G10: Pav Bhaji Point | H10: Pav Bhaji Point | I10: Mumbai | J10: Street Food
A11: hyderabad | B11: Hyderabad | D11: wallet | E11: Wallet | G11: Mumbai Pizza Co | H11: Mumbai Pizza Co | I11: Mumbai | J11: Pizza
A12: hyd | B12: Hyderabad | D12: paytm wallet | E12: Wallet | G12: Dragon Express | H12: Dragon Express | I12: Mumbai | J12: Chinese
A13: chennai | B13: Chennai | D13: e-wallet | E13: Wallet | G13: Tandoor Tales | H13: Tandoor Tales | I13: Delhi | J13: North Indian
A14: madras | B14: Chennai | D14: net banking | E14: Net Banking | G14: Chaat Corner | H14: Chaat Corner | I14: Delhi | J14: Street Food
A15: pune | B15: Pune | D15: netbanking | E15: Net Banking | G15: Burger Barn | H15: Burger Barn | I15: Delhi | J15: Burgers
A16: kolkata | B16: Kolkata | G16: Momo Magic | H16: Momo Magic | I16: Delhi | J16: Chinese
A17: calcutta | B17: Kolkata | G17: Hyderabad Dum Biryani | H17: Hyderabad Dum Biryani | I17: Hyderabad | J17: Biryani
A18: ahmedabad | B18: Ahmedabad | G18: Andhra Meals Mess | H18: Andhra Meals Mess | I18: Hyderabad | J18: South Indian
G19: Pizza Palace | H19: Pizza Palace | I19: Hyderabad | J19: Pizza
G20: Sweet Tooth Studio | H20: Sweet Tooth Studio | I20: Hyderabad | J20: Desserts
G21: Chettinad House | H21: Chettinad House | I21: Chennai | J21: South Indian
G22: Filter Coffee & Tiffin | H22: Filter Coffee & Tiffin | I22: Chennai | J22: South Indian
G23: Filter Coffee and Tiffin | H23: Filter Coffee & Tiffin | I23: Chennai | J23: South Indian
G24: Madras Biryani Co | H24: Madras Biryani Co | I24: Chennai | J24: Biryani
G25: Green Bowl Kitchen | H25: Green Bowl Kitchen | I25: Chennai | J25: Healthy Food
G26: Misal Mantra | H26: Misal Mantra | I26: Pune | J26: Street Food
G27: Pune Burger Hub | H27: Pune Burger Hub | I27: Pune | J27: Burgers
G28: Maratha Thali House | H28: Maratha Thali House | I28: Pune | J28: North Indian
G29: Cake Walk | H29: Cake Walk | I29: Pune | J29: Desserts
G30: Bengal Bites | H30: Bengal Bites | I30: Kolkata | J30: Street Food
... G37: Cheesy Slice | H37: Cheesy Slice | I37: Ahmedabad | J37: Pizza

Sheet Raw_Data
A1: order_id | B1: order_date | C1: order_time | D1: customer_id | E1: restaurant_name | F1: city | G1: cuisine | H1: quantity | I1: unit_price | J1: discount_amount | K1: payment_method | L1: order_status | M1: delivery_time_min | N1: customer_rating | O1: row_key | P1: exact_dup_check | Q1: blank_count | R1: rows_with_same_order_id | S1: order_id_action | T1: missing_order_id | U1: missing_customer_id | V1: missing_restaurant | W1: invalid_quantity | X1: invalid_price | Y1: discount_gt_order_value | Z1: invalid_rating | AA1: invalid_delivery_time | AB1: drop_reason | AC1: keep_or_drop | AD1: city_clean | AE1: restaurant_clean | AF1: payment_clean | AG1: status_clean | AH1: date_clean
A2: ORD10675 | B2: 2025-03-27 | C2: 12:57 | D2: C0623 | E2: Sweet Tooth Studio | F2: Hyderabad | G2: Desserts | H2: 2 | I2: 180 | J2: 0 | K2: UPI | L2: Delivered | M2: 17 | N2: 5 | O2: =A2&"|"&B2&"|"&C2&"|"&D2&"|"&E2&"|"&F2&"|"&G2&"|"&H2&"|"&I2&"|"&J2&"|"&K2&"|"&L2&"|"&M2&"|"&N2 -> ORD10675|2025-03-27|12:57|C0623|Sweet Tooth Studio |Hyderabad|Desserts|2|180|0|UPI|Delivered|17|5 | P2: =IF(COUNTIF($O$2:O2,O2)>1,"DUP","OK") -> OK | Q2: =COUNTBLANK(A2:N2) -> 0 | R2: =IF(A2="",0,COUNTIFS($A$2:$A$3058,A2,$P$2:$P$3058,"OK")) -> 1 | S2: =IF(OR(A2="",P2="DUP",R2<2),"",IF(Q2=_xlfn.MINIFS($Q$2:$Q$3058,$A$2:$A$3058,A2,$P$2:$P$3058,"OK"),"KEEP","DROP")) | T2: =IF(A2="",1,0) -> 0 | U2: =IF(D2="",1,0) -> 0 | V2: =IF(E2="",1,0) -> 0 | W2: =IF(OR(H2<1,H2>10),1,0) -> 0 | X2: =IF(OR(I2<=0,I2>1500),1,0) -> 0 | Y2: =IF(J2>H2*I2,1,0) -> 0 | Z2: =IF(AND(N2<>"",OR(N2<1,N2>5)),1,0) -> 0 | AA2: =IF(AND(M2<>"",OR(M2<5,M2>180)),1,0) -> 0 | AB2: =IF(P2="DUP","Exact duplicate row",IF(T2=1,"Missing Order ID",IF(S2="DROP","Duplicate Order ID (less complete row)",IF(U2=1,"Missing Customer ID",IF(V2=1,"Missing Restaurant name",IF(W2=1,"Invalid/outlier quantity",IF(X2=1,"Invalid/outlier unit price",IF(Y2=1,"Discount greater than order value","")))))))) | AC2: =IF(AB2="","KEEP","DROP") -> KEEP | AD2: =IF(TRIM(F2)="",IFERROR(INDEX(Map_Tables!$I$4:$I$37,MATCH(TRIM(E2),Map_Tables!$G$4:$G$37,0)),""),IFERROR(INDEX(Map_Tables!$B$4:$B$18,MATCH(TRIM(F2),Map_Tables!$A$4:$A$18,0)),"CHECK")) -> Hyderabad | AE2: =IF(TRIM(E2)="","",IFERROR(INDEX(Map_Tables!$H$4:$H$37,MATCH(TRIM(E2),Map_Tables!$G$4:$G$37,0)),"CHECK")) -> Sweet Tooth Studio | AF2: =IF(TRIM(K2)="","Unknown",IFERROR(INDEX(Map_Tables!$E$4:$E$15,MATCH(TRIM(K2),Map_Tables!$D$4:$D$15,0)),"CHECK")) -> UPI | AG2: =IF(LEFT(LOWER(TRIM(L2)),6)="cancel","Cancelled","Delivered") -> Delivered | AH2: =IF(ISNUMBER(SEARCH("/",B2)),DATE(VALUE(RIGHT(B2,4)),VALUE(MID(B2,4,2)),VALUE(LEFT(B2,2))),IF(MID(B2,5,1)="-",DATE(VALUE(LEFT(B2,4)),VALUE(MID(B2,6,2)),VALUE(RIGHT(B2,2))),DATE(VALUE(RIGHT(B2,4)),MATCH(MID(B2,4,3),{"Jan","Feb","Mar","Apr","May","Jun","Jul","Aug","Sep","Oct","Nov","Dec"},0),VALUE(LEFT(B2,2))))) -> 45743
A3: ORD12670 | B3: 2025-11-24 | C3: 22:08 | D3: C0449 | E3: Chaat Corner | F3: Delhi | G3: Street Food | H3: 4 | I3: 95 | J3: 30 | K3: UPI | L3: Delivered | M3: 47 | N3: 3 | O3: =A3&"|"&B3&"|"&C3&"|"&D3&"|"&E3&"|"&F3&"|"&G3&"|"&H3&"|"&I3&"|"&J3&"|"&K3&"|"&L3&"|"&M3&"|"&N3 -> ORD12670|2025-11-24|22:08|C0449|Chaat Corner|Delhi|Street Food|4|95|30|UPI|Delivered|47|3 | P3: =IF(COUNTIF($O$2:O3,O3)>1,"DUP","OK") -> OK | Q3: =COUNTBLANK(A3:N3) -> 0 | R3: =IF(A3="",0,COUNTIFS($A$2:$A$3058,A3,$P$2:$P$3058,"OK")) -> 1 | S3: =IF(OR(A3="",P3="DUP",R3<2),"",IF(Q3=_xlfn.MINIFS($Q$2:$Q$3058,$A$2:$A$3058,A3,$P$2:$P$3058,"OK"),"KEEP","DROP")) | T3: =IF(A3="",1,0) -> 0 | U3: =IF(D3="",1,0) -> 0 | V3: =IF(E3="",1,0) -> 0 | W3: =IF(OR(H3<1,H3>10),1,0) -> 0 | X3: =IF(OR(I3<=0,I3>1500),1,0) -> 0 | Y3: =IF(J3>H3*I3,1,0) -> 0 | Z3: =IF(AND(N3<>"",OR(N3<1,N3>5)),1,0) -> 0 | AA3: =IF(AND(M3<>"",OR(M3<5,M3>180)),1,0) -> 0 | AB3: =IF(P3="DUP","Exact duplicate row",IF(T3=1,"Missing Order ID",IF(S3="DROP","Duplicate Order ID (less complete row)",IF(U3=1,"Missing Customer ID",IF(V3=1,"Missing Restaurant name",IF(W3=1,"Invalid/outlier quantity",IF(X3=1,"Invalid/outlier unit price",IF(Y3=1,"Discount greater than order value","")))))))) | AC3: =IF(AB3="","KEEP","DROP") -> KEEP | AD3: =IF(TRIM(F3)="",IFERROR(INDEX(Map_Tables!$I$4:$I$37,MATCH(TRIM(E3),Map_Tables!$G$4:$G$37,0)),""),IFERROR(INDEX(Map_Tables!$B$4:$B$18,MATCH(TRIM(F3),Map_Tables!$A$4:$A$18,0)),"CHECK")) -> Delhi | AE3: =IF(TRIM(E3)="","",IFERROR(INDEX(Map_Tables!$H$4:$H$37,MATCH(TRIM(E3),Map_Tables!$G$4:$G$37,0)),"CHECK")) -> Chaat Corner | AF3: =IF(TRIM(K3)="","Unknown",IFERROR(INDEX(Map_Tables!$E$4:$E$15,MATCH(TRIM(K3),Map_Tables!$D$4:$D$15,0)),"CHECK")) -> UPI | AG3: =IF(LEFT(LOWER(TRIM(L3)),6)="cancel","Cancelled","Delivered") -> Delivered | AH3: =IF(ISNUMBER(SEARCH("/",B3)),DATE(VALUE(RIGHT(B3,4)),VALUE(MID(B3,4,2)),VALUE(LEFT(B3,2))),IF(MID(B3,5,1)="-",DATE(VALUE(LEFT(B3,4)),VALUE(MID(B3,6,2)),VALUE(RIGHT(B3,2))),DATE(VALUE(RIGHT(B3,4)),MATCH(MID(B3,4,3),{"Jan","Feb","Mar","Apr","May","Jun","Jul","Aug","Sep","Oct","Nov","Dec"},0),VALUE(LEFT(B3,2))))) -> 45985
A4: ORD10378 | B4: 2025-02-19 | C4: 20:46 | D4: C0376 | E4: Chettinad House | F4: Chennai | G4: South Indian | H4: 1 | I4: 160 | J4: 64 | K4: Cash on Delivery | L4: Delivered | M4: 51 | N4: 3 | O4: =A4&"|"&B4&"|"&C4&"|"&D4&"|"&E4&"|"&F4&"|"&G4&"|"&H4&"|"&I4&"|"&J4&"|"&K4&"|"&L4&"|"&M4&"|"&N4 -> ORD10378|2025-02-19|20:46|C0376|Chettinad House|Chennai|South Indian|1|160|64|Cash on Delivery|Delivered|51|3 | P4: =IF(COUNTIF($O$2:O4,O4)>1,"DUP","OK") -> OK | Q4: =COUNTBLANK(A4:N4) -> 0 | R4: =IF(A4="",0,COUNTIFS($A$2:$A$3058,A4,$P$2:$P$3058,"OK")) -> 1 | S4: =IF(OR(A4="",P4="DUP",R4<2),"",IF(Q4=_xlfn.MINIFS($Q$2:$Q$3058,$A$2:$A$3058,A4,$P$2:$P$3058,"OK"),"KEEP","DROP")) | T4: =IF(A4="",1,0) -> 0 | U4: =IF(D4="",1,0) -> 0 | V4: =IF(E4="",1,0) -> 0 | W4: =IF(OR(H4<1,H4>10),1,0) -> 0 | X4: =IF(OR(I4<=0,I4>1500),1,0) -> 0 | Y4: =IF(J4>H4*I4,1,0) -> 0 | Z4: =IF(AND(N4<>"",OR(N4<1,N4>5)),1,0) -> 0 | AA4: =IF(AND(M4<>"",OR(M4<5,M4>180)),1,0) -> 0 | AB4: =IF(P4="DUP","Exact duplicate row",IF(T4=1,"Missing Order ID",IF(S4="DROP","Duplicate Order ID (less complete row)",IF(U4=1,"Missing Customer ID",IF(V4=1,"Missing Restaurant name",IF(W4=1,"Invalid/outlier quantity",IF(X4=1,"Invalid/outlier unit price",IF(Y4=1,"Discount greater than order value","")))))))) | AC4: =IF(AB4="","KEEP","DROP") -> KEEP | AD4: =IF(TRIM(F4)="",IFERROR(INDEX(Map_Tables!$I$4:$I$37,MATCH(TRIM(E4),Map_Tables!$G$4:$G$37,0)),""),IFERROR(INDEX(Map_Tables!$B$4:$B$18,MATCH(TRIM(F4),Map_Tables!$A$4:$A$18,0)),"CHECK")) -> Chennai | AE4: =IF(TRIM(E4)="","",IFERROR(INDEX(Map_Tables!$H$4:$H$37,MATCH(TRIM(E4),Map_Tables!$G$4:$G$37,0)),"CHECK")) -> Chettinad House | AF4: =IF(TRIM(K4)="","Unknown",IFERROR(INDEX(Map_Tables!$E$4:$E$15,MATCH(TRIM(K4),Map_Tables!$D$4:$D$15,0)),"CHECK")) -> Cash on Delivery | AG4: =IF(LEFT(LOWER(TRIM(L4)),6)="cancel","Cancelled","Delivered") -> Delivered | AH4: =IF(ISNUMBER(SEARCH("/",B4)),DATE(VALUE(RIGHT(B4,4)),VALUE(MID(B4,4,2)),VALUE(LEFT(B4,2))),IF(MID(B4,5,1)="-",DATE(VALUE(LEFT(B4,4)),VALUE(MID(B4,6,2)),VALUE(RIGHT(B4,2))),DATE(VALUE(RIGHT(B4,4)),MATCH(MID(B4,4,3),{"Jan","Feb","Mar","Apr","May","Jun","Jul","Aug","Sep","Oct","Nov","Dec"},0),VALUE(LEFT(B4,2))))) -> 45707
A5: ORD10803 | B5: 2025-04-12 | C5: 00:02 | D5: C0164 | E5: Pav Bhaji Point | F5: Mumbai | G5: Street Food | H5: 5 | I5: 140 | J5: 50 | K5: Debit Card | L5: Delivered | M5: 55 | N5: 3 | O5: =A5&"|"&B5&"|"&C5&"|"&D5&"|"&E5&"|"&F5&"|"&G5&"|"&H5&"|"&I5&"|"&J5&"|"&K5&"|"&L5&"|"&M5&"|"&N5 -> ORD10803|2025-04-12|00:02|C0164|Pav Bhaji Point|Mumbai|Street Food|5|140|50|Debit Card|Delivered|55|3 | P5: =IF(COUNTIF($O$2:O5,O5)>1,"DUP","OK") -> OK | Q5: =COUNTBLANK(A5:N5) -> 0 | R5: =IF(A5="",0,COUNTIFS($A$2:$A$3058,A5,$P$2:$P$3058,"OK")) -> 1 | S5: =IF(OR(A5="",P5="DUP",R5<2),"",IF(Q5=_xlfn.MINIFS($Q$2:$Q$3058,$A$2:$A$3058,A5,$P$2:$P$3058,"OK"),"KEEP","DROP")) | T5: =IF(A5="",1,0) -> 0 | U5: =IF(D5="",1,0) -> 0 | V5: =IF(E5="",1,0) -> 0 | W5: =IF(OR(H5<1,H5>10),1,0) -> 0 | X5: =IF(OR(I5<=0,I5>1500),1,0) -> 0 | Y5: =IF(J5>H5*I5,1,0) -> 0 | Z5: =IF(AND(N5<>"",OR(N5<1,N5>5)),1,0) -> 0 | AA5: =IF(AND(M5<>"",OR(M5<5,M5>180)),1,0) -> 0 | AB5: =IF(P5="DUP","Exact duplicate row",IF(T5=1,"Missing Order ID",IF(S5="DROP","Duplicate Order ID (less complete row)",IF(U5=1,"Missing Customer ID",IF(V5=1,"Missing Restaurant name",IF(W5=1,"Invalid/outlier quantity",IF(X5=1,"Invalid/outlier unit price",IF(Y5=1,"Discount greater than order value","")))))))) | AC5: =IF(AB5="","KEEP","DROP") -> KEEP | AD5: =IF(TRIM(F5)="",IFERROR(INDEX(Map_Tables!$I$4:$I$37,MATCH(TRIM(E5),Map_Tables!$G$4:$G$37,0)),""),IFERROR(INDEX(Map_Tables!$B$4:$B$18,MATCH(TRIM(F5),Map_Tables!$A$4:$A$18,0)),"CHECK")) -> Mumbai | AE5: =IF(TRIM(E5)="","",IFERROR(INDEX(Map_Tables!$H$4:$H$37,MATCH(TRIM(E5),Map_Tables!$G$4:$G$37,0)),"CHECK")) -> Pav Bhaji Point | AF5: =IF(TRIM(K5)="","Unknown",IFERROR(INDEX(Map_Tables!$E$4:$E$15,MATCH(TRIM(K5),Map_Tables!$D$4:$D$15,0)),"CHECK")) -> Debit Card | AG5: =IF(LEFT(LOWER(TRIM(L5)),6)="cancel","Cancelled","Delivered") -> Delivered | AH5: =IF(ISNUMBER(SEARCH("/",B5)),DATE(VALUE(RIGHT(B5,4)),VALUE(MID(B5,4,2)),VALUE(LEFT(B5,2))),IF(MID(B5,5,1)="-",DATE(VALUE(LEFT(B5,4)),VALUE(MID(B5,6,2)),VALUE(RIGHT(B5,2))),DATE(VALUE(RIGHT(B5,4)),MATCH(MID(B5,4,3),{"Jan","Feb","Mar","Apr","May","Jun","Jul","Aug","Sep","Oct","Nov","Dec"},0),VALUE(LEFT(B5,2))))) -> 45759
A6: ORD11209 | B6: 02/06/2025 | C6: 21:40 | D6: C1083 | E6: Cheesy Slice | F6: Ahmedabad | G6: Pizza | H6: 1 | I6: 290 | J6: 116 | K6: Cash on Delivery | L6: Delivered | M6: 30 | O6: =A6&"|"&B6&"|"&C6&"|"&D6&"|"&E6&"|"&F6&"|"&G6&"|"&H6&"|"&I6&"|"&J6&"|"&K6&"|"&L6&"|"&M6&"|"&N6 -> ORD11209|02/06/2025|21:40|C1083|Cheesy Slice|Ahmedabad|Pizza|1|290|116|Cash on Delivery|Delivered|30| | P6: =IF(COUNTIF($O$2:O6,O6)>1,"DUP","OK") -> OK | Q6: =COUNTBLANK(A6:N6) -> 1 | R6: =IF(A6="",0,COUNTIFS($A$2:$A$3058,A6,$P$2:$P$3058,"OK")) -> 1 | S6: =IF(OR(A6="",P6="DUP",R6<2),"",IF(Q6=_xlfn.MINIFS($Q$2:$Q$3058,$A$2:$A$3058,A6,$P$2:$P$3058,"OK"),"KEEP","DROP")) | T6: =IF(A6="",1,0) -> 0 | U6: =IF(D6="",1,0) -> 0 | V6: =IF(E6="",1,0) -> 0 | W6: =IF(OR(H6<1,H6>10),1,0) -> 0 | X6: =IF(OR(I6<=0,I6>1500),1,0) -> 0 | Y6: =IF(J6>H6*I6,1,0) -> 0 | Z6: =IF(AND(N6<>"",OR(N6<1,N6>5)),1,0) -> 0 | AA6: =IF(AND(M6<>"",OR(M6<5,M6>180)),1,0) -> 0 | AB6: =IF(P6="DUP","Exact duplicate row",IF(T6=1,"Missing Order ID",IF(S6="DROP","Duplicate Order ID (less complete row)",IF(U6=1,"Missing Customer ID",IF(V6=1,"Missing Restaurant name",IF(W6=1,"Invalid/outlier quantity",IF(X6=1,"Invalid/outlier unit price",IF(Y6=1,"Discount greater than order value","")))))))) | AC6: =IF(AB6="","KEEP","DROP") -> KEEP | AD6: =IF(TRIM(F6)="",IFERROR(INDEX(Map_Tables!$I$4:$I$37,MATCH(TRIM(E6),Map_Tables!$G$4:$G$37,0)),""),IFERROR(INDEX(Map_Tables!$B$4:$B$18,MATCH(TRIM(F6),Map_Tables!$A$4:$A$18,0)),"CHECK")) -> Ahmedabad | AE6: =IF(TRIM(E6)="","",IFERROR(INDEX(Map_Tables!$H$4:$H$37,MATCH(TRIM(E6),Map_Tables!$G$4:$G$37,0)),"CHECK")) -> Cheesy Slice | AF6: =IF(TRIM(K6)="","Unknown",IFERROR(INDEX(Map_Tables!$E$4:$E$15,MATCH(TRIM(K6),Map_Tables!$D$4:$D$15,0)),"CHECK")) -> Cash on Delivery | AG6: =IF(LEFT(LOWER(TRIM(L6)),6)="cancel","Cancelled","Delivered") -> Delivered | AH6: =IF(ISNUMBER(SEARCH("/",B6)),DATE(VALUE(RIGHT(B6,4)),VALUE(MID(B6,4,2)),VALUE(LEFT(B6,2))),IF(MID(B6,5,1)="-",DATE(VALUE(LEFT(B6,4)),VALUE(MID(B6,6,2)),VALUE(RIGHT(B6,2))),DATE(VALUE(RIGHT(B6,4)),MATCH(MID(B6,4,3),{"Jan","Feb","Mar","Apr","May","Jun","Jul","Aug","Sep","Oct","Nov","Dec"},0),VALUE(LEFT(B6,2))))) -> 45810
A7: ORD12737 | B7: 2025-12-01 | C7: 20:37 | D7: C0481 | E7: Mumbai Pizza Co | F7: MUMBAI | G7: Pizza | H7: 3 | I7: 375 | J7: 0 | K7: Net Banking | L7: Delivered | M7: 39 | N7: 4 | O7: =A7&"|"&B7&"|"&C7&"|"&D7&"|"&E7&"|"&F7&"|"&G7&"|"&H7&"|"&I7&"|"&J7&"|"&K7&"|"&L7&"|"&M7&"|"&N7 -> ORD12737|2025-12-01|20:37|C0481|Mumbai Pizza Co|MUMBAI|Pizza|3|375|0|Net Banking|Delivered|39|4 | P7: =IF(COUNTIF($O$2:O7,O7)>1,"DUP","OK") -> OK | Q7: =COUNTBLANK(A7:N7) -> 0 | R7: =IF(A7="",0,COUNTIFS($A$2:$A$3058,A7,$P$2:$P$3058,"OK")) -> 1 | S7: =IF(OR(A7="",P7="DUP",R7<2),"",IF(Q7=_xlfn.MINIFS($Q$2:$Q$3058,$A$2:$A$3058,A7,$P$2:$P$3058,"OK"),"KEEP","DROP")) | T7: =IF(A7="",1,0) -> 0 | U7: =IF(D7="",1,0) -> 0 | V7: =IF(E7="",1,0) -> 0 | W7: =IF(OR(H7<1,H7>10),1,0) -> 0 | X7: =IF(OR(I7<=0,I7>1500),1,0) -> 0 | Y7: =IF(J7>H7*I7,1,0) -> 0 | Z7: =IF(AND(N7<>"",OR(N7<1,N7>5)),1,0) -> 0 | AA7: =IF(AND(M7<>"",OR(M7<5,M7>180)),1,0) -> 0 | AB7: =IF(P7="DUP","Exact duplicate row",IF(T7=1,"Missing Order ID",IF(S7="DROP","Duplicate Order ID (less complete row)",IF(U7=1,"Missing Customer ID",IF(V7=1,"Missing Restaurant name",IF(W7=1,"Invalid/outlier quantity",IF(X7=1,"Invalid/outlier unit price",IF(Y7=1,"Discount greater than order value","")))))))) | AC7: =IF(AB7="","KEEP","DROP") -> KEEP | AD7: =IF(TRIM(F7)="",IFERROR(INDEX(Map_Tables!$I$4:$I$37,MATCH(TRIM(E7),Map_Tables!$G$4:$G$37,0)),""),IFERROR(INDEX(Map_Tables!$B$4:$B$18,MATCH(TRIM(F7),Map_Tables!$A$4:$A$18,0)),"CHECK")) -> Mumbai | AE7: =IF(TRIM(E7)="","",IFERROR(INDEX(Map_Tables!$H$4:$H$37,MATCH(TRIM(E7),Map_Tables!$G$4:$G$37,0)),"CHECK")) -> Mumbai Pizza Co | AF7: =IF(TRIM(K7)="","Unknown",IFERROR(INDEX(Map_Tables!$E$4:$E$15,MATCH(TRIM(K7),Map_Tables!$D$4:$D$15,0)),"CHECK")) -> Net Banking | AG7: =IF(LEFT(LOWER(TRIM(L7)),6)="cancel","Cancelled","Delivered") -> Delivered | AH7: =IF(ISNUMBER(SEARCH("/",B7)),DATE(VALUE(RIGHT(B7,4)),VALUE(MID(B7,4,2)),VALUE(LEFT(B7,2))),IF(MID(B7,5,1)="-",DATE(VALUE(LEFT(B7,4)),VALUE(MID(B7,6,2)),VALUE(RIGHT(B7,2))),DATE(VALUE(RIGHT(B7,4)),MATCH(MID(B7,4,3),{"Jan","Feb","Mar","Apr","May","Jun","Jul","Aug","Sep","Oct","Nov","Dec"},0),VALUE(LEFT(B7,2))))) -> 45992
A8: ORD10853 | B8: 2025-04-18 | C8: 12:48 | D8: C1006 | E8: Chaat Corner | F8: Delhi | G8: Street Food | H8: 1 | I8: 110 | J8: 0 | K8: Credit Card | L8: DELIVERED | M8: 34 | N8: 4 | O8: =A8&"|"&B8&"|"&C8&"|"&D8&"|"&E8&"|"&F8&"|"&G8&"|"&H8&"|"&I8&"|"&J8&"|"&K8&"|"&L8&"|"&M8&"|"&N8 -> ORD10853|2025-04-18|12:48|C1006|Chaat Corner|Delhi|Street Food|1|110|0|Credit Card|DELIVERED|34|4 | P8: =IF(COUNTIF($O$2:O8,O8)>1,"DUP","OK") -> OK | Q8: =COUNTBLANK(A8:N8) -> 0 | R8: =IF(A8="",0,COUNTIFS($A$2:$A$3058,A8,$P$2:$P$3058,"OK")) -> 1 | S8: =IF(OR(A8="",P8="DUP",R8<2),"",IF(Q8=_xlfn.MINIFS($Q$2:$Q$3058,$A$2:$A$3058,A8,$P$2:$P$3058,"OK"),"KEEP","DROP")) | T8: =IF(A8="",1,0) -> 0 | U8: =IF(D8="",1,0) -> 0 | V8: =IF(E8="",1,0) -> 0 | W8: =IF(OR(H8<1,H8>10),1,0) -> 0 | X8: =IF(OR(I8<=0,I8>1500),1,0) -> 0 | Y8: =IF(J8>H8*I8,1,0) -> 0 | Z8: =IF(AND(N8<>"",OR(N8<1,N8>5)),1,0) -> 0 | AA8: =IF(AND(M8<>"",OR(M8<5,M8>180)),1,0) -> 0 | AB8: =IF(P8="DUP","Exact duplicate row",IF(T8=1,"Missing Order ID",IF(S8="DROP","Duplicate Order ID (less complete row)",IF(U8=1,"Missing Customer ID",IF(V8=1,"Missing Restaurant name",IF(W8=1,"Invalid/outlier quantity",IF(X8=1,"Invalid/outlier unit price",IF(Y8=1,"Discount greater than order value","")))))))) | AC8: =IF(AB8="","KEEP","DROP") -> KEEP | AD8: =IF(TRIM(F8)="",IFERROR(INDEX(Map_Tables!$I$4:$I$37,MATCH(TRIM(E8),Map_Tables!$G$4:$G$37,0)),""),IFERROR(INDEX(Map_Tables!$B$4:$B$18,MATCH(TRIM(F8),Map_Tables!$A$4:$A$18,0)),"CHECK")) -> Delhi | AE8: =IF(TRIM(E8)="","",IFERROR(INDEX(Map_Tables!$H$4:$H$37,MATCH(TRIM(E8),Map_Tables!$G$4:$G$37,0)),"CHECK")) -> Chaat Corner | AF8: =IF(TRIM(K8)="","Unknown",IFERROR(INDEX(Map_Tables!$E$4:$E$15,MATCH(TRIM(K8),Map_Tables!$D$4:$D$15,0)),"CHECK")) -> Credit Card | AG8: =IF(LEFT(LOWER(TRIM(L8)),6)="cancel","Cancelled","Delivered") -> Delivered | AH8: =IF(ISNUMBER(SEARCH("/",B8)),DATE(VALUE(RIGHT(B8,4)),VALUE(MID(B8,4,2)),VALUE(LEFT(B8,2))),IF(MID(B8,5,1)="-",DATE(VALUE(LEFT(B8,4)),VALUE(MID(B8,6,2)),VALUE(RIGHT(B8,2))),DATE(VALUE(RIGHT(B8,4)),MATCH(MID(B8,4,3),{"Jan","Feb","Mar","Apr","May","Jun","Jul","Aug","Sep","Oct","Nov","Dec"},0),VALUE(LEFT(B8,2))))) -> 45765
A9: ORD12786 | B9: 2025-12-07 | C9: 10:20 | D9: C1030 | E9: Filter Coffee & Tiffin | F9: Chennai | G9: South Indian | H9: 2 | I9: 105 | J9: 84 | K9: UPI | L9: Delivered | M9: 37 | N9: 3 | O9: =A9&"|"&B9&"|"&C9&"|"&D9&"|"&E9&"|"&F9&"|"&G9&"|"&H9&"|"&I9&"|"&J9&"|"&K9&"|"&L9&"|"&M9&"|"&N9 -> ORD12786|2025-12-07|10:20|C1030|Filter Coffee & Tiffin|Chennai|South Indian|2|105|84|UPI|Delivered|37|3 | P9: =IF(COUNTIF($O$2:O9,O9)>1,"DUP","OK") -> OK | Q9: =COUNTBLANK(A9:N9) -> 0 | R9: =IF(A9="",0,COUNTIFS($A$2:$A$3058,A9,$P$2:$P$3058,"OK")) -> 1 | S9: =IF(OR(A9="",P9="DUP",R9<2),"",IF(Q9=_xlfn.MINIFS($Q$2:$Q$3058,$A$2:$A$3058,A9,$P$2:$P$3058,"OK"),"KEEP","DROP")) | T9: =IF(A9="",1,0) -> 0 | U9: =IF(D9="",1,0) -> 0 | V9: =IF(E9="",1,0) -> 0 | W9: =IF(OR(H9<1,H9>10),1,0) -> 0 | X9: =IF(OR(I9<=0,I9>1500),1,0) -> 0 | Y9: =IF(J9>H9*I9,1,0) -> 0 | Z9: =IF(AND(N9<>"",OR(N9<1,N9>5)),1,0) -> 0 | AA9: =IF(AND(M9<>"",OR(M9<5,M9>180)),1,0) -> 0 | AB9: =IF(P9="DUP","Exact duplicate row",IF(T9=1,"Missing Order ID",IF(S9="DROP","Duplicate Order ID (less complete row)",IF(U9=1,"Missing Customer ID",IF(V9=1,"Missing Restaurant name",IF(W9=1,"Invalid/outlier quantity",IF(X9=1,"Invalid/outlier unit price",IF(Y9=1,"Discount greater than order value","")))))))) | AC9: =IF(AB9="","KEEP","DROP") -> KEEP | AD9: =IF(TRIM(F9)="",IFERROR(INDEX(Map_Tables!$I$4:$I$37,MATCH(TRIM(E9),Map_Tables!$G$4:$G$37,0)),""),IFERROR(INDEX(Map_Tables!$B$4:$B$18,MATCH(TRIM(F9),Map_Tables!$A$4:$A$18,0)),"CHECK")) -> Chennai | AE9: =IF(TRIM(E9)="","",IFERROR(INDEX(Map_Tables!$H$4:$H$37,MATCH(TRIM(E9),Map_Tables!$G$4:$G$37,0)),"CHECK")) -> Filter Coffee & Tiffin | AF9: =IF(TRIM(K9)="","Unknown",IFERROR(INDEX(Map_Tables!$E$4:$E$15,MATCH(TRIM(K9),Map_Tables!$D$4:$D$15,0)),"CHECK")) -> UPI | AG9: =IF(LEFT(LOWER(TRIM(L9)),6)="cancel","Cancelled","Delivered") -> Delivered | AH9: =IF(ISNUMBER(SEARCH("/",B9)),DATE(VALUE(RIGHT(B9,4)),VALUE(MID(B9,4,2)),VALUE(LEFT(B9,2))),IF(MID(B9,5,1)="-",DATE(VALUE(LEFT(B9,4)),VALUE(MID(B9,6,2)),VALUE(RIGHT(B9,2))),DATE(VALUE(RIGHT(B9,4)),MATCH(MID(B9,4,3),{"Jan","Feb","Mar","Apr","May","Jun","Jul","Aug","Sep","Oct","Nov","Dec"},0),VALUE(LEFT(B9,2))))) -> 45998
A10: ORD12001 | B10: 2025-09-16 | C10: 21:36 | D10: C1488 | E10: Mumbai Pizza Co | F10: Mumbai | G10: Pizza | H10: 5 | I10: 295 | J10: 30 | K10: Upi | L10: Delivered | M10: 46 | N10: 3 | O10: =A10&"|"&B10&"|"&C10&"|"&D10&"|"&E10&"|"&F10&"|"&G10&"|"&H10&"|"&I10&"|"&J10&"|"&K10&"|"&L10&"|"&M10&"|"&N10 -> ORD12001|2025-09-16|21:36|C1488|Mumbai Pizza Co|Mumbai|Pizza|5|295|30|Upi|Delivered|46|3 | P10: =IF(COUNTIF($O$2:O10,O10)>1,"DUP","OK") -> OK | Q10: =COUNTBLANK(A10:N10) -> 0 | R10: =IF(A10="",0,COUNTIFS($A$2:$A$3058,A10,$P$2:$P$3058,"OK")) -> 1 | S10: =IF(OR(A10="",P10="DUP",R10<2),"",IF(Q10=_xlfn.MINIFS($Q$2:$Q$3058,$A$2:$A$3058,A10,$P$2:$P$3058,"OK"),"KEEP","DROP")) | T10: =IF(A10="",1,0) -> 0 | U10: =IF(D10="",1,0) -> 0 | V10: =IF(E10="",1,0) -> 0 | W10: =IF(OR(H10<1,H10>10),1,0) -> 0 | X10: =IF(OR(I10<=0,I10>1500),1,0) -> 0 | Y10: =IF(J10>H10*I10,1,0) -> 0 | Z10: =IF(AND(N10<>"",OR(N10<1,N10>5)),1,0) -> 0 | AA10: =IF(AND(M10<>"",OR(M10<5,M10>180)),1,0) -> 0 | AB10: =IF(P10="DUP","Exact duplicate row",IF(T10=1,"Missing Order ID",IF(S10="DROP","Duplicate Order ID (less complete row)",IF(U10=1,"Missing Customer ID",IF(V10=1,"Missing Restaurant name",IF(W10=1,"Invalid/outlier quantity",IF(X10=1,"Invalid/outlier unit price",IF(Y10=1,"Discount greater than order value","")))))))) | AC10: =IF(AB10="","KEEP","DROP") -> KEEP | AD10: =IF(TRIM(F10)="",IFERROR(INDEX(Map_Tables!$I$4:$I$37,MATCH(TRIM(E10),Map_Tables!$G$4:$G$37,0)),""),IFERROR(INDEX(Map_Tables!$B$4:$B$18,MATCH(TRIM(F10),Map_Tables!$A$4:$A$18,0)),"CHECK")) -> Mumbai | AE10: =IF(TRIM(E10)="","",IFERROR(INDEX(Map_Tables!$H$4:$H$37,MATCH(TRIM(E10),Map_Tables!$G$4:$G$37,0)),"CHECK")) -> Mumbai Pizza Co | AF10: =IF(TRIM(K10)="","Unknown",IFERROR(INDEX(Map_Tables!$E$4:$E$15,MATCH(TRIM(K10),Map_Tables!$D$4:$D$15,0)),"CHECK")) -> UPI | AG10: =IF(LEFT(LOWER(TRIM(L10)),6)="cancel","Cancelled","Delivered") -> Delivered | AH10: =IF(ISNUMBER(SEARCH("/",B10)),DATE(VALUE(RIGHT(B10,4)),VALUE(MID(B10,4,2)),VALUE(LEFT(B10,2))),IF(MID(B10,5,1)="-",DATE(VALUE(LEFT(B10,4)),VALUE(MID(B10,6,2)),VALUE(RIGHT(B10,2))),DATE(VALUE(RIGHT(B10,4)),MATCH(MID(B10,4,3),{"Jan","Feb","Mar","Apr","May","Jun","Jul","Aug","Sep","Oct","Nov","Dec"},0),VALUE(LEFT(B10,2))))) -> 45916
A11: ORD12725 | B11: 2025-11-30 | C11: 21:09 | D11: C0193 | E11: Curry Leaf Kitchen | F11: Mumbai | G11: North Indian | H11: 5 | I11: 220 | J11: 100 | K11: UPI | L11: Delivered | M11: 56 | N11: 3 | O11: =A11&"|"&B11&"|"&C11&"|"&D11&"|"&E11&"|"&F11&"|"&G11&"|"&H11&"|"&I11&"|"&J11&"|"&K11&"|"&L11&"|"&M11&"|"&N11 -> ORD12725|2025-11-30|21:09|C0193|Curry Leaf Kitchen|Mumbai|North Indian|5|220|100|UPI|Delivered|56|3 | P11: =IF(COUNTIF($O$2:O11,O11)>1,"DUP","OK") -> OK | Q11: =COUNTBLANK(A11:N11) -> 0 | R11: =IF(A11="",0,COUNTIFS($A$2:$A$3058,A11,$P$2:$P$3058,"OK")) -> 1 | S11: =IF(OR(A11="",P11="DUP",R11<2),"",IF(Q11=_xlfn.MINIFS($Q$2:$Q$3058,$A$2:$A$3058,A11,$P$2:$P$3058,"OK"),"KEEP","DROP")) | T11: =IF(A11="",1,0) -> 0 | U11: =IF(D11="",1,0) -> 0 | V11: =IF(E11="",1,0) -> 0 | W11: =IF(OR(H11<1,H11>10),1,0) -> 0 | X11: =IF(OR(I11<=0,I11>1500),1,0) -> 0 | Y11: =IF(J11>H11*I11,1,0) -> 0 | Z11: =IF(AND(N11<>"",OR(N11<1,N11>5)),1,0) -> 0 | AA11: =IF(AND(M11<>"",OR(M11<5,M11>180)),1,0) -> 0 | AB11: =IF(P11="DUP","Exact duplicate row",IF(T11=1,"Missing Order ID",IF(S11="DROP","Duplicate Order ID (less complete row)",IF(U11=1,"Missing Customer ID",IF(V11=1,"Missing Restaurant name",IF(W11=1,"Invalid/outlier quantity",IF(X11=1,"Invalid/outlier unit price",IF(Y11=1,"Discount greater than order value","")))))))) | AC11: =IF(AB11="","KEEP","DROP") -> KEEP | AD11: =IF(TRIM(F11)="",IFERROR(INDEX(Map_Tables!$I$4:$I$37,MATCH(TRIM(E11),Map_Tables!$G$4:$G$37,0)),""),IFERROR(INDEX(Map_Tables!$B$4:$B$18,MATCH(TRIM(F11),Map_Tables!$A$4:$A$18,0)),"CHECK")) -> Mumbai | AE11: =IF(TRIM(E11)="","",IFERROR(INDEX(Map_Tables!$H$4:$H$37,MATCH(TRIM(E11),Map_Tables!$G$4:$G$37,0)),"CHECK")) -> Curry Leaf Kitchen | AF11: =IF(TRIM(K11)="","Unknown",IFERROR(INDEX(Map_Tables!$E$4:$E$15,MATCH(TRIM(K11),Map_Tables!$D$4:$D$15,0)),"CHECK")) -> UPI | AG11: =IF(LEFT(LOWER(TRIM(L11)),6)="cancel","Cancelled","Delivered") -> Delivered | AH11: =IF(ISNUMBER(SEARCH("/",B11)),DATE(VALUE(RIGHT(B11,4)),VALUE(MID(B11,4,2)),VALUE(LEFT(B11,2))),IF(MID(B11,5,1)="-",DATE(VALUE(LEFT(B11,4)),VALUE(MID(B11,6,2)),VALUE(RIGHT(B11,2))),DATE(VALUE(RIGHT(B11,4)),MATCH(MID(B11,4,3),{"Jan","Feb","Mar","Apr","May","Jun","Jul","Aug","Sep","Oct","Nov","Dec"},0),VALUE(LEFT(B11,2))))) -> 45991
A12: ORD10430 | B12: 2025-02-27 | C12: 19:26 | D12: C1390 | E12: Chaat Corner | F12: Delhi | G12: Street Food | H12: 5 | I12: 105 | J12: 0 | K12: UPI | L12: Cancelled | O12: =A12&"|"&B12&"|"&C12&"|"&D12&"|"&E12&"|"&F12&"|"&G12&"|"&H12&"|"&I12&"|"&J12&"|"&K12&"|"&L12&"|"&M12&"|"&N12 -> ORD10430|2025-02-27|19:26|C1390|Chaat Corner|Delhi|Street Food|5|105|0|UPI|Cancelled|| | P12: =IF(COUNTIF($O$2:O12,O12)>1,"DUP","OK") -> OK | Q12: =COUNTBLANK(A12:N12) -> 2 | R12: =IF(A12="",0,COUNTIFS($A$2:$A$3058,A12,$P$2:$P$3058,"OK")) -> 1 | S12: =IF(OR(A12="",P12="DUP",R12<2),"",IF(Q12=_xlfn.MINIFS($Q$2:$Q$3058,$A$2:$A$3058,A12,$P$2:$P$3058,"OK"),"KEEP","DROP")) | T12: =IF(A12="",1,0) -> 0 | U12: =IF(D12="",1,0) -> 0 | V12: =IF(E12="",1,0) -> 0 | W12: =IF(OR(H12<1,H12>10),1,0) -> 0 | X12: =IF(OR(I12<=0,I12>1500),1,0) -> 0 | Y12: =IF(J12>H12*I12,1,0) -> 0 | Z12: =IF(AND(N12<>"",OR(N12<1,N12>5)),1,0) -> 0 | AA12: =IF(AND(M12<>"",OR(M12<5,M12>180)),1,0) -> 0 | AB12: =IF(P12="DUP","Exact duplicate row",IF(T12=1,"Missing Order ID",IF(S12="DROP","Duplicate Order ID (less complete row)",IF(U12=1,"Missing Customer ID",IF(V12=1,"Missing Restaurant name",IF(W12=1,"Invalid/outlier quantity",IF(X12=1,"Invalid/outlier unit price",IF(Y12=1,"Discount greater than order value","")))))))) | AC12: =IF(AB12="","KEEP","DROP") -> KEEP | AD12: =IF(TRIM(F12)="",IFERROR(INDEX(Map_Tables!$I$4:$I$37,MATCH(TRIM(E12),Map_Tables!$G$4:$G$37,0)),""),IFERROR(INDEX(Map_Tables!$B$4:$B$18,MATCH(TRIM(F12),Map_Tables!$A$4:$A$18,0)),"CHECK")) -> Delhi | AE12: =IF(TRIM(E12)="","",IFERROR(INDEX(Map_Tables!$H$4:$H$37,MATCH(TRIM(E12),Map_Tables!$G$4:$G$37,0)),"CHECK")) -> Chaat Corner | AF12: =IF(TRIM(K12)="","Unknown",IFERROR(INDEX(Map_Tables!$E$4:$E$15,MATCH(TRIM(K12),Map_Tables!$D$4:$D$15,0)),"CHECK")) -> UPI | AG12: =IF(LEFT(LOWER(TRIM(L12)),6)="cancel","Cancelled","Delivered") -> Cancelled | AH12: =IF(ISNUMBER(SEARCH("/",B12)),DATE(VALUE(RIGHT(B12,4)),VALUE(MID(B12,4,2)),VALUE(LEFT(B12,2))),IF(MID(B12,5,1)="-",DATE(VALUE(LEFT(B12,4)),VALUE(MID(B12,6,2)),VALUE(RIGHT(B12,2))),DATE(VALUE(RIGHT(B12,4)),MATCH(MID(B12,4,3),{"Jan","Feb","Mar","Apr","May","Jun","Jul","Aug","Sep","Oct","Nov","Dec"},0),VALUE(LEFT(B12,2))))) -> 45715
A13: ORD12148 | B13: 2025-10-02 | C13: 11:59 | D13: C1117 | E13: Maratha Thali House | F13: Pune | G13: North Indian | H13: 4 | I13: 285 | J13: 150 | K13: Credit Card | L13: Delivered | M13: 33 | N13: 5 | O13: =A13&"|"&B13&"|"&C13&"|"&D13&"|"&E13&"|"&F13&"|"&G13&"|"&H13&"|"&I13&"|"&J13&"|"&K13&"|"&L13&"|"&M13&"|"&N13 -> ORD12148|2025-10-02|11:59|C1117|Maratha Thali House|Pune|North Indian|4|285|150|Credit Card|Delivered|33|5 | P13: =IF(COUNTIF($O$2:O13,O13)>1,"DUP","OK") -> OK | Q13: =COUNTBLANK(A13:N13) -> 0 | R13: =IF(A13="",0,COUNTIFS($A$2:$A$3058,A13,$P$2:$P$3058,"OK")) -> 1 | S13: =IF(OR(A13="",P13="DUP",R13<2),"",IF(Q13=_xlfn.MINIFS($Q$2:$Q$3058,$A$2:$A$3058,A13,$P$2:$P$3058,"OK"),"KEEP","DROP")) | T13: =IF(A13="",1,0) -> 0 | U13: =IF(D13="",1,0) -> 0 | V13: =IF(E13="",1,0) -> 0 | W13: =IF(OR(H13<1,H13>10),1,0) -> 0 | X13: =IF(OR(I13<=0,I13>1500),1,0) -> 0 | Y13: =IF(J13>H13*I13,1,0) -> 0 | Z13: =IF(AND(N13<>"",OR(N13<1,N13>5)),1,0) -> 0 | AA13: =IF(AND(M13<>"",OR(M13<5,M13>180)),1,0) -> 0 | AB13: =IF(P13="DUP","Exact duplicate row",IF(T13=1,"Missing Order ID",IF(S13="DROP","Duplicate Order ID (less complete row)",IF(U13=1,"Missing Customer ID",IF(V13=1,"Missing Restaurant name",IF(W13=1,"Invalid/outlier quantity",IF(X13=1,"Invalid/outlier unit price",IF(Y13=1,"Discount greater than order value","")))))))) | AC13: =IF(AB13="","KEEP","DROP") -> KEEP | AD13: =IF(TRIM(F13)="",IFERROR(INDEX(Map_Tables!$I$4:$I$37,MATCH(TRIM(E13),Map_Tables!$G$4:$G$37,0)),""),IFERROR(INDEX(Map_Tables!$B$4:$B$18,MATCH(TRIM(F13),Map_Tables!$A$4:$A$18,0)),"CHECK")) -> Pune | AE13: =IF(TRIM(E13)="","",IFERROR(INDEX(Map_Tables!$H$4:$H$37,MATCH(TRIM(E13),Map_Tables!$G$4:$G$37,0)),"CHECK")) -> Maratha Thali House | AF13: =IF(TRIM(K13)="","Unknown",IFERROR(INDEX(Map_Tables!$E$4:$E$15,MATCH(TRIM(K13),Map_Tables!$D$4:$D$15,0)),"CHECK")) -> Credit Card | AG13: =IF(LEFT(LOWER(TRIM(L13)),6)="cancel","Cancelled","Delivered") -> Delivered | AH13: =IF(ISNUMBER(SEARCH("/",B13)),DATE(VALUE(RIGHT(B13,4)),VALUE(MID(B13,4,2)),VALUE(LEFT(B13,2))),IF(MID(B13,5,1)="-",DATE(VALUE(LEFT(B13,4)),VALUE(MID(B13,6,2)),VALUE(RIGHT(B13,2))),DATE(VALUE(RIGHT(B13,4)),MATCH(MID(B13,4,3),{"Jan","Feb","Mar","Apr","May","Jun","Jul","Aug","Sep","Oct","Nov","Dec"},0),VALUE(LEFT(B13,2))))) -> 45932
A14: ORD10728 | B14: 2025-04-03 | C14: 13:09 | D14: C1478 | E14: Bengal Bites | F14: Kolkata | G14: Street Food | H14: 5 | I14: 110 | J14: 20 | K14: Credit Card | L14: Cancelled | O14: =A14&"|"&B14&"|"&C14&"|"&D14&"|"&E14&"|"&F14&"|"&G14&"|"&H14&"|"&I14&"|"&J14&"|"&K14&"|"&L14&"|"&M14&"|"&N14 -> ORD10728|2025-04-03|13:09|C1478|Bengal Bites|Kolkata|Street Food|5|110|20|Credit Card|Cancelled|| | P14: =IF(COUNTIF($O$2:O14,O14)>1,"DUP","OK") -> OK | Q14: =COUNTBLANK(A14:N14) -> 2 | R14: =IF(A14="",0,COUNTIFS($A$2:$A$3058,A14,$P$2:$P$3058,"OK")) -> 1 | S14: =IF(OR(A14="",P14="DUP",R14<2),"",IF(Q14=_xlfn.MINIFS($Q$2:$Q$3058,$A$2:$A$3058,A14,$P$2:$P$3058,"OK"),"KEEP","DROP")) | T14: =IF(A14="",1,0) -> 0 | U14: =IF(D14="",1,0) -> 0 | V14: =IF(E14="",1,0) -> 0 | W14: =IF(OR(H14<1,H14>10),1,0) -> 0 | X14: =IF(OR(I14<=0,I14>1500),1,0) -> 0 | Y14: =IF(J14>H14*I14,1,0) -> 0 | Z14: =IF(AND(N14<>"",OR(N14<1,N14>5)),1,0) -> 0 | AA14: =IF(AND(M14<>"",OR(M14<5,M14>180)),1,0) -> 0 | AB14: =IF(P14="DUP","Exact duplicate row",IF(T14=1,"Missing Order ID",IF(S14="DROP","Duplicate Order ID (less complete row)",IF(U14=1,"Missing Customer ID",IF(V14=1,"Missing Restaurant name",IF(W14=1,"Invalid/outlier quantity",IF(X14=1,"Invalid/outlier unit price",IF(Y14=1,"Discount greater than order value","")))))))) | AC14: =IF(AB14="","KEEP","DROP") -> KEEP | AD14: =IF(TRIM(F14)="",IFERROR(INDEX(Map_Tables!$I$4:$I$37,MATCH(TRIM(E14),Map_Tables!$G$4:$G$37,0)),""),IFERROR(INDEX(Map_Tables!$B$4:$B$18,MATCH(TRIM(F14),Map_Tables!$A$4:$A$18,0)),"CHECK")) -> Kolkata | AE14: =IF(TRIM(E14)="","",IFERROR(INDEX(Map_Tables!$H$4:$H$37,MATCH(TRIM(E14),Map_Tables!$G$4:$G$37,0)),"CHECK")) -> Bengal Bites | AF14: =IF(TRIM(K14)="","Unknown",IFERROR(INDEX(Map_Tables!$E$4:$E$15,MATCH(TRIM(K14),Map_Tables!$D$4:$D$15,0)),"CHECK")) -> Credit Card | AG14: =IF(LEFT(LOWER(TRIM(L14)),6)="cancel","Cancelled","Delivered") -> Cancelled | AH14: =IF(ISNUMBER(SEARCH("/",B14)),DATE(VALUE(RIGHT(B14,4)),VALUE(MID(B14,4,2)),VALUE(LEFT(B14,2))),IF(MID(B14,5,1)="-",DATE(VALUE(LEFT(B14,4)),VALUE(MID(B14,6,2)),VALUE(RIGHT(B14,2))),DATE(VALUE(RIGHT(B14,4)),MATCH(MID(B14,4,3),{"Jan","Feb","Mar","Apr","May","Jun","Jul","Aug","Sep","Oct","Nov","Dec"},0),VALUE(LEFT(B14,2))))) -> 45750
A15: ORD10455 | B15: 2025-03-02 | C15: 14:00 | D15: C0969 | E15: Burger Barn | F15: Delhi | G15: burgers | H15: 1 | I15: 225 | J15: 0 | K15: UPI | L15: Delivered | M15: 36 | N15: 4 | O15: =A15&"|"&B15&"|"&C15&"|"&D15&"|"&E15&"|"&F15&"|"&G15&"|"&H15&"|"&I15&"|"&J15&"|"&K15&"|"&L15&"|"&M15&"|"&N15 -> ORD10455|2025-03-02|14:00|C0969|Burger Barn|Delhi|burgers|1|225|0|UPI|Delivered|36|4 | P15: =IF(COUNTIF($O$2:O15,O15)>1,"DUP","OK") -> OK | Q15: =COUNTBLANK(A15:N15) -> 0 | R15: =IF(A15="",0,COUNTIFS($A$2:$A$3058,A15,$P$2:$P$3058,"OK")) -> 1 | S15: =IF(OR(A15="",P15="DUP",R15<2),"",IF(Q15=_xlfn.MINIFS($Q$2:$Q$3058,$A$2:$A$3058,A15,$P$2:$P$3058,"OK"),"KEEP","DROP")) | T15: =IF(A15="",1,0) -> 0 | U15: =IF(D15="",1,0) -> 0 | V15: =IF(E15="",1,0) -> 0 | W15: =IF(OR(H15<1,H15>10),1,0) -> 0 | X15: =IF(OR(I15<=0,I15>1500),1,0) -> 0 | Y15: =IF(J15>H15*I15,1,0) -> 0 | Z15: =IF(AND(N15<>"",OR(N15<1,N15>5)),1,0) -> 0 | AA15: =IF(AND(M15<>"",OR(M15<5,M15>180)),1,0) -> 0 | AB15: =IF(P15="DUP","Exact duplicate row",IF(T15=1,"Missing Order ID",IF(S15="DROP","Duplicate Order ID (less complete row)",IF(U15=1,"Missing Customer ID",IF(V15=1,"Missing Restaurant name",IF(W15=1,"Invalid/outlier quantity",IF(X15=1,"Invalid/outlier unit price",IF(Y15=1,"Discount greater than order value","")))))))) | AC15: =IF(AB15="","KEEP","DROP") -> KEEP | AD15: =IF(TRIM(F15)="",IFERROR(INDEX(Map_Tables!$I$4:$I$37,MATCH(TRIM(E15),Map_Tables!$G$4:$G$37,0)),""),IFERROR(INDEX(Map_Tables!$B$4:$B$18,MATCH(TRIM(F15),Map_Tables!$A$4:$A$18,0)),"CHECK")) -> Delhi | AE15: =IF(TRIM(E15)="","",IFERROR(INDEX(Map_Tables!$H$4:$H$37,MATCH(TRIM(E15),Map_Tables!$G$4:$G$37,0)),"CHECK")) -> Burger Barn | AF15: =IF(TRIM(K15)="","Unknown",IFERROR(INDEX(Map_Tables!$E$4:$E$15,MATCH(TRIM(K15),Map_Tables!$D$4:$D$15,0)),"CHECK")) -> UPI | AG15: =IF(LEFT(LOWER(TRIM(L15)),6)="cancel","Cancelled","Delivered") -> Delivered | AH15: =IF(ISNUMBER(SEARCH("/",B15)),DATE(VALUE(RIGHT(B15,4)),VALUE(MID(B15,4,2)),VALUE(LEFT(B15,2))),IF(MID(B15,5,1)="-",DATE(VALUE(LEFT(B15,4)),VALUE(MID(B15,6,2)),VALUE(RIGHT(B15,2))),DATE(VALUE(RIGHT(B15,4)),MATCH(MID(B15,4,3),{"Jan","Feb","Mar","Apr","May","Jun","Jul","Aug","Sep","Oct","Nov","Dec"},0),VALUE(LEFT(B15,2))))) -> 45718
A16: ORD10741 | B16: 2025-04-04 | C16: 20:58 | D16: C0821 | E16: Mumbai Pizza Co | F16: Mumbai | G16: Pizza | H16: 1 | I16: 255 | J16: 75 | K16: UPI | L16: Delivered | M16: 53 | N16: 2 | O16: =A16&"|"&B16&"|"&C16&"|"&D16&"|"&E16&"|"&F16&"|"&G16&"|"&H16&"|"&I16&"|"&J16&"|"&K16&"|"&L16&"|"&M16&"|"&N16 -> ORD10741|2025-04-04|20:58|C0821|Mumbai Pizza Co|Mumbai|Pizza|1|255|75|UPI|Delivered|53|2 | P16: =IF(COUNTIF($O$2:O16,O16)>1,"DUP","OK") -> OK | Q16: =COUNTBLANK(A16:N16) -> 0 | R16: =IF(A16="",0,COUNTIFS($A$2:$A$3058,A16,$P$2:$P$3058,"OK")) -> 1 | S16: =IF(OR(A16="",P16="DUP",R16<2),"",IF(Q16=_xlfn.MINIFS($Q$2:$Q$3058,$A$2:$A$3058,A16,$P$2:$P$3058,"OK"),"KEEP","DROP")) | T16: =IF(A16="",1,0) -> 0 | U16: =IF(D16="",1,0) -> 0 | V16: =IF(E16="",1,0) -> 0 | W16: =IF(OR(H16<1,H16>10),1,0) -> 0 | X16: =IF(OR(I16<=0,I16>1500),1,0) -> 0 | Y16: =IF(J16>H16*I16,1,0) -> 0 | Z16: =IF(AND(N16<>"",OR(N16<1,N16>5)),1,0) -> 0 | AA16: =IF(AND(M16<>"",OR(M16<5,M16>180)),1,0) -> 0 | AB16: =IF(P16="DUP","Exact duplicate row",IF(T16=1,"Missing Order ID",IF(S16="DROP","Duplicate Order ID (less complete row)",IF(U16=1,"Missing Customer ID",IF(V16=1,"Missing Restaurant name",IF(W16=1,"Invalid/outlier quantity",IF(X16=1,"Invalid/outlier unit price",IF(Y16=1,"Discount greater than order value","")))))))) | AC16: =IF(AB16="","KEEP","DROP") -> KEEP | AD16: =IF(TRIM(F16)="",IFERROR(INDEX(Map_Tables!$I$4:$I$37,MATCH(TRIM(E16),Map_Tables!$G$4:$G$37,0)),""),IFERROR(INDEX(Map_Tables!$B$4:$B$18,MATCH(TRIM(F16),Map_Tables!$A$4:$A$18,0)),"CHECK")) -> Mumbai | AE16: =IF(TRIM(E16)="","",IFERROR(INDEX(Map_Tables!$H$4:$H$37,MATCH(TRIM(E16),Map_Tables!$G$4:$G$37,0)),"CHECK")) -> Mumbai Pizza Co | AF16: =IF(TRIM(K16)="","Unknown",IFERROR(INDEX(Map_Tables!$E$4:$E$15,MATCH(TRIM(K16),Map_Tables!$D$4:$D$15,0)),"CHECK")) -> UPI | AG16: =IF(LEFT(LOWER(TRIM(L16)),6)="cancel","Cancelled","Delivered") -> Delivered | AH16: =IF(ISNUMBER(SEARCH("/",B16)),DATE(VALUE(RIGHT(B16,4)),VALUE(MID(B16,4,2)),VALUE(LEFT(B16,2))),IF(MID(B16,5,1)="-",DATE(VALUE(LEFT(B16,4)),VALUE(MID(B16,6,2)),VALUE(RIGHT(B16,2))),DATE(VALUE(RIGHT(B16,4)),MATCH(MID(B16,4,3),{"Jan","Feb","Mar","Apr","May","Jun","Jul","Aug","Sep","Oct","Nov","Dec"},0),VALUE(LEFT(B16,2))))) -> 45751
A17: ORD10363 | B17: 2025-02-17 | C17: 20:24 | D17: C0392 | E17: Burger Barn | F17: Delhi | G17: Burgers | H17: 2 | I17: 125 | J17: 100 | K17: UPI | L17: Delivered | M17: 33 | N17: 3 | O17: =A17&"|"&B17&"|"&C17&"|"&D17&"|"&E17&"|"&F17&"|"&G17&"|"&H17&"|"&I17&"|"&J17&"|"&K17&"|"&L17&"|"&M17&"|"&N17 -> ORD10363|2025-02-17|20:24|C0392| Burger Barn|Delhi|Burgers|2|125|100|UPI|Delivered|33|3 | P17: =IF(COUNTIF($O$2:O17,O17)>1,"DUP","OK") -> OK | Q17: =COUNTBLANK(A17:N17) -> 0 | R17: =IF(A17="",0,COUNTIFS($A$2:$A$3058,A17,$P$2:$P$3058,"OK")) -> 1 | S17: =IF(OR(A17="",P17="DUP",R17<2),"",IF(Q17=_xlfn.MINIFS($Q$2:$Q$3058,$A$2:$A$3058,A17,$P$2:$P$3058,"OK"),"KEEP","DROP")) | T17: =IF(A17="",1,0) -> 0 | U17: =IF(D17="",1,0) -> 0 | V17: =IF(E17="",1,0) -> 0 | W17: =IF(OR(H17<1,H17>10),1,0) -> 0 | X17: =IF(OR(I17<=0,I17>1500),1,0) -> 0 | Y17: =IF(J17>H17*I17,1,0) -> 0 | Z17: =IF(AND(N17<>"",OR(N17<1,N17>5)),1,0) -> 0 | AA17: =IF(AND(M17<>"",OR(M17<5,M17>180)),1,0) -> 0 | AB17: =IF(P17="DUP","Exact duplicate row",IF(T17=1,"Missing Order ID",IF(S17="DROP","Duplicate Order ID (less complete row)",IF(U17=1,"Missing Customer ID",IF(V17=1,"Missing Restaurant name",IF(W17=1,"Invalid/outlier quantity",IF(X17=1,"Invalid/outlier unit price",IF(Y17=1,"Discount greater than order value","")))))))) | AC17: =IF(AB17="","KEEP","DROP") -> KEEP | AD17: =IF(TRIM(F17)="",IFERROR(INDEX(Map_Tables!$I$4:$I$37,MATCH(TRIM(E17),Map_Tables!$G$4:$G$37,0)),""),IFERROR(INDEX(Map_Tables!$B$4:$B$18,MATCH(TRIM(F17),Map_Tables!$A$4:$A$18,0)),"CHECK")) -> Delhi | AE17: =IF(TRIM(E17)="","",IFERROR(INDEX(Map_Tables!$H$4:$H$37,MATCH(TRIM(E17),Map_Tables!$G$4:$G$37,0)),"CHECK")) -> Burger Barn | AF17: =IF(TRIM(K17)="","Unknown",IFERROR(INDEX(Map_Tables!$E$4:$E$15,MATCH(TRIM(K17),Map_Tables!$D$4:$D$15,0)),"CHECK")) -> UPI | AG17: =IF(LEFT(LOWER(TRIM(L17)),6)="cancel","Cancelled","Delivered") -> Delivered | AH17: =IF(ISNUMBER(SEARCH("/",B17)),DATE(VALUE(RIGHT(B17,4)),VALUE(MID(B17,4,2)),VALUE(LEFT(B17,2))),IF(MID(B17,5,1)="-",DATE(VALUE(LEFT(B17,4)),VALUE(MID(B17,6,2)),VALUE(RIGHT(B17,2))),DATE(VALUE(RIGHT(B17,4)),MATCH(MID(B17,4,3),{"Jan","Feb","Mar","Apr","May","Jun","Jul","Aug","Sep","Oct","Nov","Dec"},0),VALUE(LEFT(B17,2))))) -> 45705
A18: ORD11338 | B18: 2025-06-22 | C18: 11:22 | D18: C1445 | E18: Pune Burger Hub | F18: Pune | G18: Burgers | H18: 4 | I18: 235 | J18: 0 | K18: UPI | L18: Delivered | M18: 30 | N18: 5 | O18: =A18&"|"&B18&"|"&C18&"|"&D18&"|"&E18&"|"&F18&"|"&G18&"|"&H18&"|"&I18&"|"&J18&"|"&K18&"|"&L18&"|"&M18&"|"&N18 -> ORD11338|2025-06-22|11:22|C1445| Pune Burger Hub|Pune|Burgers|4|235|0|UPI|Delivered|30|5 | P18: =IF(COUNTIF($O$2:O18,O18)>1,"DUP","OK") -> OK | Q18: =COUNTBLANK(A18:N18) -> 0 | R18: =IF(A18="",0,COUNTIFS($A$2:$A$3058,A18,$P$2:$P$3058,"OK")) -> 1 | S18: =IF(OR(A18="",P18="DUP",R18<2),"",IF(Q18=_xlfn.MINIFS($Q$2:$Q$3058,$A$2:$A$3058,A18,$P$2:$P$3058,"OK"),"KEEP","DROP")) | T18: =IF(A18="",1,0) -> 0 | U18: =IF(D18="",1,0) -> 0 | V18: =IF(E18="",1,0) -> 0 | W18: =IF(OR(H18<1,H18>10),1,0) -> 0 | X18: =IF(OR(I18<=0,I18>1500),1,0) -> 0 | Y18: =IF(J18>H18*I18,1,0) -> 0 | Z18: =IF(AND(N18<>"",OR(N18<1,N18>5)),1,0) -> 0 | AA18: =IF(AND(M18<>"",OR(M18<5,M18>180)),1,0) -> 0 | AB18: =IF(P18="DUP","Exact duplicate row",IF(T18=1,"Missing Order ID",IF(S18="DROP","Duplicate Order ID (less complete row)",IF(U18=1,"Missing Customer ID",IF(V18=1,"Missing Restaurant name",IF(W18=1,"Invalid/outlier quantity",IF(X18=1,"Invalid/outlier unit price",IF(Y18=1,"Discount greater than order value","")))))))) | AC18: =IF(AB18="","KEEP","DROP") -> KEEP | AD18: =IF(TRIM(F18)="",IFERROR(INDEX(Map_Tables!$I$4:$I$37,MATCH(TRIM(E18),Map_Tables!$G$4:$G$37,0)),""),IFERROR(INDEX(Map_Tables!$B$4:$B$18,MATCH(TRIM(F18),Map_Tables!$A$4:$A$18,0)),"CHECK")) -> Pune | AE18: =IF(TRIM(E18)="","",IFERROR(INDEX(Map_Tables!$H$4:$H$37,MATCH(TRIM(E18),Map_Tables!$G$4:$G$37,0)),"CHECK")) -> Pune Burger Hub | AF18: =IF(TRIM(K18)="","Unknown",IFERROR(INDEX(Map_Tables!$E$4:$E$15,MATCH(TRIM(K18),Map_Tables!$D$4:$D$15,0)),"CHECK")) -> UPI | AG18: =IF(LEFT(LOWER(TRIM(L18)),6)="cancel","Cancelled","Delivered") -> Delivered | AH18: =IF(ISNUMBER(SEARCH("/",B18)),DATE(VALUE(RIGHT(B18,4)),VALUE(MID(B18,4,2)),VALUE(LEFT(B18,2))),IF(MID(B18,5,1)="-",DATE(VALUE(LEFT(B18,4)),VALUE(MID(B18,6,2)),VALUE(RIGHT(B18,2))),DATE(VALUE(RIGHT(B18,4)),MATCH(MID(B18,4,3),{"Jan","Feb","Mar","Apr","May","Jun","Jul","Aug","Sep","Oct","Nov","Dec"},0),VALUE(LEFT(B18,2))))) -> 45830
A19: ORD11217 | B19: 2025-06-03 | C19: 19:16 | D19: C1418 | E19: Wok & Roll | F19: Bengaluru | G19: Chinese | H19: 3 | I19: 210 | J19: 0 | K19: UPI | L19: Delivered | M19: 49 | N19: 3 | O19: =A19&"|"&B19&"|"&C19&"|"&D19&"|"&E19&"|"&F19&"|"&G19&"|"&H19&"|"&I19&"|"&J19&"|"&K19&"|"&L19&"|"&M19&"|"&N19 -> ORD11217|2025-06-03|19:16|C1418|Wok & Roll|Bengaluru|Chinese|3|210|0|UPI|Delivered|49|3 | P19: =IF(COUNTIF($O$2:O19,O19)>1,"DUP","OK") -> OK | Q19: =COUNTBLANK(A19:N19) -> 0 | R19: =IF(A19="",0,COUNTIFS($A$2:$A$3058,A19,$P$2:$P$3058,"OK")) -> 1 | S19: =IF(OR(A19="",P19="DUP",R19<2),"",IF(Q19=_xlfn.MINIFS($Q$2:$Q$3058,$A$2:$A$3058,A19,$P$2:$P$3058,"OK"),"KEEP","DROP")) | T19: =IF(A19="",1,0) -> 0 | U19: =IF(D19="",1,0) -> 0 | V19: =IF(E19="",1,0) -> 0 | W19: =IF(OR(H19<1,H19>10),1,0) -> 0 | X19: =IF(OR(I19<=0,I19>1500),1,0) -> 0 | Y19: =IF(J19>H19*I19,1,0) -> 0 | Z19: =IF(AND(N19<>"",OR(N19<1,N19>5)),1,0) -> 0 | AA19: =IF(AND(M19<>"",OR(M19<5,M19>180)),1,0) -> 0 | AB19: =IF(P19="DUP","Exact duplicate row",IF(T19=1,"Missing Order ID",IF(S19="DROP","Duplicate Order ID (less complete row)",IF(U19=1,"Missing Customer ID",IF(V19=1,"Missing Restaurant name",IF(W19=1,"Invalid/outlier quantity",IF(X19=1,"Invalid/outlier unit price",IF(Y19=1,"Discount greater than order value","")))))))) | AC19: =IF(AB19="","KEEP","DROP") -> KEEP | AD19: =IF(TRIM(F19)="",IFERROR(INDEX(Map_Tables!$I$4:$I$37,MATCH(TRIM(E19),Map_Tables!$G$4:$G$37,0)),""),IFERROR(INDEX(Map_Tables!$B$4:$B$18,MATCH(TRIM(F19),Map_Tables!$A$4:$A$18,0)),"CHECK")) -> Bengaluru | AE19: =IF(TRIM(E19)="","",IFERROR(INDEX(Map_Tables!$H$4:$H$37,MATCH(TRIM(E19),Map_Tables!$G$4:$G$37,0)),"CHECK")) -> Wok & Roll | AF19: =IF(TRIM(K19)="","Unknown",IFERROR(INDEX(Map_Tables!$E$4:$E$15,MATCH(TRIM(K19),Map_Tables!$D$4:$D$15,0)),"CHECK")) -> UPI | AG19: =IF(LEFT(LOWER(TRIM(L19)),6)="cancel","Cancelled","Delivered") -> Delivered | AH19: =IF(ISNUMBER(SEARCH("/",B19)),DATE(VALUE(RIGHT(B19,4)),VALUE(MID(B19,4,2)),VALUE(LEFT(B19,2))),IF(MID(B19,5,1)="-",DATE(VALUE(LEFT(B19,4)),VALUE(MID(B19,6,2)),VALUE(RIGHT(B19,2))),DATE(VALUE(RIGHT(B19,4)),MATCH(MID(B19,4,3),{"Jan","Feb","Mar","Apr","May","Jun","Jul","Aug","Sep","Oct","Nov","Dec"},0),VALUE(LEFT(B19,2))))) -> 45811
A20: ORD10581 | B20: 2025-03-15 | C20: 14:01 | D20: C1344 | E20: Pav Bhaji Point | F20: Mumbai | G20: Street Food | H20: 3 | I20: 145 | J20: 150 | K20: Wallet | L20: Delivered | M20: 42 | N20: 5 | O20: =A20&"|"&B20&"|"&C20&"|"&D20&"|"&E20&"|"&F20&"|"&G20&"|"&H20&"|"&I20&"|"&J20&"|"&K20&"|"&L20&"|"&M20&"|"&N20 -> ORD10581|2025-03-15|14:01|C1344|Pav Bhaji Point|Mumbai|Street Food|3|145|150|Wallet|Delivered|42|5 | P20: =IF(COUNTIF($O$2:O20,O20)>1,"DUP","OK") -> OK | Q20: =COUNTBLANK(A20:N20) -> 0 | R20: =IF(A20="",0,COUNTIFS($A$2:$A$3058,A20,$P$2:$P$3058,"OK")) -> 1 | S20: =IF(OR(A20="",P20="DUP",R20<2),"",IF(Q20=_xlfn.MINIFS($Q$2:$Q$3058,$A$2:$A$3058,A20,$P$2:$P$3058,"OK"),"KEEP","DROP")) | T20: =IF(A20="",1,0) -> 0 | U20: =IF(D20="",1,0) -> 0 | V20: =IF(E20="",1,0) -> 0 | W20: =IF(OR(H20<1,H20>10),1,0) -> 0 | X20: =IF(OR(I20<=0,I20>1500),1,0) -> 0 | Y20: =IF(J20>H20*I20,1,0) -> 0 | Z20: =IF(AND(N20<>"",OR(N20<1,N20>5)),1,0) -> 0 | AA20: =IF(AND(M20<>"",OR(M20<5,M20>180)),1,0) -> 0 | AB20: =IF(P20="DUP","Exact duplicate row",IF(T20=1,"Missing Order ID",IF(S20="DROP","Duplicate Order ID (less complete row)",IF(U20=1,"Missing Customer ID",IF(V20=1,"Missing Restaurant name",IF(W20=1,"Invalid/outlier quantity",IF(X20=1,"Invalid/outlier unit price",IF(Y20=1,"Discount greater than order value","")))))))) | AC20: =IF(AB20="","KEEP","DROP") -> KEEP | AD20: =IF(TRIM(F20)="",IFERROR(INDEX(Map_Tables!$I$4:$I$37,MATCH(TRIM(E20),Map_Tables!$G$4:$G$37,0)),""),IFERROR(INDEX(Map_Tables!$B$4:$B$18,MATCH(TRIM(F20),Map_Tables!$A$4:$A$18,0)),"CHECK")) -> Mumbai | AE20: =IF(TRIM(E20)="","",IFERROR(INDEX(Map_Tables!$H$4:$H$37,MATCH(TRIM(E20),Map_Tables!$G$4:$G$37,0)),"CHECK")) -> Pav Bhaji Point | AF20: =IF(TRIM(K20)="","Unknown",IFERROR(INDEX(Map_Tables!$E$4:$E$15,MATCH(TRIM(K20),Map_Tables!$D$4:$D$15,0)),"CHECK")) -> Wallet | AG20: =IF(LEFT(LOWER(TRIM(L20)),6)="cancel","Cancelled","Delivered") -> Delivered | AH20: =IF(ISNUMBER(SEARCH("/",B20)),DATE(VALUE(RIGHT(B20,4)),VALUE(MID(B20,4,2)),VALUE(LEFT(B20,2))),IF(MID(B20,5,1)="-",DATE(VALUE(LEFT(B20,4)),VALUE(MID(B20,6,2)),VALUE(RIGHT(B20,2))),DATE(VALUE(RIGHT(B20,4)),MATCH(MID(B20,4,3),{"Jan","Feb","Mar","Apr","May","Jun","Jul","Aug","Sep","Oct","Nov","Dec"},0),VALUE(LEFT(B20,2))))) -> 45731
A21: ORD10126 | B21: 2025-01-16 | C21: 20:51 | D21: C0365 | E21: Dragon Express | F21: Mumbai | G21: Chinese | H21: 2 | I21: 285 | J21: 0 | K21: UPI | L21: Delivered | M21: 47 | N21: 5 | O21: =A21&"|"&B21&"|"&C21&"|"&D21&"|"&E21&"|"&F21&"|"&G21&"|"&H21&"|"&I21&"|"&J21&"|"&K21&"|"&L21&"|"&M21&"|"&N21 -> ORD10126|2025-01-16|20:51|C0365|Dragon Express|Mumbai|Chinese|2|285|0|UPI|Delivered|47|5 | P21: =IF(COUNTIF($O$2:O21,O21)>1,"DUP","OK") -> OK | Q21: =COUNTBLANK(A21:N21) -> 0 | R21: =IF(A21="",0,COUNTIFS($A$2:$A$3058,A21,$P$2:$P$3058,"OK")) -> 1 | S21: =IF(OR(A21="",P21="DUP",R21<2),"",IF(Q21=_xlfn.MINIFS($Q$2:$Q$3058,$A$2:$A$3058,A21,$P$2:$P$3058,"OK"),"KEEP","DROP")) | T21: =IF(A21="",1,0) -> 0 | U21: =IF(D21="",1,0) -> 0 | V21: =IF(E21="",1,0) -> 0 | W21: =IF(OR(H21<1,H21>10),1,0) -> 0 | X21: =IF(OR(I21<=0,I21>1500),1,0) -> 0 | Y21: =IF(J21>H21*I21,1,0) -> 0 | Z21: =IF(AND(N21<>"",OR(N21<1,N21>5)),1,0) -> 0 | AA21: =IF(AND(M21<>"",OR(M21<5,M21>180)),1,0) -> 0 | AB21: =IF(P21="DUP","Exact duplicate row",IF(T21=1,"Missing Order ID",IF(S21="DROP","Duplicate Order ID (less complete row)",IF(U21=1,"Missing Customer ID",IF(V21=1,"Missing Restaurant name",IF(W21=1,"Invalid/outlier quantity",IF(X21=1,"Invalid/outlier unit price",IF(Y21=1,"Discount greater than order value","")))))))) | AC21: =IF(AB21="","KEEP","DROP") -> KEEP | AD21: =IF(TRIM(F21)="",IFERROR(INDEX(Map_Tables!$I$4:$I$37,MATCH(TRIM(E21),Map_Tables!$G$4:$G$37,0)),""),IFERROR(INDEX(Map_Tables!$B$4:$B$18,MATCH(TRIM(F21),Map_Tables!$A$4:$A$18,0)),"CHECK")) -> Mumbai | AE21: =IF(TRIM(E21)="","",IFERROR(INDEX(Map_Tables!$H$4:$H$37,MATCH(TRIM(E21),Map_Tables!$G$4:$G$37,0)),"CHECK")) -> Dragon Express | AF21: =IF(TRIM(K21)="","Unknown",IFERROR(INDEX(Map_Tables!$E$4:$E$15,MATCH(TRIM(K21),Map_Tables!$D$4:$D$15,0)),"CHECK")) -> UPI | AG21: =IF(LEFT(LOWER(TRIM(L21)),6)="cancel","Cancelled","Delivered") -> Delivered | AH21: =IF(ISNUMBER(SEARCH("/",B21)),DATE(VALUE(RIGHT(B21,4)),VALUE(MID(B21,4,2)),VALUE(LEFT(B21,2))),IF(MID(B21,5,1)="-",DATE(VALUE(LEFT(B21,4)),VALUE(MID(B21,6,2)),VALUE(RIGHT(B21,2))),DATE(VALUE(RIGHT(B21,4)),MATCH(MID(B21,4,3),{"Jan","Feb","Mar","Apr","May","Jun","Jul","Aug","Sep","Oct","Nov","Dec"},0),VALUE(LEFT(B21,2))))) -> 45673
A22: ORD12702 | B22: 28/11/2025 | C22: 20:39 | D22: C0984 | E22: Hyderabad Dum Biryani | F22: Hyderabad | G22: Biryani | H22: 1 | I22: 305 | J22: 122 | K22: UPI | L22: Delivered | M22: 58 | N22: 4 | O22: =A22&"|"&B22&"|"&C22&"|"&D22&"|"&E22&"|"&F22&"|"&G22&"|"&H22&"|"&I22&"|"&J22&"|"&K22&"|"&L22&"|"&M22&"|"&N22 -> ORD12702|28/11/2025|20:39|C0984|Hyderabad Dum Biryani|Hyderabad|Biryani|1|305|122|UPI|Delivered|58|4 | P22: =IF(COUNTIF($O$2:O22,O22)>1,"DUP","OK") -> OK | Q22: =COUNTBLANK(A22:N22) -> 0 | R22: =IF(A22="",0,COUNTIFS($A$2:$A$3058,A22,$P$2:$P$3058,"OK")) -> 1 | S22: =IF(OR(A22="",P22="DUP",R22<2),"",IF(Q22=_xlfn.MINIFS($Q$2:$Q$3058,$A$2:$A$3058,A22,$P$2:$P$3058,"OK"),"KEEP","DROP")) | T22: =IF(A22="",1,0) -> 0 | U22: =IF(D22="",1,0) -> 0 | V22: =IF(E22="",1,0) -> 0 | W22: =IF(OR(H22<1,H22>10),1,0) -> 0 | X22: =IF(OR(I22<=0,I22>1500),1,0) -> 0 | Y22: =IF(J22>H22*I22,1,0) -> 0 | Z22: =IF(AND(N22<>"",OR(N22<1,N22>5)),1,0) -> 0 | AA22: =IF(AND(M22<>"",OR(M22<5,M22>180)),1,0) -> 0 | AB22: =IF(P22="DUP","Exact duplicate row",IF(T22=1,"Missing Order ID",IF(S22="DROP","Duplicate Order ID (less complete row)",IF(U22=1,"Missing Customer ID",IF(V22=1,"Missing Restaurant name",IF(W22=1,"Invalid/outlier quantity",IF(X22=1,"Invalid/outlier unit price",IF(Y22=1,"Discount greater than order value","")))))))) | AC22: =IF(AB22="","KEEP","DROP") -> KEEP | AD22: =IF(TRIM(F22)="",IFERROR(INDEX(Map_Tables!$I$4:$I$37,MATCH(TRIM(E22),Map_Tables!$G$4:$G$37,0)),""),IFERROR(INDEX(Map_Tables!$B$4:$B$18,MATCH(TRIM(F22),Map_Tables!$A$4:$A$18,0)),"CHECK")) -> Hyderabad | AE22: =IF(TRIM(E22)="","",IFERROR(INDEX(Map_Tables!$H$4:$H$37,MATCH(TRIM(E22),Map_Tables!$G$4:$G$37,0)),"CHECK")) -> Hyderabad Dum Biryani | AF22: =IF(TRIM(K22)="","Unknown",IFERROR(INDEX(Map_Tables!$E$4:$E$15,MATCH(TRIM(K22),Map_Tables!$D$4:$D$15,0)),"CHECK")) -> UPI | AG22: =IF(LEFT(LOWER(TRIM(L22)),6)="cancel","Cancelled","Delivered") -> Delivered | AH22: =IF(ISNUMBER(SEARCH("/",B22)),DATE(VALUE(RIGHT(B22,4)),VALUE(MID(B22,4,2)),VALUE(LEFT(B22,2))),IF(MID(B22,5,1)="-",DATE(VALUE(LEFT(B22,4)),VALUE(MID(B22,6,2)),VALUE(RIGHT(B22,2))),DATE(VALUE(RIGHT(B22,4)),MATCH(MID(B22,4,3),{"Jan","Feb","Mar","Apr","May","Jun","Jul","Aug","Sep","Oct","Nov","Dec"},0),VALUE(LEFT(B22,2))))) -> 45989
A23: ORD12440 | B23: 2025-11-03 | C23: 11:51 | D23: C1140 | E23: Hyderabad Dum Biryani | G23: Biryani | H23: 4 | I23: 250 | J23: 150 | K23: UPI | L23: Delivered | M23: 19 | N23: 5 | O23: =A23&"|"&B23&"|"&C23&"|"&D23&"|"&E23&"|"&F23&"|"&G23&"|"&H23&"|"&I23&"|"&J23&"|"&K23&"|"&L23&"|"&M23&"|"&N23 -> ORD12440|2025-11-03|11:51|C1140|Hyderabad Dum Biryani||Biryani|4|250|150|UPI|Delivered|19|5 | P23: =IF(COUNTIF($O$2:O23,O23)>1,"DUP","OK") -> OK | Q23: =COUNTBLANK(A23:N23) -> 1 | R23: =IF(A23="",0,COUNTIFS($A$2:$A$3058,A23,$P$2:$P$3058,"OK")) -> 1 | S23: =IF(OR(A23="",P23="DUP",R23<2),"",IF(Q23=_xlfn.MINIFS($Q$2:$Q$3058,$A$2:$A$3058,A23,$P$2:$P$3058,"OK"),"KEEP","DROP")) | T23: =IF(A23="",1,0) -> 0 | U23: =IF(D23="",1,0) -> 0 | V23: =IF(E23="",1,0) -> 0 | W23: =IF(OR(H23<1,H23>10),1,0) -> 0 | X23: =IF(OR(I23<=0,I23>1500),1,0) -> 0 | Y23: =IF(J23>H23*I23,1,0) -> 0 | Z23: =IF(AND(N23<>"",OR(N23<1,N23>5)),1,0) -> 0 | AA23: =IF(AND(M23<>"",OR(M23<5,M23>180)),1,0) -> 0 | AB23: =IF(P23="DUP","Exact duplicate row",IF(T23=1,"Missing Order ID",IF(S23="DROP","Duplicate Order ID (less complete row)",IF(U23=1,"Missing Customer ID",IF(V23=1,"Missing Restaurant name",IF(W23=1,"Invalid/outlier quantity",IF(X23=1,"Invalid/outlier unit price",IF(Y23=1,"Discount greater than order value","")))))))) | AC23: =IF(AB23="","KEEP","DROP") -> KEEP | AD23: =IF(TRIM(F23)="",IFERROR(INDEX(Map_Tables!$I$4:$I$37,MATCH(TRIM(E23),Map_Tables!$G$4:$G$37,0)),""),IFERROR(INDEX(Map_Tables!$B$4:$B$18,MATCH(TRIM(F23),Map_Tables!$A$4:$A$18,0)),"CHECK")) -> Hyderabad | AE23: =IF(TRIM(E23)="","",IFERROR(INDEX(Map_Tables!$H$4:$H$37,MATCH(TRIM(E23),Map_Tables!$G$4:$G$37,0)),"CHECK")) -> Hyderabad Dum Biryani | AF23: =IF(TRIM(K23)="","Unknown",IFERROR(INDEX(Map_Tables!$E$4:$E$15,MATCH(TRIM(K23),Map_Tables!$D$4:$D$15,0)),"CHECK")) -> UPI | AG23: =IF(LEFT(LOWER(TRIM(L23)),6)="cancel","Cancelled","Delivered") -> Delivered | AH23: =IF(ISNUMBER(SEARCH("/",B23)),DATE(VALUE(RIGHT(B23,4)),VALUE(MID(B23,4,2)),VALUE(LEFT(B23,2))),IF(MID(B23,5,1)="-",DATE(VALUE(LEFT(B23,4)),VALUE(MID(B23,6,2)),VALUE(RIGHT(B23,2))),DATE(VALUE(RIGHT(B23,4)),MATCH(MID(B23,4,3),{"Jan","Feb","Mar","Apr","May","Jun","Jul","Aug","Sep","Oct","Nov","Dec"},0),VALUE(LEFT(B23,2))))) -> 45964
A24: ORD10503 | B24: 07/03/2025 | C24: 14:58 | D24: C1262 | E24: Green Bowl Kitchen | F24: Chennai | G24: Healthy Food | H24: 1 | I24: 315 | J24: 0 | K24: UPI | L24: Delivered | M24: 37 | N24: 5 | O24: =A24&"|"&B24&"|"&C24&"|"&D24&"|"&E24&"|"&F24&"|"&G24&"|"&H24&"|"&I24&"|"&J24&"|"&K24&"|"&L24&"|"&M24&"|"&N24 -> ORD10503|07/03/2025|14:58|C1262|Green Bowl Kitchen|Chennai|Healthy Food|1|315|0|UPI|Delivered|37|5 | P24: =IF(COUNTIF($O$2:O24,O24)>1,"DUP","OK") -> OK | Q24: =COUNTBLANK(A24:N24) -> 0 | R24: =IF(A24="",0,COUNTIFS($A$2:$A$3058,A24,$P$2:$P$3058,"OK")) -> 1 | S24: =IF(OR(A24="",P24="DUP",R24<2),"",IF(Q24=_xlfn.MINIFS($Q$2:$Q$3058,$A$2:$A$3058,A24,$P$2:$P$3058,"OK"),"KEEP","DROP")) | T24: =IF(A24="",1,0) -> 0 | U24: =IF(D24="",1,0) -> 0 | V24: =IF(E24="",1,0) -> 0 | W24: =IF(OR(H24<1,H24>10),1,0) -> 0 | X24: =IF(OR(I24<=0,I24>1500),1,0) -> 0 | Y24: =IF(J24>H24*I24,1,0) -> 0 | Z24: =IF(AND(N24<>"",OR(N24<1,N24>5)),1,0) -> 0 | AA24: =IF(AND(M24<>"",OR(M24<5,M24>180)),1,0) -> 0 | AB24: =IF(P24="DUP","Exact duplicate row",IF(T24=1,"Missing Order ID",IF(S24="DROP","Duplicate Order ID (less complete row)",IF(U24=1,"Missing Customer ID",IF(V24=1,"Missing Restaurant name",IF(W24=1,"Invalid/outlier quantity",IF(X24=1,"Invalid/outlier unit price",IF(Y24=1,"Discount greater than order value","")))))))) | AC24: =IF(AB24="","KEEP","DROP") -> KEEP | AD24: =IF(TRIM(F24)="",IFERROR(INDEX(Map_Tables!$I$4:$I$37,MATCH(TRIM(E24),Map_Tables!$G$4:$G$37,0)),""),IFERROR(INDEX(Map_Tables!$B$4:$B$18,MATCH(TRIM(F24),Map_Tables!$A$4:$A$18,0)),"CHECK")) -> Chennai | AE24: =IF(TRIM(E24)="","",IFERROR(INDEX(Map_Tables!$H$4:$H$37,MATCH(TRIM(E24),Map_Tables!$G$4:$G$37,0)),"CHECK")) -> Green Bowl Kitchen | AF24: =IF(TRIM(K24)="","Unknown",IFERROR(INDEX(Map_Tables!$E$4:$E$15,MATCH(TRIM(K24),Map_Tables!$D$4:$D$15,0)),"CHECK")) -> UPI | AG24: =IF(LEFT(LOWER(TRIM(L24)),6)="cancel","Cancelled","Delivered") -> Delivered | AH24: =IF(ISNUMBER(SEARCH("/",B24)),DATE(VALUE(RIGHT(B24,4)),VALUE(MID(B24,4,2)),VALUE(LEFT(B24,2))),IF(MID(B24,5,1)="-",DATE(VALUE(LEFT(B24,4)),VALUE(MID(B24,6,2)),VALUE(RIGHT(B24,2))),DATE(VALUE(RIGHT(B24,4)),MATCH(MID(B24,4,3),{"Jan","Feb","Mar","Apr","May","Jun","Jul","Aug","Sep","Oct","Nov","Dec"},0),VALUE(LEFT(B24,2))))) -> 45723
A25: ORD11228 | B25: 2025-06-05 | C25: 18:02 | D25: C1451 | E25: Burger Barn | F25: New Delhi | G25: Burgers | H25: 1 | I25: 170 | J25: 68 | K25: UPI | L25: Delivered | M25: 37 | N25: 5 | O25: =A25&"|"&B25&"|"&C25&"|"&D25&"|"&E25&"|"&F25&"|"&G25&"|"&H25&"|"&I25&"|"&J25&"|"&K25&"|"&L25&"|"&M25&"|"&N25 -> ORD11228|2025-06-05|18:02|C1451|Burger Barn|New Delhi|Burgers|1|170|68|UPI|Delivered|37|5 | P25: =IF(COUNTIF($O$2:O25,O25)>1,"DUP","OK") -> OK | Q25: =COUNTBLANK(A25:N25) -> 0 | R25: =IF(A25="",0,COUNTIFS($A$2:$A$3058,A25,$P$2:$P$3058,"OK")) -> 1 | S25: =IF(OR(A25="",P25="DUP",R25<2),"",IF(Q25=_xlfn.MINIFS($Q$2:$Q$3058,$A$2:$A$3058,A25,$P$2:$P$3058,"OK"),"KEEP","DROP")) | T25: =IF(A25="",1,0) -> 0 | U25: =IF(D25="",1,0) -> 0 | V25: =IF(E25="",1,0) -> 0 | W25: =IF(OR(H25<1,H25>10),1,0) -> 0 | X25: =IF(OR(I25<=0,I25>1500),1,0) -> 0 | Y25: =IF(J25>H25*I25,1,0) -> 0 | Z25: =IF(AND(N25<>"",OR(N25<1,N25>5)),1,0) -> 0 | AA25: =IF(AND(M25<>"",OR(M25<5,M25>180)),1,0) -> 0 | AB25: =IF(P25="DUP","Exact duplicate row",IF(T25=1,"Missing Order ID",IF(S25="DROP","Duplicate Order ID (less complete row)",IF(U25=1,"Missing Customer ID",IF(V25=1,"Missing Restaurant name",IF(W25=1,"Invalid/outlier quantity",IF(X25=1,"Invalid/outlier unit price",IF(Y25=1,"Discount greater than order value","")))))))) | AC25: =IF(AB25="","KEEP","DROP") -> KEEP | AD25: =IF(TRIM(F25)="",IFERROR(INDEX(Map_Tables!$I$4:$I$37,MATCH(TRIM(E25),Map_Tables!$G$4:$G$37,0)),""),IFERROR(INDEX(Map_Tables!$B$4:$B$18,MATCH(TRIM(F25),Map_Tables!$A$4:$A$18,0)),"CHECK")) -> Delhi | AE25: =IF(TRIM(E25)="","",IFERROR(INDEX(Map_Tables!$H$4:$H$37,MATCH(TRIM(E25),Map_Tables!$G$4:$G$37,0)),"CHECK")) -> Burger Barn | AF25: =IF(TRIM(K25)="","Unknown",IFERROR(INDEX(Map_Tables!$E$4:$E$15,MATCH(TRIM(K25),Map_Tables!$D$4:$D$15,0)),"CHECK")) -> UPI | AG25: =IF(LEFT(LOWER(TRIM(L25)),6)="cancel","Cancelled","Delivered") -> Delivered | AH25: =IF(ISNUMBER(SEARCH("/",B25)),DATE(VALUE(RIGHT(B25,4)),VALUE(MID(B25,4,2)),VALUE(LEFT(B25,2))),IF(MID(B25,5,1)="-",DATE(VALUE(LEFT(B25,4)),VALUE(MID(B25,6,2)),VALUE(RIGHT(B25,2))),DATE(VALUE(RIGHT(B25,4)),MATCH(MID(B25,4,3),{"Jan","Feb","Mar","Apr","May","Jun","Jul","Aug","Sep","Oct","Nov","Dec"},0),VALUE(LEFT(B25,2))))) -> 45813
A26: ORD10808 | B26: 2025-04-12 | C26: 21:06 | D26: C0573 | E26: Spice Junction | F26: Bengaluru | G26: North Indian | H26: 2 | I26: 255 | J26: 0 | K26: Cash On Delivery | L26: Delivered | M26: 48 | N26: 3 | O26: =A26&"|"&B26&"|"&C26&"|"&D26&"|"&E26&"|"&F26&"|"&G26&"|"&H26&"|"&I26&"|"&J26&"|"&K26&"|"&L26&"|"&M26&"|"&N26 -> ORD10808|2025-04-12|21:06|C0573|Spice Junction|Bengaluru|North Indian|2|255|0|Cash On Delivery|Delivered|48|3 | P26: =IF(COUNTIF($O$2:O26,O26)>1,"DUP","OK") -> OK | Q26: =COUNTBLANK(A26:N26) -> 0 | R26: =IF(A26="",0,COUNTIFS($A$2:$A$3058,A26,$P$2:$P$3058,"OK")) -> 1 | S26: =IF(OR(A26="",P26="DUP",R26<2),"",IF(Q26=_xlfn.MINIFS($Q$2:$Q$3058,$A$2:$A$3058,A26,$P$2:$P$3058,"OK"),"KEEP","DROP")) | T26: =IF(A26="",1,0) -> 0 | U26: =IF(D26="",1,0) -> 0 | V26: =IF(E26="",1,0) -> 0 | W26: =IF(OR(H26<1,H26>10),1,0) -> 0 | X26: =IF(OR(I26<=0,I26>1500),1,0) -> 0 | Y26: =IF(J26>H26*I26,1,0) -> 0 | Z26: =IF(AND(N26<>"",OR(N26<1,N26>5)),1,0) -> 0 | AA26: =IF(AND(M26<>"",OR(M26<5,M26>180)),1,0) -> 0 | AB26: =IF(P26="DUP","Exact duplicate row",IF(T26=1,"Missing Order ID",IF(S26="DROP","Duplicate Order ID (less complete row)",IF(U26=1,"Missing Customer ID",IF(V26=1,"Missing Restaurant name",IF(W26=1,"Invalid/outlier quantity",IF(X26=1,"Invalid/outlier unit price",IF(Y26=1,"Discount greater than order value","")))))))) | AC26: =IF(AB26="","KEEP","DROP") -> KEEP | AD26: =IF(TRIM(F26)="",IFERROR(INDEX(Map_Tables!$I$4:$I$37,MATCH(TRIM(E26),Map_Tables!$G$4:$G$37,0)),""),IFERROR(INDEX(Map_Tables!$B$4:$B$18,MATCH(TRIM(F26),Map_Tables!$A$4:$A$18,0)),"CHECK")) -> Bengaluru | AE26: =IF(TRIM(E26)="","",IFERROR(INDEX(Map_Tables!$H$4:$H$37,MATCH(TRIM(E26),Map_Tables!$G$4:$G$37,0)),"CHECK")) -> Spice Junction | AF26: =IF(TRIM(K26)="","Unknown",IFERROR(INDEX(Map_Tables!$E$4:$E$15,MATCH(TRIM(K26),Map_Tables!$D$4:$D$15,0)),"CHECK")) -> Cash on Delivery | AG26: =IF(LEFT(LOWER(TRIM(L26)),6)="cancel","Cancelled","Delivered") -> Delivered | AH26: =IF(ISNUMBER(SEARCH("/",B26)),DATE(VALUE(RIGHT(B26,4)),VALUE(MID(B26,4,2)),VALUE(LEFT(B26,2))),IF(MID(B26,5,1)="-",DATE(VALUE(LEFT(B26,4)),VALUE(MID(B26,6,2)),VALUE(RIGHT(B26,2))),DATE(VALUE(RIGHT(B26,4)),MATCH(MID(B26,4,3),{"Jan","Feb","Mar","Apr","May","Jun","Jul","Aug","Sep","Oct","Nov","Dec"},0),VALUE(LEFT(B26,2))))) -> 45759
A27: ORD11496 | B27: 2025-07-13 | C27: 21:58 | D27: C0169 | E27: Misal Mantra | F27: PUNE | G27: Street Food | H27: 1 | I27: 100 | J27: 0 | K27: Debit Card | L27: Delivered | M27: 34 | N27: 3 | O27: =A27&"|"&B27&"|"&C27&"|"&D27&"|"&E27&"|"&F27&"|"&G27&"|"&H27&"|"&I27&"|"&J27&"|"&K27&"|"&L27&"|"&M27&"|"&N27 -> ORD11496|2025-07-13|21:58|C0169|Misal Mantra|PUNE|Street Food|1|100|0|Debit Card|Delivered|34|3 | P27: =IF(COUNTIF($O$2:O27,O27)>1,"DUP","OK") -> OK | Q27: =COUNTBLANK(A27:N27) -> 0 | R27: =IF(A27="",0,COUNTIFS($A$2:$A$3058,A27,$P$2:$P$3058,"OK")) -> 1 | S27: =IF(OR(A27="",P27="DUP",R27<2),"",IF(Q27=_xlfn.MINIFS($Q$2:$Q$3058,$A$2:$A$3058,A27,$P$2:$P$3058,"OK"),"KEEP","DROP")) | T27: =IF(A27="",1,0) -> 0 | U27: =IF(D27="",1,0) -> 0 | V27: =IF(E27="",1,0) -> 0 | W27: =IF(OR(H27<1,H27>10),1,0) -> 0 | X27: =IF(OR(I27<=0,I27>1500),1,0) -> 0 | Y27: =IF(J27>H27*I27,1,0) -> 0 | Z27: =IF(AND(N27<>"",OR(N27<1,N27>5)),1,0) -> 0 | AA27: =IF(AND(M27<>"",OR(M27<5,M27>180)),1,0) -> 0 | AB27: =IF(P27="DUP","Exact duplicate row",IF(T27=1,"Missing Order ID",IF(S27="DROP","Duplicate Order ID (less complete row)",IF(U27=1,"Missing Customer ID",IF(V27=1,"Missing Restaurant name",IF(W27=1,"Invalid/outlier quantity",IF(X27=1,"Invalid/outlier unit price",IF(Y27=1,"Discount greater than order value","")))))))) | AC27: =IF(AB27="","KEEP","DROP") -> KEEP | AD27: =IF(TRIM(F27)="",IFERROR(INDEX(Map_Tables!$I$4:$I$37,MATCH(TRIM(E27),Map_Tables!$G$4:$G$37,0)),""),IFERROR(INDEX(Map_Tables!$B$4:$B$18,MATCH(TRIM(F27),Map_Tables!$A$4:$A$18,0)),"CHECK")) -> Pune | AE27: =IF(TRIM(E27)="","",IFERROR(INDEX(Map_Tables!$H$4:$H$37,MATCH(TRIM(E27),Map_Tables!$G$4:$G$37,0)),"CHECK")) -> Misal Mantra | AF27: =IF(TRIM(K27)="","Unknown",IFERROR(INDEX(Map_Tables!$E$4:$E$15,MATCH(TRIM(K27),Map_Tables!$D$4:$D$15,0)),"CHECK")) -> Debit Card | AG27: =IF(LEFT(LOWER(TRIM(L27)),6)="cancel","Cancelled","Delivered") -> Delivered | AH27: =IF(ISNUMBER(SEARCH("/",B27)),DATE(VALUE(RIGHT(B27,4)),VALUE(MID(B27,4,2)),VALUE(LEFT(B27,2))),IF(MID(B27,5,1)="-",DATE(VALUE(LEFT(B27,4)),VALUE(MID(B27,6,2)),VALUE(RIGHT(B27,2))),DATE(VALUE(RIGHT(B27,4)),MATCH(MID(B27,4,3),{"Jan","Feb","Mar","Apr","May","Jun","Jul","Aug","Sep","Oct","Nov","Dec"},0),VALUE(LEFT(B27,2))))) -> 45851
A28: ORD11903 | B28: 04-Sep-2025 | C28: 20:06 | D28: C1425 | E28: Pune Burger Hub | F28: Pune | G28: Burgers | H28: 3 | I28: 200 | J28: 0 | K28: UPI | L28: Delivered | M28: 32 | O28: =A28&"|"&B28&"|"&C28&"|"&D28&"|"&E28&"|"&F28&"|"&G28&"|"&H28&"|"&I28&"|"&J28&"|"&K28&"|"&L28&"|"&M28&"|"&N28 -> ORD11903|04-Sep-2025|20:06|C1425|Pune Burger Hub|Pune|Burgers|3|200|0|UPI|Delivered|32| | P28: =IF(COUNTIF($O$2:O28,O28)>1,"DUP","OK") -> OK | Q28: =COUNTBLANK(A28:N28) -> 1 | R28: =IF(A28="",0,COUNTIFS($A$2:$A$3058,A28,$P$2:$P$3058,"OK")) -> 1 | S28: =IF(OR(A28="",P28="DUP",R28<2),"",IF(Q28=_xlfn.MINIFS($Q$2:$Q$3058,$A$2:$A$3058,A28,$P$2:$P$3058,"OK"),"KEEP","DROP")) | T28: =IF(A28="",1,0) -> 0 | U28: =IF(D28="",1,0) -> 0 | V28: =IF(E28="",1,0) -> 0 | W28: =IF(OR(H28<1,H28>10),1,0) -> 0 | X28: =IF(OR(I28<=0,I28>1500),1,0) -> 0 | Y28: =IF(J28>H28*I28,1,0) -> 0 | Z28: =IF(AND(N28<>"",OR(N28<1,N28>5)),1,0) -> 0 | AA28: =IF(AND(M28<>"",OR(M28<5,M28>180)),1,0) -> 0 | AB28: =IF(P28="DUP","Exact duplicate row",IF(T28=1,"Missing Order ID",IF(S28="DROP","Duplicate Order ID (less complete row)",IF(U28=1,"Missing Customer ID",IF(V28=1,"Missing Restaurant name",IF(W28=1,"Invalid/outlier quantity",IF(X28=1,"Invalid/outlier unit price",IF(Y28=1,"Discount greater than order value","")))))))) | AC28: =IF(AB28="","KEEP","DROP") -> KEEP | AD28: =IF(TRIM(F28)="",IFERROR(INDEX(Map_Tables!$I$4:$I$37,MATCH(TRIM(E28),Map_Tables!$G$4:$G$37,0)),""),IFERROR(INDEX(Map_Tables!$B$4:$B$18,MATCH(TRIM(F28),Map_Tables!$A$4:$A$18,0)),"CHECK")) -> Pune | AE28: =IF(TRIM(E28)="","",IFERROR(INDEX(Map_Tables!$H$4:$H$37,MATCH(TRIM(E28),Map_Tables!$G$4:$G$37,0)),"CHECK")) -> Pune Burger Hub | AF28: =IF(TRIM(K28)="","Unknown",IFERROR(INDEX(Map_Tables!$E$4:$E$15,MATCH(TRIM(K28),Map_Tables!$D$4:$D$15,0)),"CHECK")) -> UPI | AG28: =IF(LEFT(LOWER(TRIM(L28)),6)="cancel","Cancelled","Delivered") -> Delivered | AH28: =IF(ISNUMBER(SEARCH("/",B28)),DATE(VALUE(RIGHT(B28,4)),VALUE(MID(B28,4,2)),VALUE(LEFT(B28,2))),IF(MID(B28,5,1)="-",DATE(VALUE(LEFT(B28,4)),VALUE(MID(B28,6,2)),VALUE(RIGHT(B28,2))),DATE(VALUE(RIGHT(B28,4)),MATCH(MID(B28,4,3),{"Jan","Feb","Mar","Apr","May","Jun","Jul","Aug","Sep","Oct","Nov","Dec"},0),VALUE(LEFT(B28,2))))) -> 45904
A29: ORD12820 | B29: 2025-12-11 | C29: 19:09 | D29: C1118 | E29: Pizza Palace | F29: Hyd | G29: Pizza | H29: 2 | I29: 315 | J29: 75 | K29: UPI | L29: Delivered | M29: 26 | N29: 5 | O29: =A29&"|"&B29&"|"&C29&"|"&D29&"|"&E29&"|"&F29&"|"&G29&"|"&H29&"|"&I29&"|"&J29&"|"&K29&"|"&L29&"|"&M29&"|"&N29 -> ORD12820|2025-12-11|19:09|C1118|Pizza Palace|Hyd|Pizza|2|315|75|UPI|Delivered|26|5 | P29: =IF(COUNTIF($O$2:O29,O29)>1,"DUP","OK") -> OK | Q29: =COUNTBLANK(A29:N29) -> 0 | R29: =IF(A29="",0,COUNTIFS($A$2:$A$3058,A29,$P$2:$P$3058,"OK")) -> 1 | S29: =IF(OR(A29="",P29="DUP",R29<2),"",IF(Q29=_xlfn.MINIFS($Q$2:$Q$3058,$A$2:$A$3058,A29,$P$2:$P$3058,"OK"),"KEEP","DROP")) | T29: =IF(A29="",1,0) -> 0 | U29: =IF(D29="",1,0) -> 0 | V29: =IF(E29="",1,0) -> 0 | W29: =IF(OR(H29<1,H29>10),1,0) -> 0 | X29: =IF(OR(I29<=0,I29>1500),1,0) -> 0 | Y29: =IF(J29>H29*I29,1,0) -> 0 | Z29: =IF(AND(N29<>"",OR(N29<1,N29>5)),1,0) -> 0 | AA29: =IF(AND(M29<>"",OR(M29<5,M29>180)),1,0) -> 0 | AB29: =IF(P29="DUP","Exact duplicate row",IF(T29=1,"Missing Order ID",IF(S29="DROP","Duplicate Order ID (less complete row)",IF(U29=1,"Missing Customer ID",IF(V29=1,"Missing Restaurant name",IF(W29=1,"Invalid/outlier quantity",IF(X29=1,"Invalid/outlier unit price",IF(Y29=1,"Discount greater than order value","")))))))) | AC29: =IF(AB29="","KEEP","DROP") -> KEEP | AD29: =IF(TRIM(F29)="",IFERROR(INDEX(Map_Tables!$I$4:$I$37,MATCH(TRIM(E29),Map_Tables!$G$4:$G$37,0)),""),IFERROR(INDEX(Map_Tables!$B$4:$B$18,MATCH(TRIM(F29),Map_Tables!$A$4:$A$18,0)),"CHECK")) -> Hyderabad | AE29: =IF(TRIM(E29)="","",IFERROR(INDEX(Map_Tables!$H$4:$H$37,MATCH(TRIM(E29),Map_Tables!$G$4:$G$37,0)),"CHECK")) -> Pizza Palace | AF29: =IF(TRIM(K29)="","Unknown",IFERROR(INDEX(Map_Tables!$E$4:$E$15,MATCH(TRIM(K29),Map_Tables!$D$4:$D$15,0)),"CHECK")) -> UPI | AG29: =IF(LEFT(LOWER(TRIM(L29)),6)="cancel","Cancelled","Delivered") -> Delivered | AH29: =IF(ISNUMBER(SEARCH("/",B29)),DATE(VALUE(RIGHT(B29,4)),VALUE(MID(B29,4,2)),VALUE(LEFT(B29,2))),IF(MID(B29,5,1)="-",DATE(VALUE(LEFT(B29,4)),VALUE(MID(B29,6,2)),VALUE(RIGHT(B29,2))),DATE(VALUE(RIGHT(B29,4)),MATCH(MID(B29,4,3),{"Jan","Feb","Mar","Apr","May","Jun","Jul","Aug","Sep","Oct","Nov","Dec"},0),VALUE(LEFT(B29,2))))) -> 46002
A30: ORD11313 | B30: 19/06/2025 | C30: 14:20 | D30: C0468 | E30: Maratha Thali House | F30: Pune | G30: North Indian | H30: 1 | I30: 255 | J30: 102 | K30: UPI | L30: Delivered | M30: 36 | N30: 5 | O30: =A30&"|"&B30&"|"&C30&"|"&D30&"|"&E30&"|"&F30&"|"&G30&"|"&H30&"|"&I30&"|"&J30&"|"&K30&"|"&L30&"|"&M30&"|"&N30 -> ORD11313|19/06/2025|14:20|C0468|Maratha Thali House|Pune|North Indian|1|255|102|UPI|Delivered|36|5 | P30: =IF(COUNTIF($O$2:O30,O30)>1,"DUP","OK") -> OK | Q30: =COUNTBLANK(A30:N30) -> 0 | R30: =IF(A30="",0,COUNTIFS($A$2:$A$3058,A30,$P$2:$P$3058,"OK")) -> 1 | S30: =IF(OR(A30="",P30="DUP",R30<2),"",IF(Q30=_xlfn.MINIFS($Q$2:$Q$3058,$A$2:$A$3058,A30,$P$2:$P$3058,"OK"),"KEEP","DROP")) | T30: =IF(A30="",1,0) -> 0 | U30: =IF(D30="",1,0) -> 0 | V30: =IF(E30="",1,0) -> 0 | W30: =IF(OR(H30<1,H30>10),1,0) -> 0 | X30: =IF(OR(I30<=0,I30>1500),1,0) -> 0 | Y30: =IF(J30>H30*I30,1,0) -> 0 | Z30: =IF(AND(N30<>"",OR(N30<1,N30>5)),1,0) -> 0 | AA30: =IF(AND(M30<>"",OR(M30<5,M30>180)),1,0) -> 0 | AB30: =IF(P30="DUP","Exact duplicate row",IF(T30=1,"Missing Order ID",IF(S30="DROP","Duplicate Order ID (less complete row)",IF(U30=1,"Missing Customer ID",IF(V30=1,"Missing Restaurant name",IF(W30=1,"Invalid/outlier quantity",IF(X30=1,"Invalid/outlier unit price",IF(Y30=1,"Discount greater than order value","")))))))) | AC30: =IF(AB30="","KEEP","DROP") -> KEEP | AD30: =IF(TRIM(F30)="",IFERROR(INDEX(Map_Tables!$I$4:$I$37,MATCH(TRIM(E30),Map_Tables!$G$4:$G$37,0)),""),IFERROR(INDEX(Map_Tables!$B$4:$B$18,MATCH(TRIM(F30),Map_Tables!$A$4:$A$18,0)),"CHECK")) -> Pune | AE30: =IF(TRIM(E30)="","",IFERROR(INDEX(Map_Tables!$H$4:$H$37,MATCH(TRIM(E30),Map_Tables!$G$4:$G$37,0)),"CHECK")) -> Maratha Thali House | AF30: =IF(TRIM(K30)="","Unknown",IFERROR(INDEX(Map_Tables!$E$4:$E$15,MATCH(TRIM(K30),Map_Tables!$D$4:$D$15,0)),"CHECK")) -> UPI | AG30: =IF(LEFT(LOWER(TRIM(L30)),6)="cancel","Cancelled","Delivered") -> Delivered | AH30: =IF(ISNUMBER(SEARCH("/",B30)),DATE(VALUE(RIGHT(B30,4)),VALUE(MID(B30,4,2)),VALUE(LEFT(B30,2))),IF(MID(B30,5,1)="-",DATE(VALUE(LEFT(B30,4)),VALUE(MID(B30,6,2)),VALUE(RIGHT(B30,2))),DATE(VALUE(RIGHT(B30,4)),MATCH(MID(B30,4,3),{"Jan","Feb","Mar","Apr","May","Jun","Jul","Aug","Sep","Oct","Nov","Dec"},0),VALUE(LEFT(B30,2))))) -> 45827
A31: ORD10753 | B31: 2025-04-05 | C31: 21:52 | D31: C0094 | E31: Madras Biryani Co | F31: Chennai | G31: Biryani | H31: 2 | I31: 295 | J31: 0 | K31: Credit Card | L31: Delivered | M31: 33 | N31: 5 | O31: =A31&"|"&B31&"|"&C31&"|"&D31&"|"&E31&"|"&F31&"|"&G31&"|"&H31&"|"&I31&"|"&J31&"|"&K31&"|"&L31&"|"&M31&"|"&N31 -> ORD10753|2025-04-05|21:52|C0094|Madras Biryani Co|Chennai|Biryani|2|295|0|Credit Card|Delivered|33|5 | P31: =IF(COUNTIF($O$2:O31,O31)>1,"DUP","OK") -> OK | Q31: =COUNTBLANK(A31:N31) -> 0 | R31: =IF(A31="",0,COUNTIFS($A$2:$A$3058,A31,$P$2:$P$3058,"OK")) -> 1 | S31: =IF(OR(A31="",P31="DUP",R31<2),"",IF(Q31=_xlfn.MINIFS($Q$2:$Q$3058,$A$2:$A$3058,A31,$P$2:$P$3058,"OK"),"KEEP","DROP")) | T31: =IF(A31="",1,0) -> 0 | U31: =IF(D31="",1,0) -> 0 | V31: =IF(E31="",1,0) -> 0 | W31: =IF(OR(H31<1,H31>10),1,0) -> 0 | X31: =IF(OR(I31<=0,I31>1500),1,0) -> 0 | Y31: =IF(J31>H31*I31,1,0) -> 0 | Z31: =IF(AND(N31<>"",OR(N31<1,N31>5)),1,0) -> 0 | AA31: =IF(AND(M31<>"",OR(M31<5,M31>180)),1,0) -> 0 | AB31: =IF(P31="DUP","Exact duplicate row",IF(T31=1,"Missing Order ID",IF(S31="DROP","Duplicate Order ID (less complete row)",IF(U31=1,"Missing Customer ID",IF(V31=1,"Missing Restaurant name",IF(W31=1,"Invalid/outlier quantity",IF(X31=1,"Invalid/outlier unit price",IF(Y31=1,"Discount greater than order value","")))))))) | AC31: =IF(AB31="","KEEP","DROP") -> KEEP | AD31: =IF(TRIM(F31)="",IFERROR(INDEX(Map_Tables!$I$4:$I$37,MATCH(TRIM(E31),Map_Tables!$G$4:$G$37,0)),""),IFERROR(INDEX(Map_Tables!$B$4:$B$18,MATCH(TRIM(F31),Map_Tables!$A$4:$A$18,0)),"CHECK")) -> Chennai | AE31: =IF(TRIM(E31)="","",IFERROR(INDEX(Map_Tables!$H$4:$H$37,MATCH(TRIM(E31),Map_Tables!$G$4:$G$37,0)),"CHECK")) -> Madras Biryani Co | AF31: =IF(TRIM(K31)="","Unknown",IFERROR(INDEX(Map_Tables!$E$4:$E$15,MATCH(TRIM(K31),Map_Tables!$D$4:$D$15,0)),"CHECK")) -> Credit Card | AG31: =IF(LEFT(LOWER(TRIM(L31)),6)="cancel","Cancelled","Delivered") -> Delivered | AH31: =IF(ISNUMBER(SEARCH("/",B31)),DATE(VALUE(RIGHT(B31,4)),VALUE(MID(B31,4,2)),VALUE(LEFT(B31,2))),IF(MID(B31,5,1)="-",DATE(VALUE(LEFT(B31,4)),VALUE(MID(B31,6,2)),VALUE(RIGHT(B31,2))),DATE(VALUE(RIGHT(B31,4)),MATCH(MID(B31,4,3),{"Jan","Feb","Mar","Apr","May","Jun","Jul","Aug","Sep","Oct","Nov","Dec"},0),VALUE(LEFT(B31,2))))) -> 45752
A32: ORD11052 | B32: 2025-05-13 | C32: 08:25 | D32: C1126 | E32: Maratha Thali House | F32: Pune | G32: North Indian | H32: 2 | I32: 245 | J32: 125 | K32: Cash on Delivery | L32: Delivered | M32: 33 | N32: 4 | O32: =A32&"|"&B32&"|"&C32&"|"&D32&"|"&E32&"|"&F32&"|"&G32&"|"&H32&"|"&I32&"|"&J32&"|"&K32&"|"&L32&"|"&M32&"|"&N32 -> ORD11052|2025-05-13|08:25|C1126|Maratha Thali House|Pune|North Indian|2|245|125|Cash on Delivery|Delivered|33|4 | P32: =IF(COUNTIF($O$2:O32,O32)>1,"DUP","OK") -> OK | Q32: =COUNTBLANK(A32:N32) -> 0 | R32: =IF(A32="",0,COUNTIFS($A$2:$A$3058,A32,$P$2:$P$3058,"OK")) -> 1 | S32: =IF(OR(A32="",P32="DUP",R32<2),"",IF(Q32=_xlfn.MINIFS($Q$2:$Q$3058,$A$2:$A$3058,A32,$P$2:$P$3058,"OK"),"KEEP","DROP")) | T32: =IF(A32="",1,0) -> 0 | U32: =IF(D32="",1,0) -> 0 | V32: =IF(E32="",1,0) -> 0 | W32: =IF(OR(H32<1,H32>10),1,0) -> 0 | X32: =IF(OR(I32<=0,I32>1500),1,0) -> 0 | Y32: =IF(J32>H32*I32,1,0) -> 0 | Z32: =IF(AND(N32<>"",OR(N32<1,N32>5)),1,0) -> 0 | AA32: =IF(AND(M32<>"",OR(M32<5,M32>180)),1,0) -> 0 | AB32: =IF(P32="DUP","Exact duplicate row",IF(T32=1,"Missing Order ID",IF(S32="DROP","Duplicate Order ID (less complete row)",IF(U32=1,"Missing Customer ID",IF(V32=1,"Missing Restaurant name",IF(W32=1,"Invalid/outlier quantity",IF(X32=1,"Invalid/outlier unit price",IF(Y32=1,"Discount greater than order value","")))))))) | AC32: =IF(AB32="","KEEP","DROP") -> KEEP | AD32: =IF(TRIM(F32)="",IFERROR(INDEX(Map_Tables!$I$4:$I$37,MATCH(TRIM(E32),Map_Tables!$G$4:$G$37,0)),""),IFERROR(INDEX(Map_Tables!$B$4:$B$18,MATCH(TRIM(F32),Map_Tables!$A$4:$A$18,0)),"CHECK")) -> Pune | AE32: =IF(TRIM(E32)="","",IFERROR(INDEX(Map_Tables!$H$4:$H$37,MATCH(TRIM(E32),Map_Tables!$G$4:$G$37,0)),"CHECK")) -> Maratha Thali House | AF32: =IF(TRIM(K32)="","Unknown",IFERROR(INDEX(Map_Tables!$E$4:$E$15,MATCH(TRIM(K32),Map_Tables!$D$4:$D$15,0)),"CHECK")) -> Cash on Delivery | AG32: =IF(LEFT(LOWER(TRIM(L32)),6)="cancel","Cancelled","Delivered") -> Delivered | AH32: =IF(ISNUMBER(SEARCH("/",B32)),DATE(VALUE(RIGHT(B32,4)),VALUE(MID(B32,4,2)),VALUE(LEFT(B32,2))),IF(MID(B32,5,1)="-",DATE(VALUE(LEFT(B32,4)),VALUE(MID(B32,6,2)),VALUE(RIGHT(B32,2))),DATE(VALUE(RIGHT(B32,4)),MATCH(MID(B32,4,3),{"Jan","Feb","Mar","Apr","May","Jun","Jul","Aug","Sep","Oct","Nov","Dec"},0),VALUE(LEFT(B32,2))))) -> 45790
A33: ORD12433 | B33: 2025-11-02 | C33: 19:10 | D33: C0516 | E33: Andhra Meals Mess | F33: Hyderabad | G33: South Indian | H33: 3 | I33: 150 | J33: 0 | K33: UPI | L33: Delivered | M33: 40 | N33: 3 | O33: =A33&"|"&B33&"|"&C33&"|"&D33&"|"&E33&"|"&F33&"|"&G33&"|"&H33&"|"&I33&"|"&J33&"|"&K33&"|"&L33&"|"&M33&"|"&N33 -> ORD12433|2025-11-02|19:10|C0516|Andhra Meals Mess|Hyderabad|South Indian|3|150|0|UPI|Delivered|40|3 | P33: =IF(COUNTIF($O$2:O33,O33)>1,"DUP","OK") -> OK | Q33: =COUNTBLANK(A33:N33) -> 0 | R33: =IF(A33="",0,COUNTIFS($A$2:$A$3058,A33,$P$2:$P$3058,"OK")) -> 1 | S33: =IF(OR(A33="",P33="DUP",R33<2),"",IF(Q33=_xlfn.MINIFS($Q$2:$Q$3058,$A$2:$A$3058,A33,$P$2:$P$3058,"OK"),"KEEP","DROP")) | T33: =IF(A33="",1,0) -> 0 | U33: =IF(D33="",1,0) -> 0 | V33: =IF(E33="",1,0) -> 0 | W33: =IF(OR(H33<1,H33>10),1,0) -> 0 | X33: =IF(OR(I33<=0,I33>1500),1,0) -> 0 | Y33: =IF(J33>H33*I33,1,0) -> 0 | Z33: =IF(AND(N33<>"",OR(N33<1,N33>5)),1,0) -> 0 | AA33: =IF(AND(M33<>"",OR(M33<5,M33>180)),1,0) -> 0 | AB33: =IF(P33="DUP","Exact duplicate row",IF(T33=1,"Missing Order ID",IF(S33="DROP","Duplicate Order ID (less complete row)",IF(U33=1,"Missing Customer ID",IF(V33=1,"Missing Restaurant name",IF(W33=1,"Invalid/outlier quantity",IF(X33=1,"Invalid/outlier unit price",IF(Y33=1,"Discount greater than order value","")))))))) | AC33: =IF(AB33="","KEEP","DROP") -> KEEP | AD33: =IF(TRIM(F33)="",IFERROR(INDEX(Map_Tables!$I$4:$I$37,MATCH(TRIM(E33),Map_Tables!$G$4:$G$37,0)),""),IFERROR(INDEX(Map_Tables!$B$4:$B$18,MATCH(TRIM(F33),Map_Tables!$A$4:$A$18,0)),"CHECK")) -> Hyderabad | AE33: =IF(TRIM(E33)="","",IFERROR(INDEX(Map_Tables!$H$4:$H$37,MATCH(TRIM(E33),Map_Tables!$G$4:$G$37,0)),"CHECK")) -> Andhra Meals Mess | AF33: =IF(TRIM(K33)="","Unknown",IFERROR(INDEX(Map_Tables!$E$4:$E$15,MATCH(TRIM(K33),Map_Tables!$D$4:$D$15,0)),"CHECK")) -> UPI | AG33: =IF(LEFT(LOWER(TRIM(L33)),6)="cancel","Cancelled","Delivered") -> Delivered | AH33: =IF(ISNUMBER(SEARCH("/",B33)),DATE(VALUE(RIGHT(B33,4)),VALUE(MID(B33,4,2)),VALUE(LEFT(B33,2))),IF(MID(B33,5,1)="-",DATE(VALUE(LEFT(B33,4)),VALUE(MID(B33,6,2)),VALUE(RIGHT(B33,2))),DATE(VALUE(RIGHT(B33,4)),MATCH(MID(B33,4,3),{"Jan","Feb","Mar","Apr","May","Jun","Jul","Aug","Sep","Oct","Nov","Dec"},0),VALUE(LEFT(B33,2))))) -> 45963
A34: ORD12841 | B34: 2025-12-13 | C34: 22:04 | D34: C1296 | E34: Nawabi Biryani House | F34: Bengaluru | G34: Biryani | H34: 1 | I34: 270 | J34: 0 | K34: UPI | L34: Delivered | M34: 40 | N34: 5 | O34: =A34&"|"&B34&"|"&C34&"|"&D34&"|"&E34&"|"&F34&"|"&G34&"|"&H34&"|"&I34&"|"&J34&"|"&K34&"|"&L34&"|"&M34&"|"&N34 -> ORD12841|2025-12-13|22:04|C1296|Nawabi Biryani House|Bengaluru|Biryani|1|270|0|UPI|Delivered|40|5 | P34: =IF(COUNTIF($O$2:O34,O34)>1,"DUP","OK") -> OK | Q34: =COUNTBLANK(A34:N34) -> 0 | R34: =IF(A34="",0,COUNTIFS($A$2:$A$3058,A34,$P$2:$P$3058,"OK")) -> 1 | S34: =IF(OR(A34="",P34="DUP",R34<2),"",IF(Q34=_xlfn.MINIFS($Q$2:$Q$3058,$A$2:$A$3058,A34,$P$2:$P$3058,"OK"),"KEEP","DROP")) | T34: =IF(A34="",1,0) -> 0 | U34: =IF(D34="",1,0) -> 0 | V34: =IF(E34="",1,0) -> 0 | W34: =IF(OR(H34<1,H34>10),1,0) -> 0 | X34: =IF(OR(I34<=0,I34>1500),1,0) -> 0 | Y34: =IF(J34>H34*I34,1,0) -> 0 | Z34: =IF(AND(N34<>"",OR(N34<1,N34>5)),1,0) -> 0 | AA34: =IF(AND(M34<>"",OR(M34<5,M34>180)),1,0) -> 0 | AB34: =IF(P34="DUP","Exact duplicate row",IF(T34=1,"Missing Order ID",IF(S34="DROP","Duplicate Order ID (less complete row)",IF(U34=1,"Missing Customer ID",IF(V34=1,"Missing Restaurant name",IF(W34=1,"Invalid/outlier quantity",IF(X34=1,"Invalid/outlier unit price",IF(Y34=1,"Discount greater than order value","")))))))) | AC34: =IF(AB34="","KEEP","DROP") -> KEEP | AD34: =IF(TRIM(F34)="",IFERROR(INDEX(Map_Tables!$I$4:$I$37,MATCH(TRIM(E34),Map_Tables!$G$4:$G$37,0)),""),IFERROR(INDEX(Map_Tables!$B$4:$B$18,MATCH(TRIM(F34),Map_Tables!$A$4:$A$18,0)),"CHECK")) -> Bengaluru | AE34: =IF(TRIM(E34)="","",IFERROR(INDEX(Map_Tables!$H$4:$H$37,MATCH(TRIM(E34),Map_Tables!$G$4:$G$37,0)),"CHECK")) -> Nawabi Biryani House | AF34: =IF(TRIM(K34)="","Unknown",IFERROR(INDEX(Map_Tables!$E$4:$E$15,MATCH(TRIM(K34),Map_Tables!$D$4:$D$15,0)),"CHECK")) -> UPI | AG34: =IF(LEFT(LOWER(TRIM(L34)),6)="cancel","Cancelled","Delivered") -> Delivered | AH34: =IF(ISNUMBER(SEARCH("/",B34)),DATE(VALUE(RIGHT(B34,4)),VALUE(MID(B34,4,2)),VALUE(LEFT(B34,2))),IF(MID(B34,5,1)="-",DATE(VALUE(LEFT(B34,4)),VALUE(MID(B34,6,2)),VALUE(RIGHT(B34,2))),DATE(VALUE(RIGHT(B34,4)),MATCH(MID(B34,4,3),{"Jan","Feb","Mar","Apr","May","Jun","Jul","Aug","Sep","Oct","Nov","Dec"},0),VALUE(LEFT(B34,2))))) -> 46004
A35: ORD10297 | B35: 2025-02-09 | C35: 20:16 | D35: C1223 | E35: Filter Coffee & Tiffin | F35: Chennai | G35: South Indian | H35: 2 | I35: 85 | J35: 68 | K35: UPI | L35: Delivered | M35: 44 | N35: 3 | O35: =A35&"|"&B35&"|"&C35&"|"&D35&"|"&E35&"|"&F35&"|"&G35&"|"&H35&"|"&I35&"|"&J35&"|"&K35&"|"&L35&"|"&M35&"|"&N35 -> ORD10297|2025-02-09|20:16|C1223|Filter Coffee & Tiffin|Chennai|South Indian|2|85|68|UPI|Delivered|44|3 | P35: =IF(COUNTIF($O$2:O35,O35)>1,"DUP","OK") -> OK | Q35: =COUNTBLANK(A35:N35) -> 0 | R35: =IF(A35="",0,COUNTIFS($A$2:$A$3058,A35,$P$2:$P$3058,"OK")) -> 1 | S35: =IF(OR(A35="",P35="DUP",R35<2),"",IF(Q35=_xlfn.MINIFS($Q$2:$Q$3058,$A$2:$A$3058,A35,$P$2:$P$3058,"OK"),"KEEP","DROP")) | T35: =IF(A35="",1,0) -> 0 | U35: =IF(D35="",1,0) -> 0 | V35: =IF(E35="",1,0) -> 0 | W35: =IF(OR(H35<1,H35>10),1,0) -> 0 | X35: =IF(OR(I35<=0,I35>1500),1,0) -> 0 | Y35: =IF(J35>H35*I35,1,0) -> 0 | Z35: =IF(AND(N35<>"",OR(N35<1,N35>5)),1,0) -> 0 | AA35: =IF(AND(M35<>"",OR(M35<5,M35>180)),1,0) -> 0 | AB35: =IF(P35="DUP","Exact duplicate row",IF(T35=1,"Missing Order ID",IF(S35="DROP","Duplicate Order ID (less complete row)",IF(U35=1,"Missing Customer ID",IF(V35=1,"Missing Restaurant name",IF(W35=1,"Invalid/outlier quantity",IF(X35=1,"Invalid/outlier unit price",IF(Y35=1,"Discount greater than order value","")))))))) | AC35: =IF(AB35="","KEEP","DROP") -> KEEP | AD35: =IF(TRIM(F35)="",IFERROR(INDEX(Map_Tables!$I$4:$I$37,MATCH(TRIM(E35),Map_Tables!$G$4:$G$37,0)),""),IFERROR(INDEX(Map_Tables!$B$4:$B$18,MATCH(TRIM(F35),Map_Tables!$A$4:$A$18,0)),"CHECK")) -> Chennai | AE35: =IF(TRIM(E35)="","",IFERROR(INDEX(Map_Tables!$H$4:$H$37,MATCH(TRIM(E35),Map_Tables!$G$4:$G$37,0)),"CHECK")) -> Filter Coffee & Tiffin | AF35: =IF(TRIM(K35)="","Unknown",IFERROR(INDEX(Map_Tables!$E$4:$E$15,MATCH(TRIM(K35),Map_Tables!$D$4:$D$15,0)),"CHECK")) -> UPI | AG35: =IF(LEFT(LOWER(TRIM(L35)),6)="cancel","Cancelled","Delivered") -> Delivered | AH35: =IF(ISNUMBER(SEARCH("/",B35)),DATE(VALUE(RIGHT(B35,4)),VALUE(MID(B35,4,2)),VALUE(LEFT(B35,2))),IF(MID(B35,5,1)="-",DATE(VALUE(LEFT(B35,4)),VALUE(MID(B35,6,2)),VALUE(RIGHT(B35,2))),DATE(VALUE(RIGHT(B35,4)),MATCH(MID(B35,4,3),{"Jan","Feb","Mar","Apr","May","Jun","Jul","Aug","Sep","Oct","Nov","Dec"},0),VALUE(LEFT(B35,2))))) -> 45697
A36: ORD12146 | B36: 2025-10-02 | C36: 09:42 | D36: C0245 | E36: Spice Junction | F36: Bengaluru | G36: North Indian | H36: 2 | I36: 240 | J36: 75 | K36: Wallet | L36: Delivered | M36: 30 | O36: =A36&"|"&B36&"|"&C36&"|"&D36&"|"&E36&"|"&F36&"|"&G36&"|"&H36&"|"&I36&"|"&J36&"|"&K36&"|"&L36&"|"&M36&"|"&N36 -> ORD12146|2025-10-02|09:42|C0245|Spice Junction|Bengaluru|North Indian|2|240|75|Wallet|Delivered|30| | P36: =IF(COUNTIF($O$2:O36,O36)>1,"DUP","OK") -> OK | Q36: =COUNTBLANK(A36:N36) -> 1 | R36: =IF(A36="",0,COUNTIFS($A$2:$A$3058,A36,$P$2:$P$3058,"OK")) -> 1 | S36: =IF(OR(A36="",P36="DUP",R36<2),"",IF(Q36=_xlfn.MINIFS($Q$2:$Q$3058,$A$2:$A$3058,A36,$P$2:$P$3058,"OK"),"KEEP","DROP")) | T36: =IF(A36="",1,0) -> 0 | U36: =IF(D36="",1,0) -> 0 | V36: =IF(E36="",1,0) -> 0 | W36: =IF(OR(H36<1,H36>10),1,0) -> 0 | X36: =IF(OR(I36<=0,I36>1500),1,0) -> 0 | Y36: =IF(J36>H36*I36,1,0) -> 0 | Z36: =IF(AND(N36<>"",OR(N36<1,N36>5)),1,0) -> 0 | AA36: =IF(AND(M36<>"",OR(M36<5,M36>180)),1,0) -> 0 | AB36: =IF(P36="DUP","Exact duplicate row",IF(T36=1,"Missing Order ID",IF(S36="DROP","Duplicate Order ID (less complete row)",IF(U36=1,"Missing Customer ID",IF(V36=1,"Missing Restaurant name",IF(W36=1,"Invalid/outlier quantity",IF(X36=1,"Invalid/outlier unit price",IF(Y36=1,"Discount greater than order value","")))))))) | AC36: =IF(AB36="","KEEP","DROP") -> KEEP | AD36: =IF(TRIM(F36)="",IFERROR(INDEX(Map_Tables!$I$4:$I$37,MATCH(TRIM(E36),Map_Tables!$G$4:$G$37,0)),""),IFERROR(INDEX(Map_Tables!$B$4:$B$18,MATCH(TRIM(F36),Map_Tables!$A$4:$A$18,0)),"CHECK")) -> Bengaluru | AE36: =IF(TRIM(E36)="","",IFERROR(INDEX(Map_Tables!$H$4:$H$37,MATCH(TRIM(E36),Map_Tables!$G$4:$G$37,0)),"CHECK")) -> Spice Junction | AF36: =IF(TRIM(K36)="","Unknown",IFERROR(INDEX(Map_Tables!$E$4:$E$15,MATCH(TRIM(K36),Map_Tables!$D$4:$D$15,0)),"CHECK")) -> Wallet | AG36: =IF(LEFT(LOWER(TRIM(L36)),6)="cancel","Cancelled","Delivered") -> Delivered | AH36: =IF(ISNUMBER(SEARCH("/",B36)),DATE(VALUE(RIGHT(B36,4)),VALUE(MID(B36,4,2)),VALUE(LEFT(B36,2))),IF(MID(B36,5,1)="-",DATE(VALUE(LEFT(B36,4)),VALUE(MID(B36,6,2)),VALUE(RIGHT(B36,2))),DATE(VALUE(RIGHT(B36,4)),MATCH(MID(B36,4,3),{"Jan","Feb","Mar","Apr","May","Jun","Jul","Aug","Sep","Oct","Nov","Dec"},0),VALUE(LEFT(B36,2))))) -> 45932
A37: ORD10319 | B37: 2025-02-12 | C37: 09:57 | D37: C0999 | E37: Chaat Corner | F37: Delhi | G37: Street Food | H37: 2 | I37: 110 | J37: 50 | K37: Cash on Delivery | L37: Delivered | M37: 42 | N37: 5 | O37: =A37&"|"&B37&"|"&C37&"|"&D37&"|"&E37&"|"&F37&"|"&G37&"|"&H37&"|"&I37&"|"&J37&"|"&K37&"|"&L37&"|"&M37&"|"&N37 -> ORD10319|2025-02-12|09:57|C0999|Chaat Corner|Delhi|Street Food|2|110|50|Cash on Delivery|Delivered|42|5 | P37: =IF(COUNTIF($O$2:O37,O37)>1,"DUP","OK") -> OK | Q37: =COUNTBLANK(A37:N37) -> 0 | R37: =IF(A37="",0,COUNTIFS($A$2:$A$3058,A37,$P$2:$P$3058,"OK")) -> 1 | S37: =IF(OR(A37="",P37="DUP",R37<2),"",IF(Q37=_xlfn.MINIFS($Q$2:$Q$3058,$A$2:$A$3058,A37,$P$2:$P$3058,"OK"),"KEEP","DROP")) | T37: =IF(A37="",1,0) -> 0 | U37: =IF(D37="",1,0) -> 0 | V37: =IF(E37="",1,0) -> 0 | W37: =IF(OR(H37<1,H37>10),1,0) -> 0 | X37: =IF(OR(I37<=0,I37>1500),1,0) -> 0 | Y37: =IF(J37>H37*I37,1,0) -> 0 | Z37: =IF(AND(N37<>"",OR(N37<1,N37>5)),1,0) -> 0 | AA37: =IF(AND(M37<>"",OR(M37<5,M37>180)),1,0) -> 0 | AB37: =IF(P37="DUP","Exact duplicate row",IF(T37=1,"Missing Order ID",IF(S37="DROP","Duplicate Order ID (less complete row)",IF(U37=1,"Missing Customer ID",IF(V37=1,"Missing Restaurant name",IF(W37=1,"Invalid/outlier quantity",IF(X37=1,"Invalid/outlier unit price",IF(Y37=1,"Discount greater than order value","")))))))) | AC37: =IF(AB37="","KEEP","DROP") -> KEEP | AD37: =IF(TRIM(F37)="",IFERROR(INDEX(Map_Tables!$I$4:$I$37,MATCH(TRIM(E37),Map_Tables!$G$4:$G$37,0)),""),IFERROR(INDEX(Map_Tables!$B$4:$B$18,MATCH(TRIM(F37),Map_Tables!$A$4:$A$18,0)),"CHECK")) -> Delhi | AE37: =IF(TRIM(E37)="","",IFERROR(INDEX(Map_Tables!$H$4:$H$37,MATCH(TRIM(E37),Map_Tables!$G$4:$G$37,0)),"CHECK")) -> Chaat Corner | AF37: =IF(TRIM(K37)="","Unknown",IFERROR(INDEX(Map_Tables!$E$4:$E$15,MATCH(TRIM(K37),Map_Tables!$D$4:$D$15,0)),"CHECK")) -> Cash on Delivery | AG37: =IF(LEFT(LOWER(TRIM(L37)),6)="cancel","Cancelled","Delivered") -> Delivered | AH37: =IF(ISNUMBER(SEARCH("/",B37)),DATE(VALUE(RIGHT(B37,4)),VALUE(MID(B37,4,2)),VALUE(LEFT(B37,2))),IF(MID(B37,5,1)="-",DATE(VALUE(LEFT(B37,4)),VALUE(MID(B37,6,2)),VALUE(RIGHT(B37,2))),DATE(VALUE(RIGHT(B37,4)),MATCH(MID(B37,4,3),{"Jan","Feb","Mar","Apr","May","Jun","Jul","Aug","Sep","Oct","Nov","Dec"},0),VALUE(LEFT(B37,2))))) -> 45700
A38: ORD10890 | B38: 2025-04-22 | C38: 19:18 | D38: C1497 | E38: CAKE WALK | F38: Pune | G38: Desserts | H38: 1 | I38: 180 | J38: 72 | K38: Debit Card | L38: Delivered | M38: 36 | N38: 4 | O38: =A38&"|"&B38&"|"&C38&"|"&D38&"|"&E38&"|"&F38&"|"&G38&"|"&H38&"|"&I38&"|"&J38&"|"&K38&"|"&L38&"|"&M38&"|"&N38 -> ORD10890|2025-04-22|19:18|C1497|CAKE WALK|Pune|Desserts|1|180|72|Debit Card|Delivered|36|4 | P38: =IF(COUNTIF($O$2:O38,O38)>1,"DUP","OK") -> OK | Q38: =COUNTBLANK(A38:N38) -> 0 | R38: =IF(A38="",0,COUNTIFS($A$2:$A$3058,A38,$P$2:$P$3058,"OK")) -> 1 | S38: =IF(OR(A38="",P38="DUP",R38<2),"",IF(Q38=_xlfn.MINIFS($Q$2:$Q$3058,$A$2:$A$3058,A38,$P$2:$P$3058,"OK"),"KEEP","DROP")) | T38: =IF(A38="",1,0) -> 0 | U38: =IF(D38="",1,0) -> 0 | V38: =IF(E38="",1,0) -> 0 | W38: =IF(OR(H38<1,H38>10),1,0) -> 0 | X38: =IF(OR(I38<=0,I38>1500),1,0) -> 0 | Y38: =IF(J38>H38*I38,1,0) -> 0 | Z38: =IF(AND(N38<>"",OR(N38<1,N38>5)),1,0) -> 0 | AA38: =IF(AND(M38<>"",OR(M38<5,M38>180)),1,0) -> 0 | AB38: =IF(P38="DUP","Exact duplicate row",IF(T38=1,"Missing Order ID",IF(S38="DROP","Duplicate Order ID (less complete row)",IF(U38=1,"Missing Customer ID",IF(V38=1,"Missing Restaurant name",IF(W38=1,"Invalid/outlier quantity",IF(X38=1,"Invalid/outlier unit price",IF(Y38=1,"Discount greater than order value","")))))))) | AC38: =IF(AB38="","KEEP","DROP") -> KEEP | AD38: =IF(TRIM(F38)="",IFERROR(INDEX(Map_Tables!$I$4:$I$37,MATCH(TRIM(E38),Map_Tables!$G$4:$G$37,0)),""),IFERROR(INDEX(Map_Tables!$B$4:$B$18,MATCH(TRIM(F38),Map_Tables!$A$4:$A$18,0)),"CHECK")) -> Pune | AE38: =IF(TRIM(E38)="","",IFERROR(INDEX(Map_Tables!$H$4:$H$37,MATCH(TRIM(E38),Map_Tables!$G$4:$G$37,0)),"CHECK")) -> Cake Walk | AF38: =IF(TRIM(K38)="","Unknown",IFERROR(INDEX(Map_Tables!$E$4:$E$15,MATCH(TRIM(K38),Map_Tables!$D$4:$D$15,0)),"CHECK")) -> Debit Card | AG38: =IF(LEFT(LOWER(TRIM(L38)),6)="cancel","Cancelled","Delivered") -> Delivered | AH38: =IF(ISNUMBER(SEARCH("/",B38)),DATE(VALUE(RIGHT(B38,4)),VALUE(MID(B38,4,2)),VALUE(LEFT(B38,2))),IF(MID(B38,5,1)="-",DATE(VALUE(LEFT(B38,4)),VALUE(MID(B38,6,2)),VALUE(RIGHT(B38,2))),DATE(VALUE(RIGHT(B38,4)),MATCH(MID(B38,4,3),{"Jan","Feb","Mar","Apr","May","Jun","Jul","Aug","Sep","Oct","Nov","Dec"},0),VALUE(LEFT(B38,2))))) -> 45769
A39: ORD10700 | B39: 2025-03-29 | C39: 18:14 | D39: C1259 | E39: Dosa Darbar | F39: Bengaluru | G39: South Indian | H39: 1 | I39: 105 | J39: 0 | K39: UPI | L39: Delivered | M39: 36 | N39: 3 | O39: =A39&"|"&B39&"|"&C39&"|"&D39&"|"&E39&"|"&F39&"|"&G39&"|"&H39&"|"&I39&"|"&J39&"|"&K39&"|"&L39&"|"&M39&"|"&N39 -> ORD10700|2025-03-29|18:14|C1259|Dosa Darbar |Bengaluru|South Indian|1|105|0|UPI|Delivered|36|3 | P39: =IF(COUNTIF($O$2:O39,O39)>1,"DUP","OK") -> OK | Q39: =COUNTBLANK(A39:N39) -> 0 | R39: =IF(A39="",0,COUNTIFS($A$2:$A$3058,A39,$P$2:$P$3058,"OK")) -> 1 | S39: =IF(OR(A39="",P39="DUP",R39<2),"",IF(Q39=_xlfn.MINIFS($Q$2:$Q$3058,$A$2:$A$3058,A39,$P$2:$P$3058,"OK"),"KEEP","DROP")) | T39: =IF(A39="",1,0) -> 0 | U39: =IF(D39="",1,0) -> 0 | V39: =IF(E39="",1,0) -> 0 | W39: =IF(OR(H39<1,H39>10),1,0) -> 0 | X39: =IF(OR(I39<=0,I39>1500),1,0) -> 0 | Y39: =IF(J39>H39*I39,1,0) -> 0 | Z39: =IF(AND(N39<>"",OR(N39<1,N39>5)),1,0) -> 0 | AA39: =IF(AND(M39<>"",OR(M39<5,M39>180)),1,0) -> 0 | AB39: =IF(P39="DUP","Exact duplicate row",IF(T39=1,"Missing Order ID",IF(S39="DROP","Duplicate Order ID (less complete row)",IF(U39=1,"Missing Customer ID",IF(V39=1,"Missing Restaurant name",IF(W39=1,"Invalid/outlier quantity",IF(X39=1,"Invalid/outlier unit price",IF(Y39=1,"Discount greater than order value","")))))))) | AC39: =IF(AB39="","KEEP","DROP") -> KEEP | AD39: =IF(TRIM(F39)="",IFERROR(INDEX(Map_Tables!$I$4:$I$37,MATCH(TRIM(E39),Map_Tables!$G$4:$G$37,0)),""),IFERROR(INDEX(Map_Tables!$B$4:$B$18,MATCH(TRIM(F39),Map_Tables!$A$4:$A$18,0)),"CHECK")) -> Bengaluru | AE39: =IF(TRIM(E39)="","",IFERROR(INDEX(Map_Tables!$H$4:$H$37,MATCH(TRIM(E39),Map_Tables!$G$4:$G$37,0)),"CHECK")) -> Dosa Darbar | AF39: =IF(TRIM(K39)="","Unknown",IFERROR(INDEX(Map_Tables!$E$4:$E$15,MATCH(TRIM(K39),Map_Tables!$D$4:$D$15,0)),"CHECK")) -> UPI | AG39: =IF(LEFT(LOWER(TRIM(L39)),6)="cancel","Cancelled","Delivered") -> Delivered | AH39: =IF(ISNUMBER(SEARCH("/",B39)),DATE(VALUE(RIGHT(B39,4)),VALUE(MID(B39,4,2)),VALUE(LEFT(B39,2))),IF(MID(B39,5,1)="-",DATE(VALUE(LEFT(B39,4)),VALUE(MID(B39,6,2)),VALUE(RIGHT(B39,2))),DATE(VALUE(RIGHT(B39,4)),MATCH(MID(B39,4,3),{"Jan","Feb","Mar","Apr","May","Jun","Jul","Aug","Sep","Oct","Nov","Dec"},0),VALUE(LEFT(B39,2))))) -> 45745
A40: ORD11152 | B40: 2025-05-27 | C40: 14:47 | D40: C0088 | E40: maratha thali house | F40: Pune | G40: North Indian | H40: 2 | I40: 205 | J40: 0 | K40: Debit Card | L40: Delivered | M40: 33 | N40: 5 | O40: =A40&"|"&B40&"|"&C40&"|"&D40&"|"&E40&"|"&F40&"|"&G40&"|"&H40&"|"&I40&"|"&J40&"|"&K40&"|"&L40&"|"&M40&"|"&N40 -> ORD11152|2025-05-27|14:47|C0088|maratha thali house|Pune|North Indian|2|205|0|Debit Card|Delivered|33|5 | P40: =IF(COUNTIF($O$2:O40,O40)>1,"DUP","OK") -> OK | Q40: =COUNTBLANK(A40:N40) -> 0 | R40: =IF(A40="",0,COUNTIFS($A$2:$A$3058,A40,$P$2:$P$3058,"OK")) -> 1 | S40: =IF(OR(A40="",P40="DUP",R40<2),"",IF(Q40=_xlfn.MINIFS($Q$2:$Q$3058,$A$2:$A$3058,A40,$P$2:$P$3058,"OK"),"KEEP","DROP")) | T40: =IF(A40="",1,0) -> 0 | U40: =IF(D40="",1,0) -> 0 | V40: =IF(E40="",1,0) -> 0 | W40: =IF(OR(H40<1,H40>10),1,0) -> 0 | X40: =IF(OR(I40<=0,I40>1500),1,0) -> 0 | Y40: =IF(J40>H40*I40,1,0) -> 0 | Z40: =IF(AND(N40<>"",OR(N40<1,N40>5)),1,0) -> 0 | AA40: =IF(AND(M40<>"",OR(M40<5,M40>180)),1,0) -> 0 | AB40: =IF(P40="DUP","Exact duplicate row",IF(T40=1,"Missing Order ID",IF(S40="DROP","Duplicate Order ID (less complete row)",IF(U40=1,"Missing Customer ID",IF(V40=1,"Missing Restaurant name",IF(W40=1,"Invalid/outlier quantity",IF(X40=1,"Invalid/outlier unit price",IF(Y40=1,"Discount greater than order value","")))))))) | AC40: =IF(AB40="","KEEP","DROP") -> KEEP | AD40: =IF(TRIM(F40)="",IFERROR(INDEX(Map_Tables!$I$4:$I$37,MATCH(TRIM(E40),Map_Tables!$G$4:$G$37,0)),""),IFERROR(INDEX(Map_Tables!$B$4:$B$18,MATCH(TRIM(F40),Map_Tables!$A$4:$A$18,0)),"CHECK")) -> Pune | AE40: =IF(TRIM(E40)="","",IFERROR(INDEX(Map_Tables!$H$4:$H$37,MATCH(TRIM(E40),Map_Tables!$G$4:$G$37,0)),"CHECK")) -> Maratha Thali House | AF40: =IF(TRIM(K40)="","Unknown",IFERROR(INDEX(Map_Tables!$E$4:$E$15,MATCH(TRIM(K40),Map_Tables!$D$4:$D$15,0)),"CHECK")) -> Debit Card | AG40: =IF(LEFT(LOWER(TRIM(L40)),6)="cancel","Cancelled","Delivered") -> Delivered | AH40: =IF(ISNUMBER(SEARCH("/",B40)),DATE(VALUE(RIGHT(B40,4)),VALUE(MID(B40,4,2)),VALUE(LEFT(B40,2))),IF(MID(B40,5,1)="-",DATE(VALUE(LEFT(B40,4)),VALUE(MID(B40,6,2)),VALUE(RIGHT(B40,2))),DATE(VALUE(RIGHT(B40,4)),MATCH(MID(B40,4,3),{"Jan","Feb","Mar","Apr","May","Jun","Jul","Aug","Sep","Oct","Nov","Dec"},0),VALUE(LEFT(B40,2))))) -> 45804
A41: ORD10721 | B41: 2025-04-02 | C41: 11:08 | D41: C0387 | E41: Maratha Thali House | F41: Pune | G41: North Indian | H41: 1 | I41: 215 | J41: 0 | K41: Upi | L41: Delivered | M41: 34 | N41: 5 | O41: =A41&"|"&B41&"|"&C41&"|"&D41&"|"&E41&"|"&F41&"|"&G41&"|"&H41&"|"&I41&"|"&J41&"|"&K41&"|"&L41&"|"&M41&"|"&N41 -> ORD10721|2025-04-02|11:08|C0387|Maratha Thali House|Pune|North Indian|1|215|0|Upi|Delivered|34|5 | P41: =IF(COUNTIF($O$2:O41,O41)>1,"DUP","OK") -> OK | Q41: =COUNTBLANK(A41:N41) -> 0 | R41: =IF(A41="",0,COUNTIFS($A$2:$A$3058,A41,$P$2:$P$3058,"OK")) -> 1 | S41: =IF(OR(A41="",P41="DUP",R41<2),"",IF(Q41=_xlfn.MINIFS($Q$2:$Q$3058,$A$2:$A$3058,A41,$P$2:$P$3058,"OK"),"KEEP","DROP")) | T41: =IF(A41="",1,0) -> 0 | U41: =IF(D41="",1,0) -> 0 | V41: =IF(E41="",1,0) -> 0 | W41: =IF(OR(H41<1,H41>10),1,0) -> 0 | X41: =IF(OR(I41<=0,I41>1500),1,0) -> 0 | Y41: =IF(J41>H41*I41,1,0) -> 0 | Z41: =IF(AND(N41<>"",OR(N41<1,N41>5)),1,0) -> 0 | AA41: =IF(AND(M41<>"",OR(M41<5,M41>180)),1,0) -> 0 | AB41: =IF(P41="DUP","Exact duplicate row",IF(T41=1,"Missing Order ID",IF(S41="DROP","Duplicate Order ID (less complete row)",IF(U41=1,"Missing Customer ID",IF(V41=1,"Missing Restaurant name",IF(W41=1,"Invalid/outlier quantity",IF(X41=1,"Invalid/outlier unit price",IF(Y41=1,"Discount greater than order value","")))))))) | AC41: =IF(AB41="","KEEP","DROP") -> KEEP | AD41: =IF(TRIM(F41)="",IFERROR(INDEX(Map_Tables!$I$4:$I$37,MATCH(TRIM(E41),Map_Tables!$G$4:$G$37,0)),""),IFERROR(INDEX(Map_Tables!$B$4:$B$18,MATCH(TRIM(F41),Map_Tables!$A$4:$A$18,0)),"CHECK")) -> Pune | AE41: =IF(TRIM(E41)="","",IFERROR(INDEX(Map_Tables!$H$4:$H$37,MATCH(TRIM(E41),Map_Tables!$G$4:$G$37,0)),"CHECK")) -> Maratha Thali House | AF41: =IF(TRIM(K41)="","Unknown",IFERROR(INDEX(Map_Tables!$E$4:$E$15,MATCH(TRIM(K41),Map_Tables!$D$4:$D$15,0)),"CHECK")) -> UPI | AG41: =IF(LEFT(LOWER(TRIM(L41)),6)="cancel","Cancelled","Delivered") -> Delivered | AH41: =IF(ISNUMBER(SEARCH("/",B41)),DATE(VALUE(RIGHT(B41,4)),VALUE(MID(B41,4,2)),VALUE(LEFT(B41,2))),IF(MID(B41,5,1)="-",DATE(VALUE(LEFT(B41,4)),VALUE(MID(B41,6,2)),VALUE(RIGHT(B41,2))),DATE(VALUE(RIGHT(B41,4)),MATCH(MID(B41,4,3),{"Jan","Feb","Mar","Apr","May","Jun","Jul","Aug","Sep","Oct","Nov","Dec"},0),VALUE(LEFT(B41,2))))) -> 45749
A42: ORD11418 | B42: 2025-07-03 | C42: 20:55 | D42: C0187 | E42: Burger Barn | F42: Delhi | G42: Burgers | H42: 2 | I42: 240 | J42: 30 | K42: Cash on Delivery | L42: Delivered | M42: 32 | N42: 3 | O42: =A42&"|"&B42&"|"&C42&"|"&D42&"|"&E42&"|"&F42&"|"&G42&"|"&H42&"|"&I42&"|"&J42&"|"&K42&"|"&L42&"|"&M42&"|"&N42 -> ORD11418|2025-07-03|20:55|C0187|Burger Barn|Delhi|Burgers|2|240|30|Cash on Delivery|Delivered|32|3 | P42: =IF(COUNTIF($O$2:O42,O42)>1,"DUP","OK") -> OK | Q42: =COUNTBLANK(A42:N42) -> 0 | R42: =IF(A42="",0,COUNTIFS($A$2:$A$3058,A42,$P$2:$P$3058,"OK")) -> 1 | S42: =IF(OR(A42="",P42="DUP",R42<2),"",IF(Q42=_xlfn.MINIFS($Q$2:$Q$3058,$A$2:$A$3058,A42,$P$2:$P$3058,"OK"),"KEEP","DROP")) | T42: =IF(A42="",1,0) -> 0 | U42: =IF(D42="",1,0) -> 0 | V42: =IF(E42="",1,0) -> 0 | W42: =IF(OR(H42<1,H42>10),1,0) -> 0 | X42: =IF(OR(I42<=0,I42>1500),1,0) -> 0 | Y42: =IF(J42>H42*I42,1,0) -> 0 | Z42: =IF(AND(N42<>"",OR(N42<1,N42>5)),1,0) -> 0 | AA42: =IF(AND(M42<>"",OR(M42<5,M42>180)),1,0) -> 0 | AB42: =IF(P42="DUP","Exact duplicate row",IF(T42=1,"Missing Order ID",IF(S42="DROP","Duplicate Order ID (less complete row)",IF(U42=1,"Missing Customer ID",IF(V42=1,"Missing Restaurant name",IF(W42=1,"Invalid/outlier quantity",IF(X42=1,"Invalid/outlier unit price",IF(Y42=1,"Discount greater than order value","")))))))) | AC42: =IF(AB42="","KEEP","DROP") -> KEEP | AD42: =IF(TRIM(F42)="",IFERROR(INDEX(Map_Tables!$I$4:$I$37,MATCH(TRIM(E42),Map_Tables!$G$4:$G$37,0)),""),IFERROR(INDEX(Map_Tables!$B$4:$B$18,MATCH(TRIM(F42),Map_Tables!$A$4:$A$18,0)),"CHECK")) -> Delhi | AE42: =IF(TRIM(E42)="","",IFERROR(INDEX(Map_Tables!$H$4:$H$37,MATCH(TRIM(E42),Map_Tables!$G$4:$G$37,0)),"CHECK")) -> Burger Barn | AF42: =IF(TRIM(K42)="","Unknown",IFERROR(INDEX(Map_Tables!$E$4:$E$15,MATCH(TRIM(K42),Map_Tables!$D$4:$D$15,0)),"CHECK")) -> Cash on Delivery | AG42: =IF(LEFT(LOWER(TRIM(L42)),6)="cancel","Cancelled","Delivered") -> Delivered | AH42: =IF(ISNUMBER(SEARCH("/",B42)),DATE(VALUE(RIGHT(B42,4)),VALUE(MID(B42,4,2)),VALUE(LEFT(B42,2))),IF(MID(B42,5,1)="-",DATE(VALUE(LEFT(B42,4)),VALUE(MID(B42,6,2)),VALUE(RIGHT(B42,2))),DATE(VALUE(RIGHT(B42,4)),MATCH(MID(B42,4,3),{"Jan","Feb","Mar","Apr","May","Jun","Jul","Aug","Sep","Oct","Nov","Dec"},0),VALUE(LEFT(B42,2))))) -> 45841
A43: ORD10181 | B43: 2025-01-24 | C43: 19:29 | D43: C0092 | E43: Hyderabad Dum Biryani | F43: Hyderabad | G43: Biryani | H43: 5 | I43: 290 | J43: 0 | K43: debit card | L43: Delivered | M43: 46 | N43: 5 | O43: =A43&"|"&B43&"|"&C43&"|"&D43&"|"&E43&"|"&F43&"|"&G43&"|"&H43&"|"&I43&"|"&J43&"|"&K43&"|"&L43&"|"&M43&"|"&N43 -> ORD10181|2025-01-24|19:29|C0092|Hyderabad Dum Biryani|Hyderabad|Biryani|5|290|0|debit card|Delivered|46|5 | P43: =IF(COUNTIF($O$2:O43,O43)>1,"DUP","OK") -> OK | Q43: =COUNTBLANK(A43:N43) -> 0 | R43: =IF(A43="",0,COUNTIFS($A$2:$A$3058,A43,$P$2:$P$3058,"OK")) -> 1 | S43: =IF(OR(A43="",P43="DUP",R43<2),"",IF(Q43=_xlfn.MINIFS($Q$2:$Q$3058,$A$2:$A$3058,A43,$P$2:$P$3058,"OK"),"KEEP","DROP")) | T43: =IF(A43="",1,0) -> 0 | U43: =IF(D43="",1,0) -> 0 | V43: =IF(E43="",1,0) -> 0 | W43: =IF(OR(H43<1,H43>10),1,0) -> 0 | X43: =IF(OR(I43<=0,I43>1500),1,0) -> 0 | Y43: =IF(J43>H43*I43,1,0) -> 0 | Z43: =IF(AND(N43<>"",OR(N43<1,N43>5)),1,0) -> 0 | AA43: =IF(AND(M43<>"",OR(M43<5,M43>180)),1,0) -> 0 | AB43: =IF(P43="DUP","Exact duplicate row",IF(T43=1,"Missing Order ID",IF(S43="DROP","Duplicate Order ID (less complete row)",IF(U43=1,"Missing Customer ID",IF(V43=1,"Missing Restaurant name",IF(W43=1,"Invalid/outlier quantity",IF(X43=1,"Invalid/outlier unit price",IF(Y43=1,"Discount greater than order value","")))))))) | AC43: =IF(AB43="","KEEP","DROP") -> KEEP | AD43: =IF(TRIM(F43)="",IFERROR(INDEX(Map_Tables!$I$4:$I$37,MATCH(TRIM(E43),Map_Tables!$G$4:$G$37,0)),""),IFERROR(INDEX(Map_Tables!$B$4:$B$18,MATCH(TRIM(F43),Map_Tables!$A$4:$A$18,0)),"CHECK")) -> Hyderabad | AE43: =IF(TRIM(E43)="","",IFERROR(INDEX(Map_Tables!$H$4:$H$37,MATCH(TRIM(E43),Map_Tables!$G$4:$G$37,0)),"CHECK")) -> Hyderabad Dum Biryani | AF43: =IF(TRIM(K43)="","Unknown",IFERROR(INDEX(Map_Tables!$E$4:$E$15,MATCH(TRIM(K43),Map_Tables!$D$4:$D$15,0)),"CHECK")) -> Debit Card | AG43: =IF(LEFT(LOWER(TRIM(L43)),6)="cancel","Cancelled","Delivered") -> Delivered | AH43: =IF(ISNUMBER(SEARCH("/",B43)),DATE(VALUE(RIGHT(B43,4)),VALUE(MID(B43,4,2)),VALUE(LEFT(B43,2))),IF(MID(B43,5,1)="-",DATE(VALUE(LEFT(B43,4)),VALUE(MID(B43,6,2)),VALUE(RIGHT(B43,2))),DATE(VALUE(RIGHT(B43,4)),MATCH(MID(B43,4,3),{"Jan","Feb","Mar","Apr","May","Jun","Jul","Aug","Sep","Oct","Nov","Dec"},0),VALUE(LEFT(B43,2))))) -> 45681
A44: ORD10639 | B44: 2025-03-22 | C44: 17:46 | D44: C0254 | E44: Tandoor Tales | F44: Delhi | G44: North Indian | H44: 3 | I44: 220 | J44: 30 | K44: Cash on Delivery | L44: Delivered | M44: 47 | N44: 3 | O44: =A44&"|"&B44&"|"&C44&"|"&D44&"|"&E44&"|"&F44&"|"&G44&"|"&H44&"|"&I44&"|"&J44&"|"&K44&"|"&L44&"|"&M44&"|"&N44 -> ORD10639|2025-03-22|17:46|C0254|Tandoor Tales|Delhi|North Indian|3|220|30|Cash on Delivery|Delivered|47|3 | P44: =IF(COUNTIF($O$2:O44,O44)>1,"DUP","OK") -> OK | Q44: =COUNTBLANK(A44:N44) -> 0 | R44: =IF(A44="",0,COUNTIFS($A$2:$A$3058,A44,$P$2:$P$3058,"OK")) -> 1 | S44: =IF(OR(A44="",P44="DUP",R44<2),"",IF(Q44=_xlfn.MINIFS($Q$2:$Q$3058,$A$2:$A$3058,A44,$P$2:$P$3058,"OK"),"KEEP","DROP")) | T44: =IF(A44="",1,0) -> 0 | U44: =IF(D44="",1,0) -> 0 | V44: =IF(E44="",1,0) -> 0 | W44: =IF(OR(H44<1,H44>10),1,0) -> 0 | X44: =IF(OR(I44<=0,I44>1500),1,0) -> 0 | Y44: =IF(J44>H44*I44,1,0) -> 0 | Z44: =IF(AND(N44<>"",OR(N44<1,N44>5)),1,0) -> 0 | AA44: =IF(AND(M44<>"",OR(M44<5,M44>180)),1,0) -> 0 | AB44: =IF(P44="DUP","Exact duplicate row",IF(T44=1,"Missing Order ID",IF(S44="DROP","Duplicate Order ID (less complete row)",IF(U44=1,"Missing Customer ID",IF(V44=1,"Missing Restaurant name",IF(W44=1,"Invalid/outlier quantity",IF(X44=1,"Invalid/outlier unit price",IF(Y44=1,"Discount greater than order value","")))))))) | AC44: =IF(AB44="","KEEP","DROP") -> KEEP | AD44: =IF(TRIM(F44)="",IFERROR(INDEX(Map_Tables!$I$4:$I$37,MATCH(TRIM(E44),Map_Tables!$G$4:$G$37,0)),""),IFERROR(INDEX(Map_Tables!$B$4:$B$18,MATCH(TRIM(F44),Map_Tables!$A$4:$A$18,0)),"CHECK")) -> Delhi | AE44: =IF(TRIM(E44)="","",IFERROR(INDEX(Map_Tables!$H$4:$H$37,MATCH(TRIM(E44),Map_Tables!$G$4:$G$37,0)),"CHECK")) -> Tandoor Tales | AF44: =IF(TRIM(K44)="","Unknown",IFERROR(INDEX(Map_Tables!$E$4:$E$15,MATCH(TRIM(K44),Map_Tables!$D$4:$D$15,0)),"CHECK")) -> Cash on Delivery | AG44: =IF(LEFT(LOWER(TRIM(L44)),6)="cancel","Cancelled","Delivered") -> Delivered | AH44: =IF(ISNUMBER(SEARCH("/",B44)),DATE(VALUE(RIGHT(B44,4)),VALUE(MID(B44,4,2)),VALUE(LEFT(B44,2))),IF(MID(B44,5,1)="-",DATE(VALUE(LEFT(B44,4)),VALUE(MID(B44,6,2)),VALUE(RIGHT(B44,2))),DATE(VALUE(RIGHT(B44,4)),MATCH(MID(B44,4,3),{"Jan","Feb","Mar","Apr","May","Jun","Jul","Aug","Sep","Oct","Nov","Dec"},0),VALUE(LEFT(B44,2))))) -> 45738
A45: ORD11497 | B45: 2025-07-14 | C45: 12:00 | D45: C0854 | E45: Fit Fuel Kitchen | F45: Ahmedabad | G45: Healthy Food | H45: 4 | I45: 210 | J45: 0 | K45: Credit card | L45: Delivered | M45: 32 | N45: 1 | O45: =A45&"|"&B45&"|"&C45&"|"&D45&"|"&E45&"|"&F45&"|"&G45&"|"&H45&"|"&I45&"|"&J45&"|"&K45&"|"&L45&"|"&M45&"|"&N45 -> ORD11497|2025-07-14|12:00|C0854|Fit Fuel Kitchen|Ahmedabad|Healthy Food|4|210|0|Credit card|Delivered|32|1 | P45: =IF(COUNTIF($O$2:O45,O45)>1,"DUP","OK") -> OK | Q45: =COUNTBLANK(A45:N45) -> 0 | R45: =IF(A45="",0,COUNTIFS($A$2:$A$3058,A45,$P$2:$P$3058,"OK")) -> 1 | S45: =IF(OR(A45="",P45="DUP",R45<2),"",IF(Q45=_xlfn.MINIFS($Q$2:$Q$3058,$A$2:$A$3058,A45,$P$2:$P$3058,"OK"),"KEEP","DROP")) | T45: =IF(A45="",1,0) -> 0 | U45: =IF(D45="",1,0) -> 0 | V45: =IF(E45="",1,0) -> 0 | W45: =IF(OR(H45<1,H45>10),1,0) -> 0 | X45: =IF(OR(I45<=0,I45>1500),1,0) -> 0 | Y45: =IF(J45>H45*I45,1,0) -> 0 | Z45: =IF(AND(N45<>"",OR(N45<1,N45>5)),1,0) -> 0 | AA45: =IF(AND(M45<>"",OR(M45<5,M45>180)),1,0) -> 0 | AB45: =IF(P45="DUP","Exact duplicate row",IF(T45=1,"Missing Order ID",IF(S45="DROP","Duplicate Order ID (less complete row)",IF(U45=1,"Missing Customer ID",IF(V45=1,"Missing Restaurant name",IF(W45=1,"Invalid/outlier quantity",IF(X45=1,"Invalid/outlier unit price",IF(Y45=1,"Discount greater than order value","")))))))) | AC45: =IF(AB45="","KEEP","DROP") -> KEEP | AD45: =IF(TRIM(F45)="",IFERROR(INDEX(Map_Tables!$I$4:$I$37,MATCH(TRIM(E45),Map_Tables!$G$4:$G$37,0)),""),IFERROR(INDEX(Map_Tables!$B$4:$B$18,MATCH(TRIM(F45),Map_Tables!$A$4:$A$18,0)),"CHECK")) -> Ahmedabad | AE45: =IF(TRIM(E45)="","",IFERROR(INDEX(Map_Tables!$H$4:$H$37,MATCH(TRIM(E45),Map_Tables!$G$4:$G$37,0)),"CHECK")) -> Fit Fuel Kitchen | AF45: =IF(TRIM(K45)="","Unknown",IFERROR(INDEX(Map_Tables!$E$4:$E$15,MATCH(TRIM(K45),Map_Tables!$D$4:$D$15,0)),"CHECK")) -> Credit Card | AG45: =IF(LEFT(LOWER(TRIM(L45)),6)="cancel","Cancelled","Delivered") -> Delivered | AH45: =IF(ISNUMBER(SEARCH("/",B45)),DATE(VALUE(RIGHT(B45,4)),VALUE(MID(B45,4,2)),VALUE(LEFT(B45,2))),IF(MID(B45,5,1)="-",DATE(VALUE(LEFT(B45,4)),VALUE(MID(B45,6,2)),VALUE(RIGHT(B45,2))),DATE(VALUE(RIGHT(B45,4)),MATCH(MID(B45,4,3),{"Jan","Feb","Mar","Apr","May","Jun","Jul","Aug","Sep","Oct","Nov","Dec"},0),VALUE(LEFT(B45,2))))) -> 45852
A46: ORD10207 | B46: 2025-01-28 | C46: 18:26 | D46: C1082 | E46: Mumbai Pizza Co | F46: Mumbai | G46: Pizza | H46: 2 | I46: 270 | J46: 0 | K46: Wallet | L46: Delivered | M46: 999 | N46: 4 | O46: =A46&"|"&B46&"|"&C46&"|"&D46&"|"&E46&"|"&F46&"|"&G46&"|"&H46&"|"&I46&"|"&J46&"|"&K46&"|"&L46&"|"&M46&"|"&N46 -> ORD10207|2025-01-28|18:26|C1082|Mumbai Pizza Co|Mumbai|Pizza|2|270|0|Wallet|Delivered|999|4 | P46: =IF(COUNTIF($O$2:O46,O46)>1,"DUP","OK") -> OK | Q46: =COUNTBLANK(A46:N46) -> 0 | R46: =IF(A46="",0,COUNTIFS($A$2:$A$3058,A46,$P$2:$P$3058,"OK")) -> 1 | S46: =IF(OR(A46="",P46="DUP",R46<2),"",IF(Q46=_xlfn.MINIFS($Q$2:$Q$3058,$A$2:$A$3058,A46,$P$2:$P$3058,"OK"),"KEEP","DROP")) | T46: =IF(A46="",1,0) -> 0 | U46: =IF(D46="",1,0) -> 0 | V46: =IF(E46="",1,0) -> 0 | W46: =IF(OR(H46<1,H46>10),1,0) -> 0 | X46: =IF(OR(I46<=0,I46>1500),1,0) -> 0 | Y46: =IF(J46>H46*I46,1,0) -> 0 | Z46: =IF(AND(N46<>"",OR(N46<1,N46>5)),1,0) -> 0 | AA46: =IF(AND(M46<>"",OR(M46<5,M46>180)),1,0) -> 1 | AB46: =IF(P46="DUP","Exact duplicate row",IF(T46=1,"Missing Order ID",IF(S46="DROP","Duplicate Order ID (less complete row)",IF(U46=1,"Missing Customer ID",IF(V46=1,"Missing Restaurant name",IF(W46=1,"Invalid/outlier quantity",IF(X46=1,"Invalid/outlier unit price",IF(Y46=1,"Discount greater than order value","")))))))) | AC46: =IF(AB46="","KEEP","DROP") -> KEEP | AD46: =IF(TRIM(F46)="",IFERROR(INDEX(Map_Tables!$I$4:$I$37,MATCH(TRIM(E46),Map_Tables!$G$4:$G$37,0)),""),IFERROR(INDEX(Map_Tables!$B$4:$B$18,MATCH(TRIM(F46),Map_Tables!$A$4:$A$18,0)),"CHECK")) -> Mumbai | AE46: =IF(TRIM(E46)="","",IFERROR(INDEX(Map_Tables!$H$4:$H$37,MATCH(TRIM(E46),Map_Tables!$G$4:$G$37,0)),"CHECK")) -> Mumbai Pizza Co | AF46: =IF(TRIM(K46)="","Unknown",IFERROR(INDEX(Map_Tables!$E$4:$E$15,MATCH(TRIM(K46),Map_Tables!$D$4:$D$15,0)),"CHECK")) -> Wallet | AG46: =IF(LEFT(LOWER(TRIM(L46)),6)="cancel","Cancelled","Delivered") -> Delivered | AH46: =IF(ISNUMBER(SEARCH("/",B46)),DATE(VALUE(RIGHT(B46,4)),VALUE(MID(B46,4,2)),VALUE(LEFT(B46,2))),IF(MID(B46,5,1)="-",DATE(VALUE(LEFT(B46,4)),VALUE(MID(B46,6,2)),VALUE(RIGHT(B46,2))),DATE(VALUE(RIGHT(B46,4)),MATCH(MID(B46,4,3),{"Jan","Feb","Mar","Apr","May","Jun","Jul","Aug","Sep","Oct","Nov","Dec"},0),VALUE(LEFT(B46,2))))) -> 45685
A47: ORD11534 | B47: 2025-07-18 | C47: 11:53 | D47: C0754 | E47: Maratha Thali House | F47: Pune | G47: North Indian | H47: 1 | I47: 235 | J47: 0 | K47: UPI | L47: Cancelled | O47: =A47&"|"&B47&"|"&C47&"|"&D47&"|"&E47&"|"&F47&"|"&G47&"|"&H47&"|"&I47&"|"&J47&"|"&K47&"|"&L47&"|"&M47&"|"&N47 -> ORD11534|2025-07-18|11:53|C0754|Maratha Thali House |Pune|North Indian|1|235|0|UPI|Cancelled|| | P47: =IF(COUNTIF($O$2:O47,O47)>1,"DUP","OK") -> OK | Q47: =COUNTBLANK(A47:N47) -> 2 | R47: =IF(A47="",0,COUNTIFS($A$2:$A$3058,A47,$P$2:$P$3058,"OK")) -> 1 | S47: =IF(OR(A47="",P47="DUP",R47<2),"",IF(Q47=_xlfn.MINIFS($Q$2:$Q$3058,$A$2:$A$3058,A47,$P$2:$P$3058,"OK"),"KEEP","DROP")) | T47: =IF(A47="",1,0) -> 0 | U47: =IF(D47="",1,0) -> 0 | V47: =IF(E47="",1,0) -> 0 | W47: =IF(OR(H47<1,H47>10),1,0) -> 0 | X47: =IF(OR(I47<=0,I47>1500),1,0) -> 0 | Y47: =IF(J47>H47*I47,1,0) -> 0 | Z47: =IF(AND(N47<>"",OR(N47<1,N47>5)),1,0) -> 0 | AA47: =IF(AND(M47<>"",OR(M47<5,M47>180)),1,0) -> 0 | AB47: =IF(P47="DUP","Exact duplicate row",IF(T47=1,"Missing Order ID",IF(S47="DROP","Duplicate Order ID (less complete row)",IF(U47=1,"Missing Customer ID",IF(V47=1,"Missing Restaurant name",IF(W47=1,"Invalid/outlier quantity",IF(X47=1,"Invalid/outlier unit price",IF(Y47=1,"Discount greater than order value","")))))))) | AC47: =IF(AB47="","KEEP","DROP") -> KEEP | AD47: =IF(TRIM(F47)="",IFERROR(INDEX(Map_Tables!$I$4:$I$37,MATCH(TRIM(E47),Map_Tables!$G$4:$G$37,0)),""),IFERROR(INDEX(Map_Tables!$B$4:$B$18,MATCH(TRIM(F47),Map_Tables!$A$4:$A$18,0)),"CHECK")) -> Pune | AE47: =IF(TRIM(E47)="","",IFERROR(INDEX(Map_Tables!$H$4:$H$37,MATCH(TRIM(E47),Map_Tables!$G$4:$G$37,0)),"CHECK")) -> Maratha Thali House | AF47: =IF(TRIM(K47)="","Unknown",IFERROR(INDEX(Map_Tables!$E$4:$E$15,MATCH(TRIM(K47),Map_Tables!$D$4:$D$15,0)),"CHECK")) -> UPI | AG47: =IF(LEFT(LOWER(TRIM(L47)),6)="cancel","Cancelled","Delivered") -> Cancelled | AH47: =IF(ISNUMBER(SEARCH("/",B47)),DATE(VALUE(RIGHT(B47,4)),VALUE(MID(B47,4,2)),VALUE(LEFT(B47,2))),IF(MID(B47,5,1)="-",DATE(VALUE(LEFT(B47,4)),VALUE(MID(B47,6,2)),VALUE(RIGHT(B47,2))),DATE(VALUE(RIGHT(B47,4)),MATCH(MID(B47,4,3),{"Jan","Feb","Mar","Apr","May","Jun","Jul","Aug","Sep","Oct","Nov","Dec"},0),VALUE(LEFT(B47,2))))) -> 45856
A48: ORD11237 | B48: 2025-06-06 | C48: 19:50 | D48: C1106 | E48: Cake Walk | F48: Pune | G48: Desserts | H48: 1 | I48: 175 | J48: 0 | L48: Delivered | M48: 25 | N48: 5 | O48: =A48&"|"&B48&"|"&C48&"|"&D48&"|"&E48&"|"&F48&"|"&G48&"|"&H48&"|"&I48&"|"&J48&"|"&K48&"|"&L48&"|"&M48&"|"&N48 -> ORD11237|2025-06-06|19:50|C1106|Cake Walk|Pune|Desserts|1|175|0||Delivered|25|5 | P48: =IF(COUNTIF($O$2:O48,O48)>1,"DUP","OK") -> OK | Q48: =COUNTBLANK(A48:N48) -> 1 | R48: =IF(A48="",0,COUNTIFS($A$2:$A$3058,A48,$P$2:$P$3058,"OK")) -> 1 | S48: =IF(OR(A48="",P48="DUP",R48<2),"",IF(Q48=_xlfn.MINIFS($Q$2:$Q$3058,$A$2:$A$3058,A48,$P$2:$P$3058,"OK"),"KEEP","DROP")) | T48: =IF(A48="",1,0) -> 0 | U48: =IF(D48="",1,0) -> 0 | V48: =IF(E48="",1,0) -> 0 | W48: =IF(OR(H48<1,H48>10),1,0) -> 0 | X48: =IF(OR(I48<=0,I48>1500),1,0) -> 0 | Y48: =IF(J48>H48*I48,1,0) -> 0 | Z48: =IF(AND(N48<>"",OR(N48<1,N48>5)),1,0) -> 0 | AA48: =IF(AND(M48<>"",OR(M48<5,M48>180)),1,0) -> 0 | AB48: =IF(P48="DUP","Exact duplicate row",IF(T48=1,"Missing Order ID",IF(S48="DROP","Duplicate Order ID (less complete row)",IF(U48=1,"Missing Customer ID",IF(V48=1,"Missing Restaurant name",IF(W48=1,"Invalid/outlier quantity",IF(X48=1,"Invalid/outlier unit price",IF(Y48=1,"Discount greater than order value","")))))))) | AC48: =IF(AB48="","KEEP","DROP") -> KEEP | AD48: =IF(TRIM(F48)="",IFERROR(INDEX(Map_Tables!$I$4:$I$37,MATCH(TRIM(E48),Map_Tables!$G$4:$G$37,0)),""),IFERROR(INDEX(Map_Tables!$B$4:$B$18,MATCH(TRIM(F48),Map_Tables!$A$4:$A$18,0)),"CHECK")) -> Pune | AE48: =IF(TRIM(E48)="","",IFERROR(INDEX(Map_Tables!$H$4:$H$37,MATCH(TRIM(E48),Map_Tables!$G$4:$G$37,0)),"CHECK")) -> Cake Walk | AF48: =IF(TRIM(K48)="","Unknown",IFERROR(INDEX(Map_Tables!$E$4:$E$15,MATCH(TRIM(K48),Map_Tables!$D$4:$D$15,0)),"CHECK")) -> Unknown | AG48: =IF(LEFT(LOWER(TRIM(L48)),6)="cancel","Cancelled","Delivered") -> Delivered | AH48: =IF(ISNUMBER(SEARCH("/",B48)),DATE(VALUE(RIGHT(B48,4)),VALUE(MID(B48,4,2)),VALUE(LEFT(B48,2))),IF(MID(B48,5,1)="-",DATE(VALUE(LEFT(B48,4)),VALUE(MID(B48,6,2)),VALUE(RIGHT(B48,2))),DATE(VALUE(RIGHT(B48,4)),MATCH(MID(B48,4,3),{"Jan","Feb","Mar","Apr","May","Jun","Jul","Aug","Sep","Oct","Nov","Dec"},0),VALUE(LEFT(B48,2))))) -> 45814
A49: ORD11464 | B49: 09/07/2025 | C49: 22:13 | D49: C0312 | E49: Pav Bhaji Point | F49: Mumbai | G49: Street Food | H49: 2 | I49: 150 | J49: 0 | K49: Credit Card | L49: Delivered | M49: 49 | N49: 5 | O49: =A49&"|"&B49&"|"&C49&"|"&D49&"|"&E49&"|"&F49&"|"&G49&"|"&H49&"|"&I49&"|"&J49&"|"&K49&"|"&L49&"|"&M49&"|"&N49 -> ORD11464|09/07/2025|22:13|C0312|Pav Bhaji Point|Mumbai|Street Food|2|150|0|Credit Card|Delivered|49|5 | P49: =IF(COUNTIF($O$2:O49,O49)>1,"DUP","OK") -> OK | Q49: =COUNTBLANK(A49:N49) -> 0 | R49: =IF(A49="",0,COUNTIFS($A$2:$A$3058,A49,$P$2:$P$3058,"OK")) -> 1 | S49: =IF(OR(A49="",P49="DUP",R49<2),"",IF(Q49=_xlfn.MINIFS($Q$2:$Q$3058,$A$2:$A$3058,A49,$P$2:$P$3058,"OK"),"KEEP","DROP")) | T49: =IF(A49="",1,0) -> 0 | U49: =IF(D49="",1,0) -> 0 | V49: =IF(E49="",1,0) -> 0 | W49: =IF(OR(H49<1,H49>10),1,0) -> 0 | X49: =IF(OR(I49<=0,I49>1500),1,0) -> 0 | Y49: =IF(J49>H49*I49,1,0) -> 0 | Z49: =IF(AND(N49<>"",OR(N49<1,N49>5)),1,0) -> 0 | AA49: =IF(AND(M49<>"",OR(M49<5,M49>180)),1,0) -> 0 | AB49: =IF(P49="DUP","Exact duplicate row",IF(T49=1,"Missing Order ID",IF(S49="DROP","Duplicate Order ID (less complete row)",IF(U49=1,"Missing Customer ID",IF(V49=1,"Missing Restaurant name",IF(W49=1,"Invalid/outlier quantity",IF(X49=1,"Invalid/outlier unit price",IF(Y49=1,"Discount greater than order value","")))))))) | AC49: =IF(AB49="","KEEP","DROP") -> KEEP | AD49: =IF(TRIM(F49)="",IFERROR(INDEX(Map_Tables!$I$4:$I$37,MATCH(TRIM(E49),Map_Tables!$G$4:$G$37,0)),""),IFERROR(INDEX(Map_Tables!$B$4:$B$18,MATCH(TRIM(F49),Map_Tables!$A$4:$A$18,0)),"CHECK")) -> Mumbai | AE49: =IF(TRIM(E49)="","",IFERROR(INDEX(Map_Tables!$H$4:$H$37,MATCH(TRIM(E49),Map_Tables!$G$4:$G$37,0)),"CHECK")) -> Pav Bhaji Point | AF49: =IF(TRIM(K49)="","Unknown",IFERROR(INDEX(Map_Tables!$E$4:$E$15,MATCH(TRIM(K49),Map_Tables!$D$4:$D$15,0)),"CHECK")) -> Credit Card | AG49: =IF(LEFT(LOWER(TRIM(L49)),6)="cancel","Cancelled","Delivered") -> Delivered | AH49: =IF(ISNUMBER(SEARCH("/",B49)),DATE(VALUE(RIGHT(B49,4)),VALUE(MID(B49,4,2)),VALUE(LEFT(B49,2))),IF(MID(B49,5,1)="-",DATE(VALUE(LEFT(B49,4)),VALUE(MID(B49,6,2)),VALUE(RIGHT(B49,2))),DATE(VALUE(RIGHT(B49,4)),MATCH(MID(B49,4,3),{"Jan","Feb","Mar","Apr","May","Jun","Jul","Aug","Sep","Oct","Nov","Dec"},0),VALUE(LEFT(B49,2))))) -> 45847
A50: ORD12411 | B50: 31/10/2025 | C50: 12:43 | D50: C1305 | E50: Pav Bhaji Point | F50: Mumbai | G50: Street Food | H50: 2 | I50: 145 | J50: 116 | K50: UPI | L50: Delivered | M50: 49 | O50: =A50&"|"&B50&"|"&C50&"|"&D50&"|"&E50&"|"&F50&"|"&G50&"|"&H50&"|"&I50&"|"&J50&"|"&K50&"|"&L50&"|"&M50&"|"&N50 -> ORD12411|31/10/2025|12:43|C1305|Pav Bhaji Point|Mumbai|Street Food|2|145|116|UPI|Delivered|49| | P50: =IF(COUNTIF($O$2:O50,O50)>1,"DUP","OK") -> OK | Q50: =COUNTBLANK(A50:N50) -> 1 | R50: =IF(A50="",0,COUNTIFS($A$2:$A$3058,A50,$P$2:$P$3058,"OK")) -> 1 | S50: =IF(OR(A50="",P50="DUP",R50<2),"",IF(Q50=_xlfn.MINIFS($Q$2:$Q$3058,$A$2:$A$3058,A50,$P$2:$P$3058,"OK"),"KEEP","DROP")) | T50: =IF(A50="",1,0) -> 0 | U50: =IF(D50="",1,0) -> 0 | V50: =IF(E50="",1,0) -> 0 | W50: =IF(OR(H50<1,H50>10),1,0) -> 0 | X50: =IF(OR(I50<=0,I50>1500),1,0) -> 0 | Y50: =IF(J50>H50*I50,1,0) -> 0 | Z50: =IF(AND(N50<>"",OR(N50<1,N50>5)),1,0) -> 0 | AA50: =IF(AND(M50<>"",OR(M50<5,M50>180)),1,0) -> 0 | AB50: =IF(P50="DUP","Exact duplicate row",IF(T50=1,"Missing Order ID",IF(S50="DROP","Duplicate Order ID (less complete row)",IF(U50=1,"Missing Customer ID",IF(V50=1,"Missing Restaurant name",IF(W50=1,"Invalid/outlier quantity",IF(X50=1,"Invalid/outlier unit price",IF(Y50=1,"Discount greater than order value","")))))))) | AC50: =IF(AB50="","KEEP","DROP") -> KEEP | AD50: =IF(TRIM(F50)="",IFERROR(INDEX(Map_Tables!$I$4:$I$37,MATCH(TRIM(E50),Map_Tables!$G$4:$G$37,0)),""),IFERROR(INDEX(Map_Tables!$B$4:$B$18,MATCH(TRIM(F50),Map_Tables!$A$4:$A$18,0)),"CHECK")) -> Mumbai | AE50: =IF(TRIM(E50)="","",IFERROR(INDEX(Map_Tables!$H$4:$H$37,MATCH(TRIM(E50),Map_Tables!$G$4:$G$37,0)),"CHECK")) -> Pav Bhaji Point | AF50: =IF(TRIM(K50)="","Unknown",IFERROR(INDEX(Map_Tables!$E$4:$E$15,MATCH(TRIM(K50),Map_Tables!$D$4:$D$15,0)),"CHECK")) -> UPI | AG50: =IF(LEFT(LOWER(TRIM(L50)),6)="cancel","Cancelled","Delivered") -> Delivered | AH50: =IF(ISNUMBER(SEARCH("/",B50)),DATE(VALUE(RIGHT(B50,4)),VALUE(MID(B50,4,2)),VALUE(LEFT(B50,2))),IF(MID(B50,5,1)="-",DATE(VALUE(LEFT(B50,4)),VALUE(MID(B50,6,2)),VALUE(RIGHT(B50,2))),DATE(VALUE(RIGHT(B50,4)),MATCH(MID(B50,4,3),{"Jan","Feb","Mar","Apr","May","Jun","Jul","Aug","Sep","Oct","Nov","Dec"},0),VALUE(LEFT(B50,2))))) -> 45961
A51: ORD12101 | B51: 2025-09-28 | C51: 11:13 | D51: C0885 | E51: Biryani Baadshah | F51: Kolkata | G51: Biryani | H51: 3 | I51: 245 | J51: 30 | K51: Debit Card | L51: Delivered | M51: 36 | N51: 4 | O51: =A51&"|"&B51&"|"&C51&"|"&D51&"|"&E51&"|"&F51&"|"&G51&"|"&H51&"|"&I51&"|"&J51&"|"&K51&"|"&L51&"|"&M51&"|"&N51 -> ORD12101|2025-09-28|11:13|C0885|Biryani Baadshah|Kolkata|Biryani|3|245|30|Debit Card|Delivered|36|4 | P51: =IF(COUNTIF($O$2:O51,O51)>1,"DUP","OK") -> OK | Q51: =COUNTBLANK(A51:N51) -> 0 | R51: =IF(A51="",0,COUNTIFS($A$2:$A$3058,A51,$P$2:$P$3058,"OK")) -> 1 | S51: =IF(OR(A51="",P51="DUP",R51<2),"",IF(Q51=_xlfn.MINIFS($Q$2:$Q$3058,$A$2:$A$3058,A51,$P$2:$P$3058,"OK"),"KEEP","DROP")) | T51: =IF(A51="",1,0) -> 0 | U51: =IF(D51="",1,0) -> 0 | V51: =IF(E51="",1,0) -> 0 | W51: =IF(OR(H51<1,H51>10),1,0) -> 0 | X51: =IF(OR(I51<=0,I51>1500),1,0) -> 0 | Y51: =IF(J51>H51*I51,1,0) -> 0 | Z51: =IF(AND(N51<>"",OR(N51<1,N51>5)),1,0) -> 0 | AA51: =IF(AND(M51<>"",OR(M51<5,M51>180)),1,0) -> 0 | AB51: =IF(P51="DUP","Exact duplicate row",IF(T51=1,"Missing Order ID",IF(S51="DROP","Duplicate Order ID (less complete row)",IF(U51=1,"Missing Customer ID",IF(V51=1,"Missing Restaurant name",IF(W51=1,"Invalid/outlier quantity",IF(X51=1,"Invalid/outlier unit price",IF(Y51=1,"Discount greater than order value","")))))))) | AC51: =IF(AB51="","KEEP","DROP") -> KEEP | AD51: =IF(TRIM(F51)="",IFERROR(INDEX(Map_Tables!$I$4:$I$37,MATCH(TRIM(E51),Map_Tables!$G$4:$G$37,0)),""),IFERROR(INDEX(Map_Tables!$B$4:$B$18,MATCH(TRIM(F51),Map_Tables!$A$4:$A$18,0)),"CHECK")) -> Kolkata | AE51: =IF(TRIM(E51)="","",IFERROR(INDEX(Map_Tables!$H$4:$H$37,MATCH(TRIM(E51),Map_Tables!$G$4:$G$37,0)),"CHECK")) -> Biryani Baadshah | AF51: =IF(TRIM(K51)="","Unknown",IFERROR(INDEX(Map_Tables!$E$4:$E$15,MATCH(TRIM(K51),Map_Tables!$D$4:$D$15,0)),"CHECK")) -> Debit Card | AG51: =IF(LEFT(LOWER(TRIM(L51)),6)="cancel","Cancelled","Delivered") -> Delivered | AH51: =IF(ISNUMBER(SEARCH("/",B51)),DATE(VALUE(RIGHT(B51,4)),VALUE(MID(B51,4,2)),VALUE(LEFT(B51,2))),IF(MID(B51,5,1)="-",DATE(VALUE(LEFT(B51,4)),VALUE(MID(B51,6,2)),VALUE(RIGHT(B51,2))),DATE(VALUE(RIGHT(B51,4)),MATCH(MID(B51,4,3),{"Jan","Feb","Mar","Apr","May","Jun","Jul","Aug","Sep","Oct","Nov","Dec"},0),VALUE(LEFT(B51,2))))) -> 45928
A52: ORD10718 | B52: 2025-04-01 | C52: 22:42 | D52: C0166 | E52: Wok & Roll | F52: Bengaluru | G52: Chinese | H52: 2 | I52: 240 | J52: 75 | K52: UPI | L52: Delivered | M52: 43 | N52: 3 | O52: =A52&"|"&B52&"|"&C52&"|"&D52&"|"&E52&"|"&F52&"|"&G52&"|"&H52&"|"&I52&"|"&J52&"|"&K52&"|"&L52&"|"&M52&"|"&N52 -> ORD10718|2025-04-01|22:42|C0166|Wok & Roll|Bengaluru|Chinese|2|240|75|UPI|Delivered|43|3 | P52: =IF(COUNTIF($O$2:O52,O52)>1,"DUP","OK") -> OK | Q52: =COUNTBLANK(A52:N52) -> 0 | R52: =IF(A52="",0,COUNTIFS($A$2:$A$3058,A52,$P$2:$P$3058,"OK")) -> 1 | S52: =IF(OR(A52="",P52="DUP",R52<2),"",IF(Q52=_xlfn.MINIFS($Q$2:$Q$3058,$A$2:$A$3058,A52,$P$2:$P$3058,"OK"),"KEEP","DROP")) | T52: =IF(A52="",1,0) -> 0 | U52: =IF(D52="",1,0) -> 0 | V52: =IF(E52="",1,0) -> 0 | W52: =IF(OR(H52<1,H52>10),1,0) -> 0 | X52: =IF(OR(I52<=0,I52>1500),1,0) -> 0 | Y52: =IF(J52>H52*I52,1,0) -> 0 | Z52: =IF(AND(N52<>"",OR(N52<1,N52>5)),1,0) -> 0 | AA52: =IF(AND(M52<>"",OR(M52<5,M52>180)),1,0) -> 0 | AB52: =IF(P52="DUP","Exact duplicate row",IF(T52=1,"Missing Order ID",IF(S52="DROP","Duplicate Order ID (less complete row)",IF(U52=1,"Missing Customer ID",IF(V52=1,"Missing Restaurant name",IF(W52=1,"Invalid/outlier quantity",IF(X52=1,"Invalid/outlier unit price",IF(Y52=1,"Discount greater than order value","")))))))) | AC52: =IF(AB52="","KEEP","DROP") -> KEEP | AD52: =IF(TRIM(F52)="",IFERROR(INDEX(Map_Tables!$I$4:$I$37,MATCH(TRIM(E52),Map_Tables!$G$4:$G$37,0)),""),IFERROR(INDEX(Map_Tables!$B$4:$B$18,MATCH(TRIM(F52),Map_Tables!$A$4:$A$18,0)),"CHECK")) -> Bengaluru | AE52: =IF(TRIM(E52)="","",IFERROR(INDEX(Map_Tables!$H$4:$H$37,MATCH(TRIM(E52),Map_Tables!$G$4:$G$37,0)),"CHECK")) -> Wok & Roll | AF52: =IF(TRIM(K52)="","Unknown",IFERROR(INDEX(Map_Tables!$E$4:$E$15,MATCH(TRIM(K52),Map_Tables!$D$4:$D$15,0)),"CHECK")) -> UPI | AG52: =IF(LEFT(LOWER(TRIM(L52)),6)="cancel","Cancelled","Delivered") -> Delivered | AH52: =IF(ISNUMBER(SEARCH("/",B52)),DATE(VALUE(RIGHT(B52,4)),VALUE(MID(B52,4,2)),VALUE(LEFT(B52,2))),IF(MID(B52,5,1)="-",DATE(VALUE(LEFT(B52,4)),VALUE(MID(B52,6,2)),VALUE(RIGHT(B52,2))),DATE(VALUE(RIGHT(B52,4)),MATCH(MID(B52,4,3),{"Jan","Feb","Mar","Apr","May","Jun","Jul","Aug","Sep","Oct","Nov","Dec"},0),VALUE(LEFT(B52,2))))) -> 45748
A53: ORD10276 | B53: 2025-02-07 | C53: 18:00 | D53: C1426 | E53: Curry Leaf Kitchen | F53: Mumbai | G53: North Indian | H53: 1 | I53: 220 | J53: 30 | K53: UPI | L53: Delivered | M53: 36 | N53: 4 | O53: =A53&"|"&B53&"|"&C53&"|"&D53&"|"&E53&"|"&F53&"|"&G53&"|"&H53&"|"&I53&"|"&J53&"|"&K53&"|"&L53&"|"&M53&"|"&N53 -> ORD10276|2025-02-07|18:00|C1426|Curry Leaf Kitchen|Mumbai|North Indian|1|220|30|UPI|Delivered|36|4 | P53: =IF(COUNTIF($O$2:O53,O53)>1,"DUP","OK") -> OK | Q53: =COUNTBLANK(A53:N53) -> 0 | R53: =IF(A53="",0,COUNTIFS($A$2:$A$3058,A53,$P$2:$P$3058,"OK")) -> 1 | S53: =IF(OR(A53="",P53="DUP",R53<2),"",IF(Q53=_xlfn.MINIFS($Q$2:$Q$3058,$A$2:$A$3058,A53,$P$2:$P$3058,"OK"),"KEEP","DROP")) | T53: =IF(A53="",1,0) -> 0 | U53: =IF(D53="",1,0) -> 0 | V53: =IF(E53="",1,0) -> 0 | W53: =IF(OR(H53<1,H53>10),1,0) -> 0 | X53: =IF(OR(I53<=0,I53>1500),1,0) -> 0 | Y53: =IF(J53>H53*I53,1,0) -> 0 | Z53: =IF(AND(N53<>"",OR(N53<1,N53>5)),1,0) -> 0 | AA53: =IF(AND(M53<>"",OR(M53<5,M53>180)),1,0) -> 0 | AB53: =IF(P53="DUP","Exact duplicate row",IF(T53=1,"Missing Order ID",IF(S53="DROP","Duplicate Order ID (less complete row)",IF(U53=1,"Missing Customer ID",IF(V53=1,"Missing Restaurant name",IF(W53=1,"Invalid/outlier quantity",IF(X53=1,"Invalid/outlier unit price",IF(Y53=1,"Discount greater than order value","")))))))) | AC53: =IF(AB53="","KEEP","DROP") -> KEEP | AD53: =IF(TRIM(F53)="",IFERROR(INDEX(Map_Tables!$I$4:$I$37,MATCH(TRIM(E53),Map_Tables!$G$4:$G$37,0)),""),IFERROR(INDEX(Map_Tables!$B$4:$B$18,MATCH(TRIM(F53),Map_Tables!$A$4:$A$18,0)),"CHECK")) -> Mumbai | AE53: =IF(TRIM(E53)="","",IFERROR(INDEX(Map_Tables!$H$4:$H$37,MATCH(TRIM(E53),Map_Tables!$G$4:$G$37,0)),"CHECK")) -> Curry Leaf Kitchen | AF53: =IF(TRIM(K53)="","Unknown",IFERROR(INDEX(Map_Tables!$E$4:$E$15,MATCH(TRIM(K53),Map_Tables!$D$4:$D$15,0)),"CHECK")) -> UPI | AG53: =IF(LEFT(LOWER(TRIM(L53)),6)="cancel","Cancelled","Delivered") -> Delivered | AH53: =IF(ISNUMBER(SEARCH("/",B53)),DATE(VALUE(RIGHT(B53,4)),VALUE(MID(B53,4,2)),VALUE(LEFT(B53,2))),IF(MID(B53,5,1)="-",DATE(VALUE(LEFT(B53,4)),VALUE(MID(B53,6,2)),VALUE(RIGHT(B53,2))),DATE(VALUE(RIGHT(B53,4)),MATCH(MID(B53,4,3),{"Jan","Feb","Mar","Apr","May","Jun","Jul","Aug","Sep","Oct","Nov","Dec"},0),VALUE(LEFT(B53,2))))) -> 45695
A54: ORD10416 | B54: 2025-02-25 | C54: 18:58 | D54: C0410 | E54: Madras Biryani Co | F54: Chennai | G54: Biryani | H54: 1 | I54: 290 | J54: 116 | K54: UPI | L54: Delivered | M54: 26 | N54: 2 | O54: =A54&"|"&B54&"|"&C54&"|"&D54&"|"&E54&"|"&F54&"|"&G54&"|"&H54&"|"&I54&"|"&J54&"|"&K54&"|"&L54&"|"&M54&"|"&N54 -> ORD10416|2025-02-25|18:58|C0410|Madras Biryani Co|Chennai|Biryani|1|290|116|UPI|Delivered|26|2 | P54: =IF(COUNTIF($O$2:O54,O54)>1,"DUP","OK") -> OK | Q54: =COUNTBLANK(A54:N54) -> 0 | R54: =IF(A54="",0,COUNTIFS($A$2:$A$3058,A54,$P$2:$P$3058,"OK")) -> 1 | S54: =IF(OR(A54="",P54="DUP",R54<2),"",IF(Q54=_xlfn.MINIFS($Q$2:$Q$3058,$A$2:$A$3058,A54,$P$2:$P$3058,"OK"),"KEEP","DROP")) | T54: =IF(A54="",1,0) -> 0 | U54: =IF(D54="",1,0) -> 0 | V54: =IF(E54="",1,0) -> 0 | W54: =IF(OR(H54<1,H54>10),1,0) -> 0 | X54: =IF(OR(I54<=0,I54>1500),1,0) -> 0 | Y54: =IF(J54>H54*I54,1,0) -> 0 | Z54: =IF(AND(N54<>"",OR(N54<1,N54>5)),1,0) -> 0 | AA54: =IF(AND(M54<>"",OR(M54<5,M54>180)),1,0) -> 0 | AB54: =IF(P54="DUP","Exact duplicate row",IF(T54=1,"Missing Order ID",IF(S54="DROP","Duplicate Order ID (less complete row)",IF(U54=1,"Missing Customer ID",IF(V54=1,"Missing Restaurant name",IF(W54=1,"Invalid/outlier quantity",IF(X54=1,"Invalid/outlier unit price",IF(Y54=1,"Discount greater than order value","")))))))) | AC54: =IF(AB54="","KEEP","DROP") -> KEEP | AD54: =IF(TRIM(F54)="",IFERROR(INDEX(Map_Tables!$I$4:$I$37,MATCH(TRIM(E54),Map_Tables!$G$4:$G$37,0)),""),IFERROR(INDEX(Map_Tables!$B$4:$B$18,MATCH(TRIM(F54),Map_Tables!$A$4:$A$18,0)),"CHECK")) -> Chennai | AE54: =IF(TRIM(E54)="","",IFERROR(INDEX(Map_Tables!$H$4:$H$37,MATCH(TRIM(E54),Map_Tables!$G$4:$G$37,0)),"CHECK")) -> Madras Biryani Co | AF54: =IF(TRIM(K54)="","Unknown",IFERROR(INDEX(Map_Tables!$E$4:$E$15,MATCH(TRIM(K54),Map_Tables!$D$4:$D$15,0)),"CHECK")) -> UPI | AG54: =IF(LEFT(LOWER(TRIM(L54)),6)="cancel","Cancelled","Delivered") -> Delivered | AH54: =IF(ISNUMBER(SEARCH("/",B54)),DATE(VALUE(RIGHT(B54,4)),VALUE(MID(B54,4,2)),VALUE(LEFT(B54,2))),IF(MID(B54,5,1)="-",DATE(VALUE(LEFT(B54,4)),VALUE(MID(B54,6,2)),VALUE(RIGHT(B54,2))),DATE(VALUE(RIGHT(B54,4)),MATCH(MID(B54,4,3),{"Jan","Feb","Mar","Apr","May","Jun","Jul","Aug","Sep","Oct","Nov","Dec"},0),VALUE(LEFT(B54,2))))) -> 45713
A55: ORD12262 | B55: 2025-10-14 | C55: 10:45 | D55: C1122 | E55: Dosa Darbar | F55: Bengaluru | G55: South Indian | H55: 1 | I55: 120 | J55: 20 | K55: UPI | L55: Cancelled | O55: =A55&"|"&B55&"|"&C55&"|"&D55&"|"&E55&"|"&F55&"|"&G55&"|"&H55&"|"&I55&"|"&J55&"|"&K55&"|"&L55&"|"&M55&"|"&N55 -> ORD12262|2025-10-14|10:45|C1122|Dosa Darbar|Bengaluru|South Indian|1|120|20|UPI |Cancelled|| | P55: =IF(COUNTIF($O$2:O55,O55)>1,"DUP","OK") -> OK | Q55: =COUNTBLANK(A55:N55) -> 2 | R55: =IF(A55="",0,COUNTIFS($A$2:$A$3058,A55,$P$2:$P$3058,"OK")) -> 1 | S55: =IF(OR(A55="",P55="DUP",R55<2),"",IF(Q55=_xlfn.MINIFS($Q$2:$Q$3058,$A$2:$A$3058,A55,$P$2:$P$3058,"OK"),"KEEP","DROP")) | T55: =IF(A55="",1,0) -> 0 | U55: =IF(D55="",1,0) -> 0 | V55: =IF(E55="",1,0) -> 0 | W55: =IF(OR(H55<1,H55>10),1,0) -> 0 | X55: =IF(OR(I55<=0,I55>1500),1,0) -> 0 | Y55: =IF(J55>H55*I55,1,0) -> 0 | Z55: =IF(AND(N55<>"",OR(N55<1,N55>5)),1,0) -> 0 | AA55: =IF(AND(M55<>"",OR(M55<5,M55>180)),1,0) -> 0 | AB55: =IF(P55="DUP","Exact duplicate row",IF(T55=1,"Missing Order ID",IF(S55="DROP","Duplicate Order ID (less complete row)",IF(U55=1,"Missing Customer ID",IF(V55=1,"Missing Restaurant name",IF(W55=1,"Invalid/outlier quantity",IF(X55=1,"Invalid/outlier unit price",IF(Y55=1,"Discount greater than order value","")))))))) | AC55: =IF(AB55="","KEEP","DROP") -> KEEP | AD55: =IF(TRIM(F55)="",IFERROR(INDEX(Map_Tables!$I$4:$I$37,MATCH(TRIM(E55),Map_Tables!$G$4:$G$37,0)),""),IFERROR(INDEX(Map_Tables!$B$4:$B$18,MATCH(TRIM(F55),Map_Tables!$A$4:$A$18,0)),"CHECK")) -> Bengaluru | AE55: =IF(TRIM(E55)="","",IFERROR(INDEX(Map_Tables!$H$4:$H$37,MATCH(TRIM(E55),Map_Tables!$G$4:$G$37,0)),"CHECK")) -> Dosa Darbar | AF55: =IF(TRIM(K55)="","Unknown",IFERROR(INDEX(Map_Tables!$E$4:$E$15,MATCH(TRIM(K55),Map_Tables!$D$4:$D$15,0)),"CHECK")) -> UPI | AG55: =IF(LEFT(LOWER(TRIM(L55)),6)="cancel","Cancelled","Delivered") -> Cancelled | AH55: =IF(ISNUMBER(SEARCH("/",B55)),DATE(VALUE(RIGHT(B55,4)),VALUE(MID(B55,4,2)),VALUE(LEFT(B55,2))),IF(MID(B55,5,1)="-",DATE(VALUE(LEFT(B55,4)),VALUE(MID(B55,6,2)),VALUE(RIGHT(B55,2))),DATE(VALUE(RIGHT(B55,4)),MATCH(MID(B55,4,3),{"Jan","Feb","Mar","Apr","May","Jun","Jul","Aug","Sep","Oct","Nov","Dec"},0),VALUE(LEFT(B55,2))))) -> 45944
A56: ORD12920 | B56: 23-Dec-2025 | C56: 00:41 | D56: C1386 | E56: Green Bowl Kitchen | F56: Chennai | G56: Healthy Food | H56: 1 | I56: 250 | J56: 0 | K56: UPI | L56: Delivered | M56: 39 | N56: 5 | O56: =A56&"|"&B56&"|"&C56&"|"&D56&"|"&E56&"|"&F56&"|"&G56&"|"&H56&"|"&I56&"|"&J56&"|"&K56&"|"&L56&"|"&M56&"|"&N56 -> ORD12920|23-Dec-2025|00:41|C1386|Green Bowl Kitchen|Chennai|Healthy Food|1|250|0|UPI|Delivered|39|5 | P56: =IF(COUNTIF($O$2:O56,O56)>1,"DUP","OK") -> OK | Q56: =COUNTBLANK(A56:N56) -> 0 | R56: =IF(A56="",0,COUNTIFS($A$2:$A$3058,A56,$P$2:$P$3058,"OK")) -> 1 | S56: =IF(OR(A56="",P56="DUP",R56<2),"",IF(Q56=_xlfn.MINIFS($Q$2:$Q$3058,$A$2:$A$3058,A56,$P$2:$P$3058,"OK"),"KEEP","DROP")) | T56: =IF(A56="",1,0) -> 0 | U56: =IF(D56="",1,0) -> 0 | V56: =IF(E56="",1,0) -> 0 | W56: =IF(OR(H56<1,H56>10),1,0) -> 0 | X56: =IF(OR(I56<=0,I56>1500),1,0) -> 0 | Y56: =IF(J56>H56*I56,1,0) -> 0 | Z56: =IF(AND(N56<>"",OR(N56<1,N56>5)),1,0) -> 0 | AA56: =IF(AND(M56<>"",OR(M56<5,M56>180)),1,0) -> 0 | AB56: =IF(P56="DUP","Exact duplicate row",IF(T56=1,"Missing Order ID",IF(S56="DROP","Duplicate Order ID (less complete row)",IF(U56=1,"Missing Customer ID",IF(V56=1,"Missing Restaurant name",IF(W56=1,"Invalid/outlier quantity",IF(X56=1,"Invalid/outlier unit price",IF(Y56=1,"Discount greater than order value","")))))))) | AC56: =IF(AB56="","KEEP","DROP") -> KEEP | AD56: =IF(TRIM(F56)="",IFERROR(INDEX(Map_Tables!$I$4:$I$37,MATCH(TRIM(E56),Map_Tables!$G$4:$G$37,0)),""),IFERROR(INDEX(Map_Tables!$B$4:$B$18,MATCH(TRIM(F56),Map_Tables!$A$4:$A$18,0)),"CHECK")) -> Chennai | AE56: =IF(TRIM(E56)="","",IFERROR(INDEX(Map_Tables!$H$4:$H$37,MATCH(TRIM(E56),Map_Tables!$G$4:$G$37,0)),"CHECK")) -> Green Bowl Kitchen | AF56: =IF(TRIM(K56)="","Unknown",IFERROR(INDEX(Map_Tables!$E$4:$E$15,MATCH(TRIM(K56),Map_Tables!$D$4:$D$15,0)),"CHECK")) -> UPI | AG56: =IF(LEFT(LOWER(TRIM(L56)),6)="cancel","Cancelled","Delivered") -> Delivered | AH56: =IF(ISNUMBER(SEARCH("/",B56)),DATE(VALUE(RIGHT(B56,4)),VALUE(MID(B56,4,2)),VALUE(LEFT(B56,2))),IF(MID(B56,5,1)="-",DATE(VALUE(LEFT(B56,4)),VALUE(MID(B56,6,2)),VALUE(RIGHT(B56,2))),DATE(VALUE(RIGHT(B56,4)),MATCH(MID(B56,4,3),{"Jan","Feb","Mar","Apr","May","Jun","Jul","Aug","Sep","Oct","Nov","Dec"},0),VALUE(LEFT(B56,2))))) -> 46014
A57: ORD11814 | B57: 2025-08-25 | C57: 10:24 | D57: C1150 | E57: Pav Bhaji Point | F57: Mumbai | G57: Street Food | H57: 1 | I57: 120 | J57: 0 | K57: UPI | L57: Delivered | M57: 48 | N57: 3 | O57: =A57&"|"&B57&"|"&C57&"|"&D57&"|"&E57&"|"&F57&"|"&G57&"|"&H57&"|"&I57&"|"&J57&"|"&K57&"|"&L57&"|"&M57&"|"&N57 -> ORD11814|2025-08-25|10:24|C1150| Pav Bhaji Point|Mumbai|Street Food|1|120|0|UPI|Delivered|48|3 | P57: =IF(COUNTIF($O$2:O57,O57)>1,"DUP","OK") -> OK | Q57: =COUNTBLANK(A57:N57) -> 0 | R57: =IF(A57="",0,COUNTIFS($A$2:$A$3058,A57,$P$2:$P$3058,"OK")) -> 1 | S57: =IF(OR(A57="",P57="DUP",R57<2),"",IF(Q57=_xlfn.MINIFS($Q$2:$Q$3058,$A$2:$A$3058,A57,$P$2:$P$3058,"OK"),"KEEP","DROP")) | T57: =IF(A57="",1,0) -> 0 | U57: =IF(D57="",1,0) -> 0 | V57: =IF(E57="",1,0) -> 0 | W57: =IF(OR(H57<1,H57>10),1,0) -> 0 | X57: =IF(OR(I57<=0,I57>1500),1,0) -> 0 | Y57: =IF(J57>H57*I57,1,0) -> 0 | Z57: =IF(AND(N57<>"",OR(N57<1,N57>5)),1,0) -> 0 | AA57: =IF(AND(M57<>"",OR(M57<5,M57>180)),1,0) -> 0 | AB57: =IF(P57="DUP","Exact duplicate row",IF(T57=1,"Missing Order ID",IF(S57="DROP","Duplicate Order ID (less complete row)",IF(U57=1,"Missing Customer ID",IF(V57=1,"Missing Restaurant name",IF(W57=1,"Invalid/outlier quantity",IF(X57=1,"Invalid/outlier unit price",IF(Y57=1,"Discount greater than order value","")))))))) | AC57: =IF(AB57="","KEEP","DROP") -> KEEP | AD57: =IF(TRIM(F57)="",IFERROR(INDEX(Map_Tables!$I$4:$I$37,MATCH(TRIM(E57),Map_Tables!$G$4:$G$37,0)),""),IFERROR(INDEX(Map_Tables!$B$4:$B$18,MATCH(TRIM(F57),Map_Tables!$A$4:$A$18,0)),"CHECK")) -> Mumbai | AE57: =IF(TRIM(E57)="","",IFERROR(INDEX(Map_Tables!$H$4:$H$37,MATCH(TRIM(E57),Map_Tables!$G$4:$G$37,0)),"CHECK")) -> Pav Bhaji Point | AF57: =IF(TRIM(K57)="","Unknown",IFERROR(INDEX(Map_Tables!$E$4:$E$15,MATCH(TRIM(K57),Map_Tables!$D$4:$D$15,0)),"CHECK")) -> UPI | AG57: =IF(LEFT(LOWER(TRIM(L57)),6)="cancel","Cancelled","Delivered") -> Delivered | AH57: =IF(ISNUMBER(SEARCH("/",B57)),DATE(VALUE(RIGHT(B57,4)),VALUE(MID(B57,4,2)),VALUE(LEFT(B57,2))),IF(MID(B57,5,1)="-",DATE(VALUE(LEFT(B57,4)),VALUE(MID(B57,6,2)),VALUE(RIGHT(B57,2))),DATE(VALUE(RIGHT(B57,4)),MATCH(MID(B57,4,3),{"Jan","Feb","Mar","Apr","May","Jun","Jul","Aug","Sep","Oct","Nov","Dec"},0),VALUE(LEFT(B57,2))))) -> 45894
A58: ORD11808 | B58: 2025-08-24 | C58: 19:43 | D58: C0418 | F58: Pune | G58: Street Food | H58: 1 | I58: 125 | J58: 30 | K58: UPI | L58: Delivered | M58: 39 | N58: 4 | O58: =A58&"|"&B58&"|"&C58&"|"&D58&"|"&E58&"|"&F58&"|"&G58&"|"&H58&"|"&I58&"|"&J58&"|"&K58&"|"&L58&"|"&M58&"|"&N58 -> ORD11808|2025-08-24|19:43|C0418||Pune|Street Food|1|125|30|UPI|Delivered|39|4 | P58: =IF(COUNTIF($O$2:O58,O58)>1,"DUP","OK") -> OK | Q58: =COUNTBLANK(A58:N58) -> 1 | R58: =IF(A58="",0,COUNTIFS($A$2:$A$3058,A58,$P$2:$P$3058,"OK")) -> 1 | S58: =IF(OR(A58="",P58="DUP",R58<2),"",IF(Q58=_xlfn.MINIFS($Q$2:$Q$3058,$A$2:$A$3058,A58,$P$2:$P$3058,"OK"),"KEEP","DROP")) | T58: =IF(A58="",1,0) -> 0 | U58: =IF(D58="",1,0) -> 0 | V58: =IF(E58="",1,0) -> 1 | W58: =IF(OR(H58<1,H58>10),1,0) -> 0 | X58: =IF(OR(I58<=0,I58>1500),1,0) -> 0 | Y58: =IF(J58>H58*I58,1,0) -> 0 | Z58: =IF(AND(N58<>"",OR(N58<1,N58>5)),1,0) -> 0 | AA58: =IF(AND(M58<>"",OR(M58<5,M58>180)),1,0) -> 0 | AB58: =IF(P58="DUP","Exact duplicate row",IF(T58=1,"Missing Order ID",IF(S58="DROP","Duplicate Order ID (less complete row)",IF(U58=1,"Missing Customer ID",IF(V58=1,"Missing Restaurant name",IF(W58=1,"Invalid/outlier quantity",IF(X58=1,"Invalid/outlier unit price",IF(Y58=1,"Discount greater than order value","")))))))) -> Missing Restaurant name | AC58: =IF(AB58="","KEEP","DROP") -> DROP | AD58: =IF(TRIM(F58)="",IFERROR(INDEX(Map_Tables!$I$4:$I$37,MATCH(TRIM(E58),Map_Tables!$G$4:$G$37,0)),""),IFERROR(INDEX(Map_Tables!$B$4:$B$18,MATCH(TRIM(F58),Map_Tables!$A$4:$A$18,0)),"CHECK")) -> Pune | AE58: =IF(TRIM(E58)="","",IFERROR(INDEX(Map_Tables!$H$4:$H$37,MATCH(TRIM(E58),Map_Tables!$G$4:$G$37,0)),"CHECK")) | AF58: =IF(TRIM(K58)="","Unknown",IFERROR(INDEX(Map_Tables!$E$4:$E$15,MATCH(TRIM(K58),Map_Tables!$D$4:$D$15,0)),"CHECK")) -> UPI | AG58: =IF(LEFT(LOWER(TRIM(L58)),6)="cancel","Cancelled","Delivered") -> Delivered | AH58: =IF(ISNUMBER(SEARCH("/",B58)),DATE(VALUE(RIGHT(B58,4)),VALUE(MID(B58,4,2)),VALUE(LEFT(B58,2))),IF(MID(B58,5,1)="-",DATE(VALUE(LEFT(B58,4)),VALUE(MID(B58,6,2)),VALUE(RIGHT(B58,2))),DATE(VALUE(RIGHT(B58,4)),MATCH(MID(B58,4,3),{"Jan","Feb","Mar","Apr","May","Jun","Jul","Aug","Sep","Oct","Nov","Dec"},0),VALUE(LEFT(B58,2))))) -> 45893
A59: ORD10096 | B59: 2025-01-12 | C59: 22:59 | D59: C0640 | E59: Burger Barn | F59: Delhi | G59: Burgers | H59: 4 | I59: 215 | J59: 0 | K59: Wallet | L59: Delivered | M59: 34 | N59: 5 | O59: =A59&"|"&B59&"|"&C59&"|"&D59&"|"&E59&"|"&F59&"|"&G59&"|"&H59&"|"&I59&"|"&J59&"|"&K59&"|"&L59&"|"&M59&"|"&N59 -> ORD10096|2025-01-12|22:59|C0640|Burger Barn|Delhi|Burgers|4|215|0|Wallet|Delivered|34|5 | P59: =IF(COUNTIF($O$2:O59,O59)>1,"DUP","OK") -> OK | Q59: =COUNTBLANK(A59:N59) -> 0 | R59: =IF(A59="",0,COUNTIFS($A$2:$A$3058,A59,$P$2:$P$3058,"OK")) -> 1 | S59: =IF(OR(A59="",P59="DUP",R59<2),"",IF(Q59=_xlfn.MINIFS($Q$2:$Q$3058,$A$2:$A$3058,A59,$P$2:$P$3058,"OK"),"KEEP","DROP")) | T59: =IF(A59="",1,0) -> 0 | U59: =IF(D59="",1,0) -> 0 | V59: =IF(E59="",1,0) -> 0 | W59: =IF(OR(H59<1,H59>10),1,0) -> 0 | X59: =IF(OR(I59<=0,I59>1500),1,0) -> 0 | Y59: =IF(J59>H59*I59,1,0) -> 0 | Z59: =IF(AND(N59<>"",OR(N59<1,N59>5)),1,0) -> 0 | AA59: =IF(AND(M59<>"",OR(M59<5,M59>180)),1,0) -> 0 | AB59: =IF(P59="DUP","Exact duplicate row",IF(T59=1,"Missing Order ID",IF(S59="DROP","Duplicate Order ID (less complete row)",IF(U59=1,"Missing Customer ID",IF(V59=1,"Missing Restaurant name",IF(W59=1,"Invalid/outlier quantity",IF(X59=1,"Invalid/outlier unit price",IF(Y59=1,"Discount greater than order value","")))))))) | AC59: =IF(AB59="","KEEP","DROP") -> KEEP | AD59: =IF(TRIM(F59)="",IFERROR(INDEX(Map_Tables!$I$4:$I$37,MATCH(TRIM(E59),Map_Tables!$G$4:$G$37,0)),""),IFERROR(INDEX(Map_Tables!$B$4:$B$18,MATCH(TRIM(F59),Map_Tables!$A$4:$A$18,0)),"CHECK")) -> Delhi | AE59: =IF(TRIM(E59)="","",IFERROR(INDEX(Map_Tables!$H$4:$H$37,MATCH(TRIM(E59),Map_Tables!$G$4:$G$37,0)),"CHECK")) -> Burger Barn | AF59: =IF(TRIM(K59)="","Unknown",IFERROR(INDEX(Map_Tables!$E$4:$E$15,MATCH(TRIM(K59),Map_Tables!$D$4:$D$15,0)),"CHECK")) -> Wallet | AG59: =IF(LEFT(LOWER(TRIM(L59)),6)="cancel","Cancelled","Delivered") -> Delivered | AH59: =IF(ISNUMBER(SEARCH("/",B59)),DATE(VALUE(RIGHT(B59,4)),VALUE(MID(B59,4,2)),VALUE(LEFT(B59,2))),IF(MID(B59,5,1)="-",DATE(VALUE(LEFT(B59,4)),VALUE(MID(B59,6,2)),VALUE(RIGHT(B59,2))),DATE(VALUE(RIGHT(B59,4)),MATCH(MID(B59,4,3),{"Jan","Feb","Mar","Apr","May","Jun","Jul","Aug","Sep","Oct","Nov","Dec"},0),VALUE(LEFT(B59,2))))) -> 45669
A60: ORD11492 | B60: 2025-07-13 | C60: 11:17 | D60: C0885 | E60: Dosa Darbar | F60: Bengaluru | G60: South Indian | H60: 5 | I60: 120 | J60: 40 | K60: cash on delivery | L60: Delivered | M60: 34 | N60: 4 | O60: =A60&"|"&B60&"|"&C60&"|"&D60&"|"&E60&"|"&F60&"|"&G60&"|"&H60&"|"&I60&"|"&J60&"|"&K60&"|"&L60&"|"&M60&"|"&N60 -> ORD11492|2025-07-13|11:17|C0885|Dosa Darbar|Bengaluru|South Indian|5|120|40|cash on delivery|Delivered|34|4 | P60: =IF(COUNTIF($O$2:O60,O60)>1,"DUP","OK") -> OK | Q60: =COUNTBLANK(A60:N60) -> 0 | R60: =IF(A60="",0,COUNTIFS($A$2:$A$3058,A60,$P$2:$P$3058,"OK")) -> 1 | S60: =IF(OR(A60="",P60="DUP",R60<2),"",IF(Q60=_xlfn.MINIFS($Q$2:$Q$3058,$A$2:$A$3058,A60,$P$2:$P$3058,"OK"),"KEEP","DROP")) | T60: =IF(A60="",1,0) -> 0 | U60: =IF(D60="",1,0) -> 0 | V60: =IF(E60="",1,0) -> 0 | W60: =IF(OR(H60<1,H60>10),1,0) -> 0 | X60: =IF(OR(I60<=0,I60>1500),1,0) -> 0 | Y60: =IF(J60>H60*I60,1,0) -> 0 | Z60: =IF(AND(N60<>"",OR(N60<1,N60>5)),1,0) -> 0 | AA60: =IF(AND(M60<>"",OR(M60<5,M60>180)),1,0) -> 0 | AB60: =IF(P60="DUP","Exact duplicate row",IF(T60=1,"Missing Order ID",IF(S60="DROP","Duplicate Order ID (less complete row)",IF(U60=1,"Missing Customer ID",IF(V60=1,"Missing Restaurant name",IF(W60=1,"Invalid/outlier quantity",IF(X60=1,"Invalid/outlier unit price",IF(Y60=1,"Discount greater than order value","")))))))) | AC60: =IF(AB60="","KEEP","DROP") -> KEEP | AD60: =IF(TRIM(F60)="",IFERROR(INDEX(Map_Tables!$I$4:$I$37,MATCH(TRIM(E60),Map_Tables!$G$4:$G$37,0)),""),IFERROR(INDEX(Map_Tables!$B$4:$B$18,MATCH(TRIM(F60),Map_Tables!$A$4:$A$18,0)),"CHECK")) -> Bengaluru | AE60: =IF(TRIM(E60)="","",IFERROR(INDEX(Map_Tables!$H$4:$H$37,MATCH(TRIM(E60),Map_Tables!$G$4:$G$37,0)),"CHECK")) -> Dosa Darbar | AF60: =IF(TRIM(K60)="","Unknown",IFERROR(INDEX(Map_Tables!$E$4:$E$15,MATCH(TRIM(K60),Map_Tables!$D$4:$D$15,0)),"CHECK")) -> Cash on Delivery | AG60: =IF(LEFT(LOWER(TRIM(L60)),6)="cancel","Cancelled","Delivered") -> Delivered | AH60: =IF(ISNUMBER(SEARCH("/",B60)),DATE(VALUE(RIGHT(B60,4)),VALUE(MID(B60,4,2)),VALUE(LEFT(B60,2))),IF(MID(B60,5,1)="-",DATE(VALUE(LEFT(B60,4)),VALUE(MID(B60,6,2)),VALUE(RIGHT(B60,2))),DATE(VALUE(RIGHT(B60,4)),MATCH(MID(B60,4,3),{"Jan","Feb","Mar","Apr","May","Jun","Jul","Aug","Sep","Oct","Nov","Dec"},0),VALUE(LEFT(B60,2))))) -> 45851
A61: ORD10604 | B61: 2025-03-17 | C61: 22:51 | D61: C0480 | E61: Chaat Corner | F61: Delhi | G61: Street Food | H61: 2 | I61: 100 | J61: 0 | K61: UPI | L61: Delivered | M61: 45 | N61: 3 | O61: =A61&"|"&B61&"|"&C61&"|"&D61&"|"&E61&"|"&F61&"|"&G61&"|"&H61&"|"&I61&"|"&J61&"|"&K61&"|"&L61&"|"&M61&"|"&N61 -> ORD10604|2025-03-17|22:51|C0480|Chaat Corner|Delhi|Street Food|2|100|0|UPI|Delivered|45|3 | P61: =IF(COUNTIF($O$2:O61,O61)>1,"DUP","OK") -> OK | Q61: =COUNTBLANK(A61:N61) -> 0 | R61: =IF(A61="",0,COUNTIFS($A$2:$A$3058,A61,$P$2:$P$3058,"OK")) -> 1 | S61: =IF(OR(A61="",P61="DUP",R61<2),"",IF(Q61=_xlfn.MINIFS($Q$2:$Q$3058,$A$2:$A$3058,A61,$P$2:$P$3058,"OK"),"KEEP","DROP")) | T61: =IF(A61="",1,0) -> 0 | U61: =IF(D61="",1,0) -> 0 | V61: =IF(E61="",1,0) -> 0 | W61: =IF(OR(H61<1,H61>10),1,0) -> 0 | X61: =IF(OR(I61<=0,I61>1500),1,0) -> 0 | Y61: =IF(J61>H61*I61,1,0) -> 0 | Z61: =IF(AND(N61<>"",OR(N61<1,N61>5)),1,0) -> 0 | AA61: =IF(AND(M61<>"",OR(M61<5,M61>180)),1,0) -> 0 | AB61: =IF(P61="DUP","Exact duplicate row",IF(T61=1,"Missing Order ID",IF(S61="DROP","Duplicate Order ID (less complete row)",IF(U61=1,"Missing Customer ID",IF(V61=1,"Missing Restaurant name",IF(W61=1,"Invalid/outlier quantity",IF(X61=1,"Invalid/outlier unit price",IF(Y61=1,"Discount greater than order value","")))))))) | AC61: =IF(AB61="","KEEP","DROP") -> KEEP | AD61: =IF(TRIM(F61)="",IFERROR(INDEX(Map_Tables!$I$4:$I$37,MATCH(TRIM(E61),Map_Tables!$G$4:$G$37,0)),""),IFERROR(INDEX(Map_Tables!$B$4:$B$18,MATCH(TRIM(F61),Map_Tables!$A$4:$A$18,0)),"CHECK")) -> Delhi | AE61: =IF(TRIM(E61)="","",IFERROR(INDEX(Map_Tables!$H$4:$H$37,MATCH(TRIM(E61),Map_Tables!$G$4:$G$37,0)),"CHECK")) -> Chaat Corner | AF61: =IF(TRIM(K61)="","Unknown",IFERROR(INDEX(Map_Tables!$E$4:$E$15,MATCH(TRIM(K61),Map_Tables!$D$4:$D$15,0)),"CHECK")) -> UPI | AG61: =IF(LEFT(LOWER(TRIM(L61)),6)="cancel","Cancelled","Delivered") -> Delivered | AH61: =IF(ISNUMBER(SEARCH("/",B61)),DATE(VALUE(RIGHT(B61,4)),VALUE(MID(B61,4,2)),VALUE(LEFT(B61,2))),IF(MID(B61,5,1)="-",DATE(VALUE(LEFT(B61,4)),VALUE(MID(B61,6,2)),VALUE(RIGHT(B61,2))),DATE(VALUE(RIGHT(B61,4)),MATCH(MID(B61,4,3),{"Jan","Feb","Mar","Apr","May","Jun","Jul","Aug","Sep","Oct","Nov","Dec"},0),VALUE(LEFT(B61,2))))) -> 45733
A62: ORD10528 | B62: 2025-03-09 | C62: 20:28 | D62: C1284 | E62: Spice Junction | F62: BLR | G62: North Indian | H62: 2 | I62: 215 | J62: 40 | K62: Debit Card | L62: Delivered | M62: 30 | N62: 3 | O62: =A62&"|"&B62&"|"&C62&"|"&D62&"|"&E62&"|"&F62&"|"&G62&"|"&H62&"|"&I62&"|"&J62&"|"&K62&"|"&L62&"|"&M62&"|"&N62 -> ORD10528|2025-03-09|20:28|C1284|Spice Junction|BLR|North Indian|2|215|40|Debit Card|Delivered|30|3 | P62: =IF(COUNTIF($O$2:O62,O62)>1,"DUP","OK") -> OK | Q62: =COUNTBLANK(A62:N62) -> 0 | R62: =IF(A62="",0,COUNTIFS($A$2:$A$3058,A62,$P$2:$P$3058,"OK")) -> 1 | S62: =IF(OR(A62="",P62="DUP",R62<2),"",IF(Q62=_xlfn.MINIFS($Q$2:$Q$3058,$A$2:$A$3058,A62,$P$2:$P$3058,"OK"),"KEEP","DROP")) | T62: =IF(A62="",1,0) -> 0 | U62: =IF(D62="",1,0) -> 0 | V62: =IF(E62="",1,0) -> 0 | W62: =IF(OR(H62<1,H62>10),1,0) -> 0 | X62: =IF(OR(I62<=0,I62>1500),1,0) -> 0 | Y62: =IF(J62>H62*I62,1,0) -> 0 | Z62: =IF(AND(N62<>"",OR(N62<1,N62>5)),1,0) -> 0 | AA62: =IF(AND(M62<>"",OR(M62<5,M62>180)),1,0) -> 0 | AB62: =IF(P62="DUP","Exact duplicate row",IF(T62=1,"Missing Order ID",IF(S62="DROP","Duplicate Order ID (less complete row)",IF(U62=1,"Missing Customer ID",IF(V62=1,"Missing Restaurant name",IF(W62=1,"Invalid/outlier quantity",IF(X62=1,"Invalid/outlier unit price",IF(Y62=1,"Discount greater than order value","")))))))) | AC62: =IF(AB62="","KEEP","DROP") -> KEEP | AD62: =IF(TRIM(F62)="",IFERROR(INDEX(Map_Tables!$I$4:$I$37,MATCH(TRIM(E62),Map_Tables!$G$4:$G$37,0)),""),IFERROR(INDEX(Map_Tables!$B$4:$B$18,MATCH(TRIM(F62),Map_Tables!$A$4:$A$18,0)),"CHECK")) -> Bengaluru | AE62: =IF(TRIM(E62)="","",IFERROR(INDEX(Map_Tables!$H$4:$H$37,MATCH(TRIM(E62),Map_Tables!$G$4:$G$37,0)),"CHECK")) -> Spice Junction | AF62: =IF(TRIM(K62)="","Unknown",IFERROR(INDEX(Map_Tables!$E$4:$E$15,MATCH(TRIM(K62),Map_Tables!$D$4:$D$15,0)),"CHECK")) -> Debit Card | AG62: =IF(LEFT(LOWER(TRIM(L62)),6)="cancel","Cancelled","Delivered") -> Delivered | AH62: =IF(ISNUMBER(SEARCH("/",B62)),DATE(VALUE(RIGHT(B62,4)),VALUE(MID(B62,4,2)),VALUE(LEFT(B62,2))),IF(MID(B62,5,1)="-",DATE(VALUE(LEFT(B62,4)),VALUE(MID(B62,6,2)),VALUE(RIGHT(B62,2))),DATE(VALUE(RIGHT(B62,4)),MATCH(MID(B62,4,3),{"Jan","Feb","Mar","Apr","May","Jun","Jul","Aug","Sep","Oct","Nov","Dec"},0),VALUE(LEFT(B62,2))))) -> 45725
A63: ORD11527 | B63: 2025-07-17 | C63: 19:34 | D63: C0965 | E63: Chaat Corner | F63: Delhi | G63: Street Food | H63: 1 | I63: 120 | J63: 0 | K63: credit card | L63: Delivered | M63: 51 | N63: 5 | O63: =A63&"|"&B63&"|"&C63&"|"&D63&"|"&E63&"|"&F63&"|"&G63&"|"&H63&"|"&I63&"|"&J63&"|"&K63&"|"&L63&"|"&M63&"|"&N63 -> ORD11527|2025-07-17|19:34|C0965|Chaat Corner|Delhi|Street Food|1|120|0|credit card|Delivered|51|5 | P63: =IF(COUNTIF($O$2:O63,O63)>1,"DUP","OK") -> OK | Q63: =COUNTBLANK(A63:N63) -> 0 | R63: =IF(A63="",0,COUNTIFS($A$2:$A$3058,A63,$P$2:$P$3058,"OK")) -> 1 | S63: =IF(OR(A63="",P63="DUP",R63<2),"",IF(Q63=_xlfn.MINIFS($Q$2:$Q$3058,$A$2:$A$3058,A63,$P$2:$P$3058,"OK"),"KEEP","DROP")) | T63: =IF(A63="",1,0) -> 0 | U63: =IF(D63="",1,0) -> 0 | V63: =IF(E63="",1,0) -> 0 | W63: =IF(OR(H63<1,H63>10),1,0) -> 0 | X63: =IF(OR(I63<=0,I63>1500),1,0) -> 0 | Y63: =IF(J63>H63*I63,1,0) -> 0 | Z63: =IF(AND(N63<>"",OR(N63<1,N63>5)),1,0) -> 0 | AA63: =IF(AND(M63<>"",OR(M63<5,M63>180)),1,0) -> 0 | AB63: =IF(P63="DUP","Exact duplicate row",IF(T63=1,"Missing Order ID",IF(S63="DROP","Duplicate Order ID (less complete row)",IF(U63=1,"Missing Customer ID",IF(V63=1,"Missing Restaurant name",IF(W63=1,"Invalid/outlier quantity",IF(X63=1,"Invalid/outlier unit price",IF(Y63=1,"Discount greater than order value","")))))))) | AC63: =IF(AB63="","KEEP","DROP") -> KEEP | AD63: =IF(TRIM(F63)="",IFERROR(INDEX(Map_Tables!$I$4:$I$37,MATCH(TRIM(E63),Map_Tables!$G$4:$G$37,0)),""),IFERROR(INDEX(Map_Tables!$B$4:$B$18,MATCH(TRIM(F63),Map_Tables!$A$4:$A$18,0)),"CHECK")) -> Delhi | AE63: =IF(TRIM(E63)="","",IFERROR(INDEX(Map_Tables!$H$4:$H$37,MATCH(TRIM(E63),Map_Tables!$G$4:$G$37,0)),"CHECK")) -> Chaat Corner | AF63: =IF(TRIM(K63)="","Unknown",IFERROR(INDEX(Map_Tables!$E$4:$E$15,MATCH(TRIM(K63),Map_Tables!$D$4:$D$15,0)),"CHECK")) -> Credit Card | AG63: =IF(LEFT(LOWER(TRIM(L63)),6)="cancel","Cancelled","Delivered") -> Delivered | AH63: =IF(ISNUMBER(SEARCH("/",B63)),DATE(VALUE(RIGHT(B63,4)),VALUE(MID(B63,4,2)),VALUE(LEFT(B63,2))),IF(MID(B63,5,1)="-",DATE(VALUE(LEFT(B63,4)),VALUE(MID(B63,6,2)),VALUE(RIGHT(B63,2))),DATE(VALUE(RIGHT(B63,4)),MATCH(MID(B63,4,3),{"Jan","Feb","Mar","Apr","May","Jun","Jul","Aug","Sep","Oct","Nov","Dec"},0),VALUE(LEFT(B63,2))))) -> 45855
A64: ORD12104 | B64: 2025-09-28 | C64: 13:24 | D64: C0750 | E64: Mumbai Pizza Co | F64: Mumbai | G64: Pizza | H64: 2 | I64: 300 | J64: 75 | K64: UPI | L64: Delivered | M64: 54 | N64: 4 | O64: =A64&"|"&B64&"|"&C64&"|"&D64&"|"&E64&"|"&F64&"|"&G64&"|"&H64&"|"&I64&"|"&J64&"|"&K64&"|"&L64&"|"&M64&"|"&N64 -> ORD12104|2025-09-28|13:24|C0750|Mumbai Pizza Co|Mumbai|Pizza|2|300|75|UPI|Delivered |54|4 | P64: =IF(COUNTIF($O$2:O64,O64)>1,"DUP","OK") -> OK | Q64: =COUNTBLANK(A64:N64) -> 0 | R64: =IF(A64="",0,COUNTIFS($A$2:$A$3058,A64,$P$2:$P$3058,"OK")) -> 1 | S64: =IF(OR(A64="",P64="DUP",R64<2),"",IF(Q64=_xlfn.MINIFS($Q$2:$Q$3058,$A$2:$A$3058,A64,$P$2:$P$3058,"OK"),"KEEP","DROP")) | T64: =IF(A64="",1,0) -> 0 | U64: =IF(D64="",1,0) -> 0 | V64: =IF(E64="",1,0) -> 0 | W64: =IF(OR(H64<1,H64>10),1,0) -> 0 | X64: =IF(OR(I64<=0,I64>1500),1,0) -> 0 | Y64: =IF(J64>H64*I64,1,0) -> 0 | Z64: =IF(AND(N64<>"",OR(N64<1,N64>5)),1,0) -> 0 | AA64: =IF(AND(M64<>"",OR(M64<5,M64>180)),1,0) -> 0 | AB64: =IF(P64="DUP","Exact duplicate row",IF(T64=1,"Missing Order ID",IF(S64="DROP","Duplicate Order ID (less complete row)",IF(U64=1,"Missing Customer ID",IF(V64=1,"Missing Restaurant name",IF(W64=1,"Invalid/outlier quantity",IF(X64=1,"Invalid/outlier unit price",IF(Y64=1,"Discount greater than order value","")))))))) | AC64: =IF(AB64="","KEEP","DROP") -> KEEP | AD64: =IF(TRIM(F64)="",IFERROR(INDEX(Map_Tables!$I$4:$I$37,MATCH(TRIM(E64),Map_Tables!$G$4:$G$37,0)),""),IFERROR(INDEX(Map_Tables!$B$4:$B$18,MATCH(TRIM(F64),Map_Tables!$A$4:$A$18,0)),"CHECK")) -> Mumbai | AE64: =IF(TRIM(E64)="","",IFERROR(INDEX(Map_Tables!$H$4:$H$37,MATCH(TRIM(E64),Map_Tables!$G$4:$G$37,0)),"CHECK")) -> Mumbai Pizza Co | AF64: =IF(TRIM(K64)="","Unknown",IFERROR(INDEX(Map_Tables!$E$4:$E$15,MATCH(TRIM(K64),Map_Tables!$D$4:$D$15,0)),"CHECK")) -> UPI | AG64: =IF(LEFT(LOWER(TRIM(L64)),6)="cancel","Cancelled","Delivered") -> Delivered | AH64: =IF(ISNUMBER(SEARCH("/",B64)),DATE(VALUE(RIGHT(B64,4)),VALUE(MID(B64,4,2)),VALUE(LEFT(B64,2))),IF(MID(B64,5,1)="-",DATE(VALUE(LEFT(B64,4)),VALUE(MID(B64,6,2)),VALUE(RIGHT(B64,2))),DATE(VALUE(RIGHT(B64,4)),MATCH(MID(B64,4,3),{"Jan","Feb","Mar","Apr","May","Jun","Jul","Aug","Sep","Oct","Nov","Dec"},0),VALUE(LEFT(B64,2))))) -> 45928
A65: ORD11546 | B65: 2025-07-20 | C65: 22:40 | D65: C0542 | E65: Dosa Darbar | F65: BLR | G65: South Indian | H65: 1 | I65: 130 | J65: 52 | K65: Credit Card | L65: Delivered | M65: 33 | N65: 3 | O65: =A65&"|"&B65&"|"&C65&"|"&D65&"|"&E65&"|"&F65&"|"&G65&"|"&H65&"|"&I65&"|"&J65&"|"&K65&"|"&L65&"|"&M65&"|"&N65 -> ORD11546|2025-07-20|22:40|C0542|Dosa Darbar|BLR|South Indian|1|130|52|Credit Card|Delivered|33|3 | P65: =IF(COUNTIF($O$2:O65,O65)>1,"DUP","OK") -> OK | Q65: =COUNTBLANK(A65:N65) -> 0 | R65: =IF(A65="",0,COUNTIFS($A$2:$A$3058,A65,$P$2:$P$3058,"OK")) -> 1 | S65: =IF(OR(A65="",P65="DUP",R65<2),"",IF(Q65=_xlfn.MINIFS($Q$2:$Q$3058,$A$2:$A$3058,A65,$P$2:$P$3058,"OK"),"KEEP","DROP")) | T65: =IF(A65="",1,0) -> 0 | U65: =IF(D65="",1,0) -> 0 | V65: =IF(E65="",1,0) -> 0 | W65: =IF(OR(H65<1,H65>10),1,0) -> 0 | X65: =IF(OR(I65<=0,I65>1500),1,0) -> 0 | Y65: =IF(J65>H65*I65,1,0) -> 0 | Z65: =IF(AND(N65<>"",OR(N65<1,N65>5)),1,0) -> 0 | AA65: =IF(AND(M65<>"",OR(M65<5,M65>180)),1,0) -> 0 | AB65: =IF(P65="DUP","Exact duplicate row",IF(T65=1,"Missing Order ID",IF(S65="DROP","Duplicate Order ID (less complete row)",IF(U65=1,"Missing Customer ID",IF(V65=1,"Missing Restaurant name",IF(W65=1,"Invalid/outlier quantity",IF(X65=1,"Invalid/outlier unit price",IF(Y65=1,"Discount greater than order value","")))))))) | AC65: =IF(AB65="","KEEP","DROP") -> KEEP | AD65: =IF(TRIM(F65)="",IFERROR(INDEX(Map_Tables!$I$4:$I$37,MATCH(TRIM(E65),Map_Tables!$G$4:$G$37,0)),""),IFERROR(INDEX(Map_Tables!$B$4:$B$18,MATCH(TRIM(F65),Map_Tables!$A$4:$A$18,0)),"CHECK")) -> Bengaluru | AE65: =IF(TRIM(E65)="","",IFERROR(INDEX(Map_Tables!$H$4:$H$37,MATCH(TRIM(E65),Map_Tables!$G$4:$G$37,0)),"CHECK")) -> Dosa Darbar | AF65: =IF(TRIM(K65)="","Unknown",IFERROR(INDEX(Map_Tables!$E$4:$E$15,MATCH(TRIM(K65),Map_Tables!$D$4:$D$15,0)),"CHECK")) -> Credit Card | AG65: =IF(LEFT(LOWER(TRIM(L65)),6)="cancel","Cancelled","Delivered") -> Delivered | AH65: =IF(ISNUMBER(SEARCH("/",B65)),DATE(VALUE(RIGHT(B65,4)),VALUE(MID(B65,4,2)),VALUE(LEFT(B65,2))),IF(MID(B65,5,1)="-",DATE(VALUE(LEFT(B65,4)),VALUE(MID(B65,6,2)),VALUE(RIGHT(B65,2))),DATE(VALUE(RIGHT(B65,4)),MATCH(MID(B65,4,3),{"Jan","Feb","Mar","Apr","May","Jun","Jul","Aug","Sep","Oct","Nov","Dec"},0),VALUE(LEFT(B65,2))))) -> 45858
A66: ORD10743 | B66: 2025-04-04 | C66: 23:54 | D66: C1013 | E66: Chettinad House | F66: Chennai | G66: South Indian | H66: 1 | I66: 170 | J66: 20 | K66: UPI | L66: Delivered | M66: 33 | N66: 5 | O66: =A66&"|"&B66&"|"&C66&"|"&D66&"|"&E66&"|"&F66&"|"&G66&"|"&H66&"|"&I66&"|"&J66&"|"&K66&"|"&L66&"|"&M66&"|"&N66 -> ORD10743|2025-04-04|23:54|C1013|Chettinad House|Chennai|South Indian|1|170|20|UPI|Delivered|33|5 | P66: =IF(COUNTIF($O$2:O66,O66)>1,"DUP","OK") -> OK | Q66: =COUNTBLANK(A66:N66) -> 0 | R66: =IF(A66="",0,COUNTIFS($A$2:$A$3058,A66,$P$2:$P$3058,"OK")) -> 1 | S66: =IF(OR(A66="",P66="DUP",R66<2),"",IF(Q66=_xlfn.MINIFS($Q$2:$Q$3058,$A$2:$A$3058,A66,$P$2:$P$3058,"OK"),"KEEP","DROP")) | T66: =IF(A66="",1,0) -> 0 | U66: =IF(D66="",1,0) -> 0 | V66: =IF(E66="",1,0) -> 0 | W66: =IF(OR(H66<1,H66>10),1,0) -> 0 | X66: =IF(OR(I66<=0,I66>1500),1,0) -> 0 | Y66: =IF(J66>H66*I66,1,0) -> 0 | Z66: =IF(AND(N66<>"",OR(N66<1,N66>5)),1,0) -> 0 | AA66: =IF(AND(M66<>"",OR(M66<5,M66>180)),1,0) -> 0 | AB66: =IF(P66="DUP","Exact duplicate row",IF(T66=1,"Missing Order ID",IF(S66="DROP","Duplicate Order ID (less complete row)",IF(U66=1,"Missing Customer ID",IF(V66=1,"Missing Restaurant name",IF(W66=1,"Invalid/outlier quantity",IF(X66=1,"Invalid/outlier unit price",IF(Y66=1,"Discount greater than order value","")))))))) | AC66: =IF(AB66="","KEEP","DROP") -> KEEP | AD66: =IF(TRIM(F66)="",IFERROR(INDEX(Map_Tables!$I$4:$I$37,MATCH(TRIM(E66),Map_Tables!$G$4:$G$37,0)),""),IFERROR(INDEX(Map_Tables!$B$4:$B$18,MATCH(TRIM(F66),Map_Tables!$A$4:$A$18,0)),"CHECK")) -> Chennai | AE66: =IF(TRIM(E66)="","",IFERROR(INDEX(Map_Tables!$H$4:$H$37,MATCH(TRIM(E66),Map_Tables!$G$4:$G$37,0)),"CHECK")) -> Chettinad House | AF66: =IF(TRIM(K66)="","Unknown",IFERROR(INDEX(Map_Tables!$E$4:$E$15,MATCH(TRIM(K66),Map_Tables!$D$4:$D$15,0)),"CHECK")) -> UPI | AG66: =IF(LEFT(LOWER(TRIM(L66)),6)="cancel","Cancelled","Delivered") -> Delivered | AH66: =IF(ISNUMBER(SEARCH("/",B66)),DATE(VALUE(RIGHT(B66,4)),VALUE(MID(B66,4,2)),VALUE(LEFT(B66,2))),IF(MID(B66,5,1)="-",DATE(VALUE(LEFT(B66,4)),VALUE(MID(B66,6,2)),VALUE(RIGHT(B66,2))),DATE(VALUE(RIGHT(B66,4)),MATCH(MID(B66,4,3),{"Jan","Feb","Mar","Apr","May","Jun","Jul","Aug","Sep","Oct","Nov","Dec"},0),VALUE(LEFT(B66,2))))) -> 45751
A67: ORD12487 | B67: 2025-11-08 | C67: 19:26 | D67: C0021 | E67: Dosa Darbar | F67: Bengaluru | G67: South Indian | H67: 1 | I67: 130 | J67: 30 | K67: Wallet | L67: Delivered | M67: 56 | N67: 4 | O67: =A67&"|"&B67&"|"&C67&"|"&D67&"|"&E67&"|"&F67&"|"&G67&"|"&H67&"|"&I67&"|"&J67&"|"&K67&"|"&L67&"|"&M67&"|"&N67 -> ORD12487|2025-11-08|19:26|C0021|Dosa Darbar|Bengaluru|South Indian|1|130|30|Wallet|Delivered|56|4 | P67: =IF(COUNTIF($O$2:O67,O67)>1,"DUP","OK") -> OK | Q67: =COUNTBLANK(A67:N67) -> 0 | R67: =IF(A67="",0,COUNTIFS($A$2:$A$3058,A67,$P$2:$P$3058,"OK")) -> 1 | S67: =IF(OR(A67="",P67="DUP",R67<2),"",IF(Q67=_xlfn.MINIFS($Q$2:$Q$3058,$A$2:$A$3058,A67,$P$2:$P$3058,"OK"),"KEEP","DROP")) | T67: =IF(A67="",1,0) -> 0 | U67: =IF(D67="",1,0) -> 0 | V67: =IF(E67="",1,0) -> 0 | W67: =IF(OR(H67<1,H67>10),1,0) -> 0 | X67: =IF(OR(I67<=0,I67>1500),1,0) -> 0 | Y67: =IF(J67>H67*I67,1,0) -> 0 | Z67: =IF(AND(N67<>"",OR(N67<1,N67>5)),1,0) -> 0 | AA67: =IF(AND(M67<>"",OR(M67<5,M67>180)),1,0) -> 0 | AB67: =IF(P67="DUP","Exact duplicate row",IF(T67=1,"Missing Order ID",IF(S67="DROP","Duplicate Order ID (less complete row)",IF(U67=1,"Missing Customer ID",IF(V67=1,"Missing Restaurant name",IF(W67=1,"Invalid/outlier quantity",IF(X67=1,"Invalid/outlier unit price",IF(Y67=1,"Discount greater than order value","")))))))) | AC67: =IF(AB67="","KEEP","DROP") -> KEEP | AD67: =IF(TRIM(F67)="",IFERROR(INDEX(Map_Tables!$I$4:$I$37,MATCH(TRIM(E67),Map_Tables!$G$4:$G$37,0)),""),IFERROR(INDEX(Map_Tables!$B$4:$B$18,MATCH(TRIM(F67),Map_Tables!$A$4:$A$18,0)),"CHECK")) -> Bengaluru | AE67: =IF(TRIM(E67)="","",IFERROR(INDEX(Map_Tables!$H$4:$H$37,MATCH(TRIM(E67),Map_Tables!$G$4:$G$37,0)),"CHECK")) -> Dosa Darbar | AF67: =IF(TRIM(K67)="","Unknown",IFERROR(INDEX(Map_Tables!$E$4:$E$15,MATCH(TRIM(K67),Map_Tables!$D$4:$D$15,0)),"CHECK")) -> Wallet | AG67: =IF(LEFT(LOWER(TRIM(L67)),6)="cancel","Cancelled","Delivered") -> Delivered | AH67: =IF(ISNUMBER(SEARCH("/",B67)),DATE(VALUE(RIGHT(B67,4)),VALUE(MID(B67,4,2)),VALUE(LEFT(B67,2))),IF(MID(B67,5,1)="-",DATE(VALUE(LEFT(B67,4)),VALUE(MID(B67,6,2)),VALUE(RIGHT(B67,2))),DATE(VALUE(RIGHT(B67,4)),MATCH(MID(B67,4,3),{"Jan","Feb","Mar","Apr","May","Jun","Jul","Aug","Sep","Oct","Nov","Dec"},0),VALUE(LEFT(B67,2))))) -> 45969
A68: ORD11683 | B68: 2025-08-08 | C68: 11:29 | D68: C0728 | E68: Curry Leaf Kitchen | F68: MUMBAI | G68: North Indian | H68: 4 | I68: 225 | J68: 100 | K68: Wallet | L68: Delivered | M68: 41 | N68: 2 | O68: =A68&"|"&B68&"|"&C68&"|"&D68&"|"&E68&"|"&F68&"|"&G68&"|"&H68&"|"&I68&"|"&J68&"|"&K68&"|"&L68&"|"&M68&"|"&N68 -> ORD11683|2025-08-08|11:29|C0728|Curry Leaf Kitchen|MUMBAI|North Indian|4|225|100|Wallet|Delivered|41|2 | P68: =IF(COUNTIF($O$2:O68,O68)>1,"DUP","OK") -> OK | Q68: =COUNTBLANK(A68:N68) -> 0 | R68: =IF(A68="",0,COUNTIFS($A$2:$A$3058,A68,$P$2:$P$3058,"OK")) -> 1 | S68: =IF(OR(A68="",P68="DUP",R68<2),"",IF(Q68=_xlfn.MINIFS($Q$2:$Q$3058,$A$2:$A$3058,A68,$P$2:$P$3058,"OK"),"KEEP","DROP")) | T68: =IF(A68="",1,0) -> 0 | U68: =IF(D68="",1,0) -> 0 | V68: =IF(E68="",1,0) -> 0 | W68: =IF(OR(H68<1,H68>10),1,0) -> 0 | X68: =IF(OR(I68<=0,I68>1500),1,0) -> 0 | Y68: =IF(J68>H68*I68,1,0) -> 0 | Z68: =IF(AND(N68<>"",OR(N68<1,N68>5)),1,0) -> 0 | AA68: =IF(AND(M68<>"",OR(M68<5,M68>180)),1,0) -> 0 | AB68: =IF(P68="DUP","Exact duplicate row",IF(T68=1,"Missing Order ID",IF(S68="DROP","Duplicate Order ID (less complete row)",IF(U68=1,"Missing Customer ID",IF(V68=1,"Missing Restaurant name",IF(W68=1,"Invalid/outlier quantity",IF(X68=1,"Invalid/outlier unit price",IF(Y68=1,"Discount greater than order value","")))))))) | AC68: =IF(AB68="","KEEP","DROP") -> KEEP | AD68: =IF(TRIM(F68)="",IFERROR(INDEX(Map_Tables!$I$4:$I$37,MATCH(TRIM(E68),Map_Tables!$G$4:$G$37,0)),""),IFERROR(INDEX(Map_Tables!$B$4:$B$18,MATCH(TRIM(F68),Map_Tables!$A$4:$A$18,0)),"CHECK")) -> Mumbai | AE68: =IF(TRIM(E68)="","",IFERROR(INDEX(Map_Tables!$H$4:$H$37,MATCH(TRIM(E68),Map_Tables!$G$4:$G$37,0)),"CHECK")) -> Curry Leaf Kitchen | AF68: =IF(TRIM(K68)="","Unknown",IFERROR(INDEX(Map_Tables!$E$4:$E$15,MATCH(TRIM(K68),Map_Tables!$D$4:$D$15,0)),"CHECK")) -> Wallet | AG68: =IF(LEFT(LOWER(TRIM(L68)),6)="cancel","Cancelled","Delivered") -> Delivered | AH68: =IF(ISNUMBER(SEARCH("/",B68)),DATE(VALUE(RIGHT(B68,4)),VALUE(MID(B68,4,2)),VALUE(LEFT(B68,2))),IF(MID(B68,5,1)="-",DATE(VALUE(LEFT(B68,4)),VALUE(MID(B68,6,2)),VALUE(RIGHT(B68,2))),DATE(VALUE(RIGHT(B68,4)),MATCH(MID(B68,4,3),{"Jan","Feb","Mar","Apr","May","Jun","Jul","Aug","Sep","Oct","Nov","Dec"},0),VALUE(LEFT(B68,2))))) -> 45877
A69: ORD10820 | B69: 2025-04-14 | C69: 16:40 | D69: C0757 | E69: Burger Barn | F69: Delhi | G69: Burgers | H69: 2 | I69: 165 | J69: 75 | K69: UPI | L69: Delivered | N69: 4 | O69: =A69&"|"&B69&"|"&C69&"|"&D69&"|"&E69&"|"&F69&"|"&G69&"|"&H69&"|"&I69&"|"&J69&"|"&K69&"|"&L69&"|"&M69&"|"&N69 -> ORD10820|2025-04-14|16:40|C0757|Burger Barn|Delhi|Burgers|2|165|75|UPI|Delivered||4 | P69: =IF(COUNTIF($O$2:O69,O69)>1,"DUP","OK") -> OK | Q69: =COUNTBLANK(A69:N69) -> 1 | R69: =IF(A69="",0,COUNTIFS($A$2:$A$3058,A69,$P$2:$P$3058,"OK")) -> 1 | S69: =IF(OR(A69="",P69="DUP",R69<2),"",IF(Q69=_xlfn.MINIFS($Q$2:$Q$3058,$A$2:$A$3058,A69,$P$2:$P$3058,"OK"),"KEEP","DROP")) | T69: =IF(A69="",1,0) -> 0 | U69: =IF(D69="",1,0) -> 0 | V69: =IF(E69="",1,0) -> 0 | W69: =IF(OR(H69<1,H69>10),1,0) -> 0 | X69: =IF(OR(I69<=0,I69>1500),1,0) -> 0 | Y69: =IF(J69>H69*I69,1,0) -> 0 | Z69: =IF(AND(N69<>"",OR(N69<1,N69>5)),1,0) -> 0 | AA69: =IF(AND(M69<>"",OR(M69<5,M69>180)),1,0) -> 0 | AB69: =IF(P69="DUP","Exact duplicate row",IF(T69=1,"Missing Order ID",IF(S69="DROP","Duplicate Order ID (less complete row)",IF(U69=1,"Missing Customer ID",IF(V69=1,"Missing Restaurant name",IF(W69=1,"Invalid/outlier quantity",IF(X69=1,"Invalid/outlier unit price",IF(Y69=1,"Discount greater than order value","")))))))) | AC69: =IF(AB69="","KEEP","DROP") -> KEEP | AD69: =IF(TRIM(F69)="",IFERROR(INDEX(Map_Tables!$I$4:$I$37,MATCH(TRIM(E69),Map_Tables!$G$4:$G$37,0)),""),IFERROR(INDEX(Map_Tables!$B$4:$B$18,MATCH(TRIM(F69),Map_Tables!$A$4:$A$18,0)),"CHECK")) -> Delhi | AE69: =IF(TRIM(E69)="","",IFERROR(INDEX(Map_Tables!$H$4:$H$37,MATCH(TRIM(E69),Map_Tables!$G$4:$G$37,0)),"CHECK")) -> Burger Barn | AF69: =IF(TRIM(K69)="","Unknown",IFERROR(INDEX(Map_Tables!$E$4:$E$15,MATCH(TRIM(K69),Map_Tables!$D$4:$D$15,0)),"CHECK")) -> UPI | AG69: =IF(LEFT(LOWER(TRIM(L69)),6)="cancel","Cancelled","Delivered") -> Delivered | AH69: =IF(ISNUMBER(SEARCH("/",B69)),DATE(VALUE(RIGHT(B69,4)),VALUE(MID(B69,4,2)),VALUE(LEFT(B69,2))),IF(MID(B69,5,1)="-",DATE(VALUE(LEFT(B69,4)),VALUE(MID(B69,6,2)),VALUE(RIGHT(B69,2))),DATE(VALUE(RIGHT(B69,4)),MATCH(MID(B69,4,3),{"Jan","Feb","Mar","Apr","May","Jun","Jul","Aug","Sep","Oct","Nov","Dec"},0),VALUE(LEFT(B69,2))))) -> 45761
A70: ORD10839 | B70: 2025-04-16 | C70: 20:03 | D70: C0989 | E70: Madras Biryani Co | F70: Chennai | G70: Biryani | H70: 3 | I70: 285 | J70: 0 | K70: UPI | L70: Delivered | M70: 43 | N70: 3 | O70: =A70&"|"&B70&"|"&C70&"|"&D70&"|"&E70&"|"&F70&"|"&G70&"|"&H70&"|"&I70&"|"&J70&"|"&K70&"|"&L70&"|"&M70&"|"&N70 -> ORD10839|2025-04-16|20:03|C0989|Madras Biryani Co|Chennai|Biryani|3|285|0|UPI|Delivered |43|3 | P70: =IF(COUNTIF($O$2:O70,O70)>1,"DUP","OK") -> OK | Q70: =COUNTBLANK(A70:N70) -> 0 | R70: =IF(A70="",0,COUNTIFS($A$2:$A$3058,A70,$P$2:$P$3058,"OK")) -> 1 | S70: =IF(OR(A70="",P70="DUP",R70<2),"",IF(Q70=_xlfn.MINIFS($Q$2:$Q$3058,$A$2:$A$3058,A70,$P$2:$P$3058,"OK"),"KEEP","DROP")) | T70: =IF(A70="",1,0) -> 0 | U70: =IF(D70="",1,0) -> 0 | V70: =IF(E70="",1,0) -> 0 | W70: =IF(OR(H70<1,H70>10),1,0) -> 0 | X70: =IF(OR(I70<=0,I70>1500),1,0) -> 0 | Y70: =IF(J70>H70*I70,1,0) -> 0 | Z70: =IF(AND(N70<>"",OR(N70<1,N70>5)),1,0) -> 0 | AA70: =IF(AND(M70<>"",OR(M70<5,M70>180)),1,0) -> 0 | AB70: =IF(P70="DUP","Exact duplicate row",IF(T70=1,"Missing Order ID",IF(S70="DROP","Duplicate Order ID (less complete row)",IF(U70=1,"Missing Customer ID",IF(V70=1,"Missing Restaurant name",IF(W70=1,"Invalid/outlier quantity",IF(X70=1,"Invalid/outlier unit price",IF(Y70=1,"Discount greater than order value","")))))))) | AC70: =IF(AB70="","KEEP","DROP") -> KEEP | AD70: =IF(TRIM(F70)="",IFERROR(INDEX(Map_Tables!$I$4:$I$37,MATCH(TRIM(E70),Map_Tables!$G$4:$G$37,0)),""),IFERROR(INDEX(Map_Tables!$B$4:$B$18,MATCH(TRIM(F70),Map_Tables!$A$4:$A$18,0)),"CHECK")) -> Chennai | AE70: =IF(TRIM(E70)="","",IFERROR(INDEX(Map_Tables!$H$4:$H$37,MATCH(TRIM(E70),Map_Tables!$G$4:$G$37,0)),"CHECK")) -> Madras Biryani Co | AF70: =IF(TRIM(K70)="","Unknown",IFERROR(INDEX(Map_Tables!$E$4:$E$15,MATCH(TRIM(K70),Map_Tables!$D$4:$D$15,0)),"CHECK")) -> UPI | AG70: =IF(LEFT(LOWER(TRIM(L70)),6)="cancel","Cancelled","Delivered") -> Delivered | AH70: =IF(ISNUMBER(SEARCH("/",B70)),DATE(VALUE(RIGHT(B70,4)),VALUE(MID(B70,4,2)),VALUE(LEFT(B70,2))),IF(MID(B70,5,1)="-",DATE(VALUE(LEFT(B70,4)),VALUE(MID(B70,6,2)),VALUE(RIGHT(B70,2))),DATE(VALUE(RIGHT(B70,4)),MATCH(MID(B70,4,3),{"Jan","Feb","Mar","Apr","May","Jun","Jul","Aug","Sep","Oct","Nov","Dec"},0),VALUE(LEFT(B70,2))))) -> 45763
A71: ORD10738 | B71: 2025-04-04 | C71: 16:53 | D71: C0476 | E71: Misal Mantra | F71: Pune | G71: Street Food | H71: 4 | I71: 125 | J71: 0 | K71: UPI | L71: Delivered | M71: 30 | N71: 3 | O71: =A71&"|"&B71&"|"&C71&"|"&D71&"|"&E71&"|"&F71&"|"&G71&"|"&H71&"|"&I71&"|"&J71&"|"&K71&"|"&L71&"|"&M71&"|"&N71 -> ORD10738|2025-04-04|16:53|C0476| Misal Mantra|Pune|Street Food|4|125|0|UPI|Delivered|30|3 | P71: =IF(COUNTIF($O$2:O71,O71)>1,"DUP","OK") -> OK | Q71: =COUNTBLANK(A71:N71) -> 0 | R71: =IF(A71="",0,COUNTIFS($A$2:$A$3058,A71,$P$2:$P$3058,"OK")) -> 1 | S71: =IF(OR(A71="",P71="DUP",R71<2),"",IF(Q71=_xlfn.MINIFS($Q$2:$Q$3058,$A$2:$A$3058,A71,$P$2:$P$3058,"OK"),"KEEP","DROP")) | T71: =IF(A71="",1,0) -> 0 | U71: =IF(D71="",1,0) -> 0 | V71: =IF(E71="",1,0) -> 0 | W71: =IF(OR(H71<1,H71>10),1,0) -> 0 | X71: =IF(OR(I71<=0,I71>1500),1,0) -> 0 | Y71: =IF(J71>H71*I71,1,0) -> 0 | Z71: =IF(AND(N71<>"",OR(N71<1,N71>5)),1,0) -> 0 | AA71: =IF(AND(M71<>"",OR(M71<5,M71>180)),1,0) -> 0 | AB71: =IF(P71="DUP","Exact duplicate row",IF(T71=1,"Missing Order ID",IF(S71="DROP","Duplicate Order ID (less complete row)",IF(U71=1,"Missing Customer ID",IF(V71=1,"Missing Restaurant name",IF(W71=1,"Invalid/outlier quantity",IF(X71=1,"Invalid/outlier unit price",IF(Y71=1,"Discount greater than order value","")))))))) | AC71: =IF(AB71="","KEEP","DROP") -> KEEP | AD71: =IF(TRIM(F71)="",IFERROR(INDEX(Map_Tables!$I$4:$I$37,MATCH(TRIM(E71),Map_Tables!$G$4:$G$37,0)),""),IFERROR(INDEX(Map_Tables!$B$4:$B$18,MATCH(TRIM(F71),Map_Tables!$A$4:$A$18,0)),"CHECK")) -> Pune | AE71: =IF(TRIM(E71)="","",IFERROR(INDEX(Map_Tables!$H$4:$H$37,MATCH(TRIM(E71),Map_Tables!$G$4:$G$37,0)),"CHECK")) -> Misal Mantra | AF71: =IF(TRIM(K71)="","Unknown",IFERROR(INDEX(Map_Tables!$E$4:$E$15,MATCH(TRIM(K71),Map_Tables!$D$4:$D$15,0)),"CHECK")) -> UPI | AG71: =IF(LEFT(LOWER(TRIM(L71)),6)="cancel","Cancelled","Delivered") -> Delivered | AH71: =IF(ISNUMBER(SEARCH("/",B71)),DATE(VALUE(RIGHT(B71,4)),VALUE(MID(B71,4,2)),VALUE(LEFT(B71,2))),IF(MID(B71,5,1)="-",DATE(VALUE(LEFT(B71,4)),VALUE(MID(B71,6,2)),VALUE(RIGHT(B71,2))),DATE(VALUE(RIGHT(B71,4)),MATCH(MID(B71,4,3),{"Jan","Feb","Mar","Apr","May","Jun","Jul","Aug","Sep","Oct","Nov","Dec"},0),VALUE(LEFT(B71,2))))) -> 45751
A72: ORD12526 | B72: 12/11/2025 | C72: 12:46 | D72: C0170 | E72: Wok & Roll | F72: Bengaluru | G72: Chinese | H72: 4 | I72: 185 | J72: 125 | K72: Credit Card | L72: Delivered | M72: 42 | N72: 4 | O72: =A72&"|"&B72&"|"&C72&"|"&D72&"|"&E72&"|"&F72&"|"&G72&"|"&H72&"|"&I72&"|"&J72&"|"&K72&"|"&L72&"|"&M72&"|"&N72 -> ORD12526|12/11/2025|12:46|C0170|Wok & Roll|Bengaluru|Chinese|4|185|125|Credit Card|Delivered|42|4 | P72: =IF(COUNTIF($O$2:O72,O72)>1,"DUP","OK") -> OK | Q72: =COUNTBLANK(A72:N72) -> 0 | R72: =IF(A72="",0,COUNTIFS($A$2:$A$3058,A72,$P$2:$P$3058,"OK")) -> 1 | S72: =IF(OR(A72="",P72="DUP",R72<2),"",IF(Q72=_xlfn.MINIFS($Q$2:$Q$3058,$A$2:$A$3058,A72,$P$2:$P$3058,"OK"),"KEEP","DROP")) | T72: =IF(A72="",1,0) -> 0 | U72: =IF(D72="",1,0) -> 0 | V72: =IF(E72="",1,0) -> 0 | W72: =IF(OR(H72<1,H72>10),1,0) -> 0 | X72: =IF(OR(I72<=0,I72>1500),1,0) -> 0 | Y72: =IF(J72>H72*I72,1,0) -> 0 | Z72: =IF(AND(N72<>"",OR(N72<1,N72>5)),1,0) -> 0 | AA72: =IF(AND(M72<>"",OR(M72<5,M72>180)),1,0) -> 0 | AB72: =IF(P72="DUP","Exact duplicate row",IF(T72=1,"Missing Order ID",IF(S72="DROP","Duplicate Order ID (less complete row)",IF(U72=1,"Missing Customer ID",IF(V72=1,"Missing Restaurant name",IF(W72=1,"Invalid/outlier quantity",IF(X72=1,"Invalid/outlier unit price",IF(Y72=1,"Discount greater than order value","")))))))) | AC72: =IF(AB72="","KEEP","DROP") -> KEEP | AD72: =IF(TRIM(F72)="",IFERROR(INDEX(Map_Tables!$I$4:$I$37,MATCH(TRIM(E72),Map_Tables!$G$4:$G$37,0)),""),IFERROR(INDEX(Map_Tables!$B$4:$B$18,MATCH(TRIM(F72),Map_Tables!$A$4:$A$18,0)),"CHECK")) -> Bengaluru | AE72: =IF(TRIM(E72)="","",IFERROR(INDEX(Map_Tables!$H$4:$H$37,MATCH(TRIM(E72),Map_Tables!$G$4:$G$37,0)),"CHECK")) -> Wok & Roll | AF72: =IF(TRIM(K72)="","Unknown",IFERROR(INDEX(Map_Tables!$E$4:$E$15,MATCH(TRIM(K72),Map_Tables!$D$4:$D$15,0)),"CHECK")) -> Credit Card | AG72: =IF(LEFT(LOWER(TRIM(L72)),6)="cancel","Cancelled","Delivered") -> Delivered | AH72: =IF(ISNUMBER(SEARCH("/",B72)),DATE(VALUE(RIGHT(B72,4)),VALUE(MID(B72,4,2)),VALUE(LEFT(B72,2))),IF(MID(B72,5,1)="-",DATE(VALUE(LEFT(B72,4)),VALUE(MID(B72,6,2)),VALUE(RIGHT(B72,2))),DATE(VALUE(RIGHT(B72,4)),MATCH(MID(B72,4,3),{"Jan","Feb","Mar","Apr","May","Jun","Jul","Aug","Sep","Oct","Nov","Dec"},0),VALUE(LEFT(B72,2))))) -> 45973
A73: ORD10122 | B73: 16/01/2025 | C73: 19:03 | D73: C0822 | E73: Dragon Express | F73: Mumbai | G73: Chinese | H73: 3 | I73: 220 | J73: 50 | K73: Credit Card | L73: Delivered | M73: 40 | N73: 4 | O73: =A73&"|"&B73&"|"&C73&"|"&D73&"|"&E73&"|"&F73&"|"&G73&"|"&H73&"|"&I73&"|"&J73&"|"&K73&"|"&L73&"|"&M73&"|"&N73 -> ORD10122|16/01/2025|19:03|C0822|Dragon Express|Mumbai|Chinese|3|220|50|Credit Card|Delivered|40|4 | P73: =IF(COUNTIF($O$2:O73,O73)>1,"DUP","OK") -> OK | Q73: =COUNTBLANK(A73:N73) -> 0 | R73: =IF(A73="",0,COUNTIFS($A$2:$A$3058,A73,$P$2:$P$3058,"OK")) -> 1 | S73: =IF(OR(A73="",P73="DUP",R73<2),"",IF(Q73=_xlfn.MINIFS($Q$2:$Q$3058,$A$2:$A$3058,A73,$P$2:$P$3058,"OK"),"KEEP","DROP")) | T73: =IF(A73="",1,0) -> 0 | U73: =IF(D73="",1,0) -> 0 | V73: =IF(E73="",1,0) -> 0 | W73: =IF(OR(H73<1,H73>10),1,0) -> 0 | X73: =IF(OR(I73<=0,I73>1500),1,0) -> 0 | Y73: =IF(J73>H73*I73,1,0) -> 0 | Z73: =IF(AND(N73<>"",OR(N73<1,N73>5)),1,0) -> 0 | AA73: =IF(AND(M73<>"",OR(M73<5,M73>180)),1,0) -> 0 | AB73: =IF(P73="DUP","Exact duplicate row",IF(T73=1,"Missing Order ID",IF(S73="DROP","Duplicate Order ID (less complete row)",IF(U73=1,"Missing Customer ID",IF(V73=1,"Missing Restaurant name",IF(W73=1,"Invalid/outlier quantity",IF(X73=1,"Invalid/outlier unit price",IF(Y73=1,"Discount greater than order value","")))))))) | AC73: =IF(AB73="","KEEP","DROP") -> KEEP | AD73: =IF(TRIM(F73)="",IFERROR(INDEX(Map_Tables!$I$4:$I$37,MATCH(TRIM(E73),Map_Tables!$G$4:$G$37,0)),""),IFERROR(INDEX(Map_Tables!$B$4:$B$18,MATCH(TRIM(F73),Map_Tables!$A$4:$A$18,0)),"CHECK")) -> Mumbai | AE73: =IF(TRIM(E73)="","",IFERROR(INDEX(Map_Tables!$H$4:$H$37,MATCH(TRIM(E73),Map_Tables!$G$4:$G$37,0)),"CHECK")) -> Dragon Express | AF73: =IF(TRIM(K73)="","Unknown",IFERROR(INDEX(Map_Tables!$E$4:$E$15,MATCH(TRIM(K73),Map_Tables!$D$4:$D$15,0)),"CHECK")) -> Credit Card | AG73: =IF(LEFT(LOWER(TRIM(L73)),6)="cancel","Cancelled","Delivered") -> Delivered | AH73: =IF(ISNUMBER(SEARCH("/",B73)),DATE(VALUE(RIGHT(B73,4)),VALUE(MID(B73,4,2)),VALUE(LEFT(B73,2))),IF(MID(B73,5,1)="-",DATE(VALUE(LEFT(B73,4)),VALUE(MID(B73,6,2)),VALUE(RIGHT(B73,2))),DATE(VALUE(RIGHT(B73,4)),MATCH(MID(B73,4,3),{"Jan","Feb","Mar","Apr","May","Jun","Jul","Aug","Sep","Oct","Nov","Dec"},0),VALUE(LEFT(B73,2))))) -> 45673
A74: ORD10225 | B74: 2025-01-31 | C74: 14:54 | D74: C1419 | E74: Dosa Darbar | F74: Bengaluru | G74: South Indian | H74: 4 | I74: 125 | J74: 150 | K74: UPI | L74: Delivered | M74: 60 | N74: 3 | O74: =A74&"|"&B74&"|"&C74&"|"&D74&"|"&E74&"|"&F74&"|"&G74&"|"&H74&"|"&I74&"|"&J74&"|"&K74&"|"&L74&"|"&M74&"|"&N74 -> ORD10225|2025-01-31|14:54|C1419|Dosa Darbar|Bengaluru|South Indian|4|125|150|UPI|Delivered|60|3 | P74: =IF(COUNTIF($O$2:O74,O74)>1,"DUP","OK") -> OK | Q74: =COUNTBLANK(A74:N74) -> 0 | R74: =IF(A74="",0,COUNTIFS($A$2:$A$3058,A74,$P$2:$P$3058,"OK")) -> 1 | S74: =IF(OR(A74="",P74="DUP",R74<2),"",IF(Q74=_xlfn.MINIFS($Q$2:$Q$3058,$A$2:$A$3058,A74,$P$2:$P$3058,"OK"),"KEEP","DROP")) | T74: =IF(A74="",1,0) -> 0 | U74: =IF(D74="",1,0) -> 0 | V74: =IF(E74="",1,0) -> 0 | W74: =IF(OR(H74<1,H74>10),1,0) -> 0 | X74: =IF(OR(I74<=0,I74>1500),1,0) -> 0 | Y74: =IF(J74>H74*I74,1,0) -> 0 | Z74: =IF(AND(N74<>"",OR(N74<1,N74>5)),1,0) -> 0 | AA74: =IF(AND(M74<>"",OR(M74<5,M74>180)),1,0) -> 0 | AB74: =IF(P74="DUP","Exact duplicate row",IF(T74=1,"Missing Order ID",IF(S74="DROP","Duplicate Order ID (less complete row)",IF(U74=1,"Missing Customer ID",IF(V74=1,"Missing Restaurant name",IF(W74=1,"Invalid/outlier quantity",IF(X74=1,"Invalid/outlier unit price",IF(Y74=1,"Discount greater than order value","")))))))) | AC74: =IF(AB74="","KEEP","DROP") -> KEEP | AD74: =IF(TRIM(F74)="",IFERROR(INDEX(Map_Tables!$I$4:$I$37,MATCH(TRIM(E74),Map_Tables!$G$4:$G$37,0)),""),IFERROR(INDEX(Map_Tables!$B$4:$B$18,MATCH(TRIM(F74),Map_Tables!$A$4:$A$18,0)),"CHECK")) -> Bengaluru | AE74: =IF(TRIM(E74)="","",IFERROR(INDEX(Map_Tables!$H$4:$H$37,MATCH(TRIM(E74),Map_Tables!$G$4:$G$37,0)),"CHECK")) -> Dosa Darbar | AF74: =IF(TRIM(K74)="","Unknown",IFERROR(INDEX(Map_Tables!$E$4:$E$15,MATCH(TRIM(K74),Map_Tables!$D$4:$D$15,0)),"CHECK")) -> UPI | AG74: =IF(LEFT(LOWER(TRIM(L74)),6)="cancel","Cancelled","Delivered") -> Delivered | AH74: =IF(ISNUMBER(SEARCH("/",B74)),DATE(VALUE(RIGHT(B74,4)),VALUE(MID(B74,4,2)),VALUE(LEFT(B74,2))),IF(MID(B74,5,1)="-",DATE(VALUE(LEFT(B74,4)),VALUE(MID(B74,6,2)),VALUE(RIGHT(B74,2))),DATE(VALUE(RIGHT(B74,4)),MATCH(MID(B74,4,3),{"Jan","Feb","Mar","Apr","May","Jun","Jul","Aug","Sep","Oct","Nov","Dec"},0),VALUE(LEFT(B74,2))))) -> 45688
A75: ORD10805 | B75: 2025-04-12 | C75: 12:48 | D75: C0413 | E75: Pav Bhaji Point | F75: Bombay | G75: Street Food | H75: 1 | I75: 115 | J75: 0 | K75: UPI | L75: Delivered | M75: 34 | N75: 5 | O75: =A75&"|"&B75&"|"&C75&"|"&D75&"|"&E75&"|"&F75&"|"&G75&"|"&H75&"|"&I75&"|"&J75&"|"&K75&"|"&L75&"|"&M75&"|"&N75 -> ORD10805|2025-04-12|12:48|C0413|Pav Bhaji Point|Bombay|Street Food|1|115|0|UPI|Delivered|34|5 | P75: =IF(COUNTIF($O$2:O75,O75)>1,"DUP","OK") -> OK | Q75: =COUNTBLANK(A75:N75) -> 0 | R75: =IF(A75="",0,COUNTIFS($A$2:$A$3058,A75,$P$2:$P$3058,"OK")) -> 1 | S75: =IF(OR(A75="",P75="DUP",R75<2),"",IF(Q75=_xlfn.MINIFS($Q$2:$Q$3058,$A$2:$A$3058,A75,$P$2:$P$3058,"OK"),"KEEP","DROP")) | T75: =IF(A75="",1,0) -> 0 | U75: =IF(D75="",1,0) -> 0 | V75: =IF(E75="",1,0) -> 0 | W75: =IF(OR(H75<1,H75>10),1,0) -> 0 | X75: =IF(OR(I75<=0,I75>1500),1,0) -> 0 | Y75: =IF(J75>H75*I75,1,0) -> 0 | Z75: =IF(AND(N75<>"",OR(N75<1,N75>5)),1,0) -> 0 | AA75: =IF(AND(M75<>"",OR(M75<5,M75>180)),1,0) -> 0 | AB75: =IF(P75="DUP","Exact duplicate row",IF(T75=1,"Missing Order ID",IF(S75="DROP","Duplicate Order ID (less complete row)",IF(U75=1,"Missing Customer ID",IF(V75=1,"Missing Restaurant name",IF(W75=1,"Invalid/outlier quantity",IF(X75=1,"Invalid/outlier unit price",IF(Y75=1,"Discount greater than order value","")))))))) | AC75: =IF(AB75="","KEEP","DROP") -> KEEP | AD75: =IF(TRIM(F75)="",IFERROR(INDEX(Map_Tables!$I$4:$I$37,MATCH(TRIM(E75),Map_Tables!$G$4:$G$37,0)),""),IFERROR(INDEX(Map_Tables!$B$4:$B$18,MATCH(TRIM(F75),Map_Tables!$A$4:$A$18,0)),"CHECK")) -> Mumbai | AE75: =IF(TRIM(E75)="","",IFERROR(INDEX(Map_Tables!$H$4:$H$37,MATCH(TRIM(E75),Map_Tables!$G$4:$G$37,0)),"CHECK")) -> Pav Bhaji Point | AF75: =IF(TRIM(K75)="","Unknown",IFERROR(INDEX(Map_Tables!$E$4:$E$15,MATCH(TRIM(K75),Map_Tables!$D$4:$D$15,0)),"CHECK")) -> UPI | AG75: =IF(LEFT(LOWER(TRIM(L75)),6)="cancel","Cancelled","Delivered") -> Delivered | AH75: =IF(ISNUMBER(SEARCH("/",B75)),DATE(VALUE(RIGHT(B75,4)),VALUE(MID(B75,4,2)),VALUE(LEFT(B75,2))),IF(MID(B75,5,1)="-",DATE(VALUE(LEFT(B75,4)),VALUE(MID(B75,6,2)),VALUE(RIGHT(B75,2))),DATE(VALUE(RIGHT(B75,4)),MATCH(MID(B75,4,3),{"Jan","Feb","Mar","Apr","May","Jun","Jul","Aug","Sep","Oct","Nov","Dec"},0),VALUE(LEFT(B75,2))))) -> 45759
A76: ORD11366 | B76: 2025-06-24 | C76: 22:51 | D76: C1331 | E76: Burger Barn | F76: Delhi | G76: Burgers | H76: 0 | I76: 195 | J76: 50 | K76: UPI | L76: Delivered | M76: 33 | N76: 4 | O76: =A76&"|"&B76&"|"&C76&"|"&D76&"|"&E76&"|"&F76&"|"&G76&"|"&H76&"|"&I76&"|"&J76&"|"&K76&"|"&L76&"|"&M76&"|"&N76 -> ORD11366|2025-06-24|22:51|C1331|Burger Barn|Delhi|Burgers|0|195|50|UPI|Delivered|33|4 | P76: =IF(COUNTIF($O$2:O76,O76)>1,"DUP","OK") -> OK | Q76: =COUNTBLANK(A76:N76) -> 0 | R76: =IF(A76="",0,COUNTIFS($A$2:$A$3058,A76,$P$2:$P$3058,"OK")) -> 1 | S76: =IF(OR(A76="",P76="DUP",R76<2),"",IF(Q76=_xlfn.MINIFS($Q$2:$Q$3058,$A$2:$A$3058,A76,$P$2:$P$3058,"OK"),"KEEP","DROP")) | T76: =IF(A76="",1,0) -> 0 | U76: =IF(D76="",1,0) -> 0 | V76: =IF(E76="",1,0) -> 0 | W76: =IF(OR(H76<1,H76>10),1,0) -> 1 | X76: =IF(OR(I76<=0,I76>1500),1,0) -> 0 | Y76: =IF(J76>H76*I76,1,0) -> 1 | Z76: =IF(AND(N76<>"",OR(N76<1,N76>5)),1,0) -> 0 | AA76: =IF(AND(M76<>"",OR(M76<5,M76>180)),1,0) -> 0 | AB76: =IF(P76="DUP","Exact duplicate row",IF(T76=1,"Missing Order ID",IF(S76="DROP","Duplicate Order ID (less complete row)",IF(U76=1,"Missing Customer ID",IF(V76=1,"Missing Restaurant name",IF(W76=1,"Invalid/outlier quantity",IF(X76=1,"Invalid/outlier unit price",IF(Y76=1,"Discount greater than order value","")))))))) -> Invalid/outlier quantity | AC76: =IF(AB76="","KEEP","DROP") -> DROP | AD76: =IF(TRIM(F76)="",IFERROR(INDEX(Map_Tables!$I$4:$I$37,MATCH(TRIM(E76),Map_Tables!$G$4:$G$37,0)),""),IFERROR(INDEX(Map_Tables!$B$4:$B$18,MATCH(TRIM(F76),Map_Tables!$A$4:$A$18,0)),"CHECK")) -> Delhi | AE76: =IF(TRIM(E76)="","",IFERROR(INDEX(Map_Tables!$H$4:$H$37,MATCH(TRIM(E76),Map_Tables!$G$4:$G$37,0)),"CHECK")) -> Burger Barn | AF76: =IF(TRIM(K76)="","Unknown",IFERROR(INDEX(Map_Tables!$E$4:$E$15,MATCH(TRIM(K76),Map_Tables!$D$4:$D$15,0)),"CHECK")) -> UPI | AG76: =IF(LEFT(LOWER(TRIM(L76)),6)="cancel","Cancelled","Delivered") -> Delivered | AH76: =IF(ISNUMBER(SEARCH("/",B76)),DATE(VALUE(RIGHT(B76,4)),VALUE(MID(B76,4,2)),VALUE(LEFT(B76,2))),IF(MID(B76,5,1)="-",DATE(VALUE(LEFT(B76,4)),VALUE(MID(B76,6,2)),VALUE(RIGHT(B76,2))),DATE(VALUE(RIGHT(B76,4)),MATCH(MID(B76,4,3),{"Jan","Feb","Mar","Apr","May","Jun","Jul","Aug","Sep","Oct","Nov","Dec"},0),VALUE(LEFT(B76,2))))) -> 45832
A77: ORD11550 | B77: 2025-07-21 | C77: 13:56 | D77: C0856 | E77: Tandoor Tales | F77: Delhi | G77: North Indian | H77: 1 | I77: 295 | J77: 100 | K77: UPI | L77: Delivered | M77: 36 | N77: 4 | O77: =A77&"|"&B77&"|"&C77&"|"&D77&"|"&E77&"|"&F77&"|"&G77&"|"&H77&"|"&I77&"|"&J77&"|"&K77&"|"&L77&"|"&M77&"|"&N77 -> ORD11550|2025-07-21|13:56|C0856|Tandoor Tales|Delhi|North Indian|1|295|100|UPI|Delivered|36|4 | P77: =IF(COUNTIF($O$2:O77,O77)>1,"DUP","OK") -> OK | Q77: =COUNTBLANK(A77:N77) -> 0 | R77: =IF(A77="",0,COUNTIFS($A$2:$A$3058,A77,$P$2:$P$3058,"OK")) -> 1 | S77: =IF(OR(A77="",P77="DUP",R77<2),"",IF(Q77=_xlfn.MINIFS($Q$2:$Q$3058,$A$2:$A$3058,A77,$P$2:$P$3058,"OK"),"KEEP","DROP")) | T77: =IF(A77="",1,0) -> 0 | U77: =IF(D77="",1,0) -> 0 | V77: =IF(E77="",1,0) -> 0 | W77: =IF(OR(H77<1,H77>10),1,0) -> 0 | X77: =IF(OR(I77<=0,I77>1500),1,0) -> 0 | Y77: =IF(J77>H77*I77,1,0) -> 0 | Z77: =IF(AND(N77<>"",OR(N77<1,N77>5)),1,0) -> 0 | AA77: =IF(AND(M77<>"",OR(M77<5,M77>180)),1,0) -> 0 | AB77: =IF(P77="DUP","Exact duplicate row",IF(T77=1,"Missing Order ID",IF(S77="DROP","Duplicate Order ID (less complete row)",IF(U77=1,"Missing Customer ID",IF(V77=1,"Missing Restaurant name",IF(W77=1,"Invalid/outlier quantity",IF(X77=1,"Invalid/outlier unit price",IF(Y77=1,"Discount greater than order value","")))))))) | AC77: =IF(AB77="","KEEP","DROP") -> KEEP | AD77: =IF(TRIM(F77)="",IFERROR(INDEX(Map_Tables!$I$4:$I$37,MATCH(TRIM(E77),Map_Tables!$G$4:$G$37,0)),""),IFERROR(INDEX(Map_Tables!$B$4:$B$18,MATCH(TRIM(F77),Map_Tables!$A$4:$A$18,0)),"CHECK")) -> Delhi | AE77: =IF(TRIM(E77)="","",IFERROR(INDEX(Map_Tables!$H$4:$H$37,MATCH(TRIM(E77),Map_Tables!$G$4:$G$37,0)),"CHECK")) -> Tandoor Tales | AF77: =IF(TRIM(K77)="","Unknown",IFERROR(INDEX(Map_Tables!$E$4:$E$15,MATCH(TRIM(K77),Map_Tables!$D$4:$D$15,0)),"CHECK")) -> UPI | AG77: =IF(LEFT(LOWER(TRIM(L77)),6)="cancel","Cancelled","Delivered") -> Delivered | AH77: =IF(ISNUMBER(SEARCH("/",B77)),DATE(VALUE(RIGHT(B77,4)),VALUE(MID(B77,4,2)),VALUE(LEFT(B77,2))),IF(MID(B77,5,1)="-",DATE(VALUE(LEFT(B77,4)),VALUE(MID(B77,6,2)),VALUE(RIGHT(B77,2))),DATE(VALUE(RIGHT(B77,4)),MATCH(MID(B77,4,3),{"Jan","Feb","Mar","Apr","May","Jun","Jul","Aug","Sep","Oct","Nov","Dec"},0),VALUE(LEFT(B77,2))))) -> 45859
A78: ORD11620 | B78: 2025-07-30 | C78: 11:56 | D78: C0087 | E78: Pune Burger Hub | F78: Pune | G78: Burgers | H78: 2 | I78: 185 | J78: 40 | K78: UPI | L78: Delivered | M78: 38 | N78: 4 | O78: =A78&"|"&B78&"|"&C78&"|"&D78&"|"&E78&"|"&F78&"|"&G78&"|"&H78&"|"&I78&"|"&J78&"|"&K78&"|"&L78&"|"&M78&"|"&N78 -> ORD11620|2025-07-30|11:56|C0087|Pune Burger Hub|Pune|Burgers|2|185|40|UPI|Delivered|38|4 | P78: =IF(COUNTIF($O$2:O78,O78)>1,"DUP","OK") -> OK | Q78: =COUNTBLANK(A78:N78) -> 0 | R78: =IF(A78="",0,COUNTIFS($A$2:$A$3058,A78,$P$2:$P$3058,"OK")) -> 1 | S78: =IF(OR(A78="",P78="DUP",R78<2),"",IF(Q78=_xlfn.MINIFS($Q$2:$Q$3058,$A$2:$A$3058,A78,$P$2:$P$3058,"OK"),"KEEP","DROP")) | T78: =IF(A78="",1,0) -> 0 | U78: =IF(D78="",1,0) -> 0 | V78: =IF(E78="",1,0) -> 0 | W78: =IF(OR(H78<1,H78>10),1,0) -> 0 | X78: =IF(OR(I78<=0,I78>1500),1,0) -> 0 | Y78: =IF(J78>H78*I78,1,0) -> 0 | Z78: =IF(AND(N78<>"",OR(N78<1,N78>5)),1,0) -> 0 | AA78: =IF(AND(M78<>"",OR(M78<5,M78>180)),1,0) -> 0 | AB78: =IF(P78="DUP","Exact duplicate row",IF(T78=1,"Missing Order ID",IF(S78="DROP","Duplicate Order ID (less complete row)",IF(U78=1,"Missing Customer ID",IF(V78=1,"Missing Restaurant name",IF(W78=1,"Invalid/outlier quantity",IF(X78=1,"Invalid/outlier unit price",IF(Y78=1,"Discount greater than order value","")))))))) | AC78: =IF(AB78="","KEEP","DROP") -> KEEP | AD78: =IF(TRIM(F78)="",IFERROR(INDEX(Map_Tables!$I$4:$I$37,MATCH(TRIM(E78),Map_Tables!$G$4:$G$37,0)),""),IFERROR(INDEX(Map_Tables!$B$4:$B$18,MATCH(TRIM(F78),Map_Tables!$A$4:$A$18,0)),"CHECK")) -> Pune | AE78: =IF(TRIM(E78)="","",IFERROR(INDEX(Map_Tables!$H$4:$H$37,MATCH(TRIM(E78),Map_Tables!$G$4:$G$37,0)),"CHECK")) -> Pune Burger Hub | AF78: =IF(TRIM(K78)="","Unknown",IFERROR(INDEX(Map_Tables!$E$4:$E$15,MATCH(TRIM(K78),Map_Tables!$D$4:$D$15,0)),"CHECK")) -> UPI | AG78: =IF(LEFT(LOWER(TRIM(L78)),6)="cancel","Cancelled","Delivered") -> Delivered | AH78: =IF(ISNUMBER(SEARCH("/",B78)),DATE(VALUE(RIGHT(B78,4)),VALUE(MID(B78,4,2)),VALUE(LEFT(B78,2))),IF(MID(B78,5,1)="-",DATE(VALUE(LEFT(B78,4)),VALUE(MID(B78,6,2)),VALUE(RIGHT(B78,2))),DATE(VALUE(RIGHT(B78,4)),MATCH(MID(B78,4,3),{"Jan","Feb","Mar","Apr","May","Jun","Jul","Aug","Sep","Oct","Nov","Dec"},0),VALUE(LEFT(B78,2))))) -> 45868
A79: ORD12845 | B79: 14/12/2025 | C79: 13:20 | D79: C0140 | E79: Chaat Corner | F79: Delhi | G79: Street Food | H79: 1 | I79: 105 | J79: 0 | K79: Net Banking | L79: Delivered | M79: 37 | N79: 2 | O79: =A79&"|"&B79&"|"&C79&"|"&D79&"|"&E79&"|"&F79&"|"&G79&"|"&H79&"|"&I79&"|"&J79&"|"&K79&"|"&L79&"|"&M79&"|"&N79 -> ORD12845|14/12/2025|13:20|C0140|Chaat Corner|Delhi|Street Food|1|105|0|Net Banking|Delivered|37|2 | P79: =IF(COUNTIF($O$2:O79,O79)>1,"DUP","OK") -> OK | Q79: =COUNTBLANK(A79:N79) -> 0 | R79: =IF(A79="",0,COUNTIFS($A$2:$A$3058,A79,$P$2:$P$3058,"OK")) -> 1 | S79: =IF(OR(A79="",P79="DUP",R79<2),"",IF(Q79=_xlfn.MINIFS($Q$2:$Q$3058,$A$2:$A$3058,A79,$P$2:$P$3058,"OK"),"KEEP","DROP")) | T79: =IF(A79="",1,0) -> 0 | U79: =IF(D79="",1,0) -> 0 | V79: =IF(E79="",1,0) -> 0 | W79: =IF(OR(H79<1,H79>10),1,0) -> 0 | X79: =IF(OR(I79<=0,I79>1500),1,0) -> 0 | Y79: =IF(J79>H79*I79,1,0) -> 0 | Z79: =IF(AND(N79<>"",OR(N79<1,N79>5)),1,0) -> 0 | AA79: =IF(AND(M79<>"",OR(M79<5,M79>180)),1,0) -> 0 | AB79: =IF(P79="DUP","Exact duplicate row",IF(T79=1,"Missing Order ID",IF(S79="DROP","Duplicate Order ID (less complete row)",IF(U79=1,"Missing Customer ID",IF(V79=1,"Missing Restaurant name",IF(W79=1,"Invalid/outlier quantity",IF(X79=1,"Invalid/outlier unit price",IF(Y79=1,"Discount greater than order value","")))))))) | AC79: =IF(AB79="","KEEP","DROP") -> KEEP | AD79: =IF(TRIM(F79)="",IFERROR(INDEX(Map_Tables!$I$4:$I$37,MATCH(TRIM(E79),Map_Tables!$G$4:$G$37,0)),""),IFERROR(INDEX(Map_Tables!$B$4:$B$18,MATCH(TRIM(F79),Map_Tables!$A$4:$A$18,0)),"CHECK")) -> Delhi | AE79: =IF(TRIM(E79)="","",IFERROR(INDEX(Map_Tables!$H$4:$H$37,MATCH(TRIM(E79),Map_Tables!$G$4:$G$37,0)),"CHECK")) -> Chaat Corner | AF79: =IF(TRIM(K79)="","Unknown",IFERROR(INDEX(Map_Tables!$E$4:$E$15,MATCH(TRIM(K79),Map_Tables!$D$4:$D$15,0)),"CHECK")) -> Net Banking | AG79: =IF(LEFT(LOWER(TRIM(L79)),6)="cancel","Cancelled","Delivered") -> Delivered | AH79: =IF(ISNUMBER(SEARCH("/",B79)),DATE(VALUE(RIGHT(B79,4)),VALUE(MID(B79,4,2)),VALUE(LEFT(B79,2))),IF(MID(B79,5,1)="-",DATE(VALUE(LEFT(B79,4)),VALUE(MID(B79,6,2)),VALUE(RIGHT(B79,2))),DATE(VALUE(RIGHT(B79,4)),MATCH(MID(B79,4,3),{"Jan","Feb","Mar","Apr","May","Jun","Jul","Aug","Sep","Oct","Nov","Dec"},0),VALUE(LEFT(B79,2))))) -> 46005
A80: ORD10260 | B80: 2025-02-04 | C80: 11:17 | D80: C0028 | E80: Mumbai Pizza Co | F80: Mumbai | G80: Pizza | H80: 2 | I80: 375 | J80: 50 | K80: Upi | L80: Delivered | M80: 36 | N80: 4 | O80: =A80&"|"&B80&"|"&C80&"|"&D80&"|"&E80&"|"&F80&"|"&G80&"|"&H80&"|"&I80&"|"&J80&"|"&K80&"|"&L80&"|"&M80&"|"&N80 -> ORD10260|2025-02-04|11:17|C0028|Mumbai Pizza Co|Mumbai|Pizza|2|375|50|Upi|Delivered|36|4 | P80: =IF(COUNTIF($O$2:O80,O80)>1,"DUP","OK") -> OK | Q80: =COUNTBLANK(A80:N80) -> 0 | R80: =IF(A80="",0,COUNTIFS($A$2:$A$3058,A80,$P$2:$P$3058,"OK")) -> 1 | S80: =IF(OR(A80="",P80="DUP",R80<2),"",IF(Q80=_xlfn.MINIFS($Q$2:$Q$3058,$A$2:$A$3058,A80,$P$2:$P$3058,"OK"),"KEEP","DROP")) | T80: =IF(A80="",1,0) -> 0 | U80: =IF(D80="",1,0) -> 0 | V80: =IF(E80="",1,0) -> 0 | W80: =IF(OR(H80<1,H80>10),1,0) -> 0 | X80: =IF(OR(I80<=0,I80>1500),1,0) -> 0 | Y80: =IF(J80>H80*I80,1,0) -> 0 | Z80: =IF(AND(N80<>"",OR(N80<1,N80>5)),1,0) -> 0 | AA80: =IF(AND(M80<>"",OR(M80<5,M80>180)),1,0) -> 0 | AB80: =IF(P80="DUP","Exact duplicate row",IF(T80=1,"Missing Order ID",IF(S80="DROP","Duplicate Order ID (less complete row)",IF(U80=1,"Missing Customer ID",IF(V80=1,"Missing Restaurant name",IF(W80=1,"Invalid/outlier quantity",IF(X80=1,"Invalid/outlier unit price",IF(Y80=1,"Discount greater than order value","")))))))) | AC80: =IF(AB80="","KEEP","DROP") -> KEEP | AD80: =IF(TRIM(F80)="",IFERROR(INDEX(Map_Tables!$I$4:$I$37,MATCH(TRIM(E80),Map_Tables!$G$4:$G$37,0)),""),IFERROR(INDEX(Map_Tables!$B$4:$B$18,MATCH(TRIM(F80),Map_Tables!$A$4:$A$18,0)),"CHECK")) -> Mumbai | AE80: =IF(TRIM(E80)="","",IFERROR(INDEX(Map_Tables!$H$4:$H$37,MATCH(TRIM(E80),Map_Tables!$G$4:$G$37,0)),"CHECK")) -> Mumbai Pizza Co | AF80: =IF(TRIM(K80)="","Unknown",IFERROR(INDEX(Map_Tables!$E$4:$E$15,MATCH(TRIM(K80),Map_Tables!$D$4:$D$15,0)),"CHECK")) -> UPI | AG80: =IF(LEFT(LOWER(TRIM(L80)),6)="cancel","Cancelled","Delivered") -> Delivered | AH80: =IF(ISNUMBER(SEARCH("/",B80)),DATE(VALUE(RIGHT(B80,4)),VALUE(MID(B80,4,2)),VALUE(LEFT(B80,2))),IF(MID(B80,5,1)="-",DATE(VALUE(LEFT(B80,4)),VALUE(MID(B80,6,2)),VALUE(RIGHT(B80,2))),DATE(VALUE(RIGHT(B80,4)),MATCH(MID(B80,4,3),{"Jan","Feb","Mar","Apr","May","Jun","Jul","Aug","Sep","Oct","Nov","Dec"},0),VALUE(LEFT(B80,2))))) -> 45692
A81: ORD11459 | B81: 2025-07-09 | C81: 19:06 | D81: C1338 | E81: Tandoor Tales | F81: DELHI | G81: North Indian | H81: 2 | I81: 255 | J81: 0 | K81: UPI | L81: Delivered | M81: 40 | O81: =A81&"|"&B81&"|"&C81&"|"&D81&"|"&E81&"|"&F81&"|"&G81&"|"&H81&"|"&I81&"|"&J81&"|"&K81&"|"&L81&"|"&M81&"|"&N81 -> ORD11459|2025-07-09|19:06|C1338|Tandoor Tales|DELHI|North Indian|2|255|0|UPI|Delivered|40| | P81: =IF(COUNTIF($O$2:O81,O81)>1,"DUP","OK") -> OK | Q81: =COUNTBLANK(A81:N81) -> 1 | R81: =IF(A81="",0,COUNTIFS($A$2:$A$3058,A81,$P$2:$P$3058,"OK")) -> 1 | S81: =IF(OR(A81="",P81="DUP",R81<2),"",IF(Q81=_xlfn.MINIFS($Q$2:$Q$3058,$A$2:$A$3058,A81,$P$2:$P$3058,"OK"),"KEEP","DROP")) | T81: =IF(A81="",1,0) -> 0 | U81: =IF(D81="",1,0) -> 0 | V81: =IF(E81="",1,0) -> 0 | W81: =IF(OR(H81<1,H81>10),1,0) -> 0 | X81: =IF(OR(I81<=0,I81>1500),1,0) -> 0 | Y81: =IF(J81>H81*I81,1,0) -> 0 | Z81: =IF(AND(N81<>"",OR(N81<1,N81>5)),1,0) -> 0 | AA81: =IF(AND(M81<>"",OR(M81<5,M81>180)),1,0) -> 0 | AB81: =IF(P81="DUP","Exact duplicate row",IF(T81=1,"Missing Order ID",IF(S81="DROP","Duplicate Order ID (less complete row)",IF(U81=1,"Missing Customer ID",IF(V81=1,"Missing Restaurant name",IF(W81=1,"Invalid/outlier quantity",IF(X81=1,"Invalid/outlier unit price",IF(Y81=1,"Discount greater than order value","")))))))) | AC81: =IF(AB81="","KEEP","DROP") -> KEEP | AD81: =IF(TRIM(F81)="",IFERROR(INDEX(Map_Tables!$I$4:$I$37,MATCH(TRIM(E81),Map_Tables!$G$4:$G$37,0)),""),IFERROR(INDEX(Map_Tables!$B$4:$B$18,MATCH(TRIM(F81),Map_Tables!$A$4:$A$18,0)),"CHECK")) -> Delhi | AE81: =IF(TRIM(E81)="","",IFERROR(INDEX(Map_Tables!$H$4:$H$37,MATCH(TRIM(E81),Map_Tables!$G$4:$G$37,0)),"CHECK")) -> Tandoor Tales | AF81: =IF(TRIM(K81)="","Unknown",IFERROR(INDEX(Map_Tables!$E$4:$E$15,MATCH(TRIM(K81),Map_Tables!$D$4:$D$15,0)),"CHECK")) -> UPI | AG81: =IF(LEFT(LOWER(TRIM(L81)),6)="cancel","Cancelled","Delivered") -> Delivered | AH81: =IF(ISNUMBER(SEARCH("/",B81)),DATE(VALUE(RIGHT(B81,4)),VALUE(MID(B81,4,2)),VALUE(LEFT(B81,2))),IF(MID(B81,5,1)="-",DATE(VALUE(LEFT(B81,4)),VALUE(MID(B81,6,2)),VALUE(RIGHT(B81,2))),DATE(VALUE(RIGHT(B81,4)),MATCH(MID(B81,4,3),{"Jan","Feb","Mar","Apr","May","Jun","Jul","Aug","Sep","Oct","Nov","Dec"},0),VALUE(LEFT(B81,2))))) -> 45847
A82: ORD11831 | B82: 2025-08-27 | C82: 15:32 | D82: C0747 | E82: Hyderabad Dum Biryani | F82: Hyderabad | G82: Biryani | H82: 2 | I82: 275 | J82: 20 | K82: DC | L82: Delivered | M82: 18 | N82: 4 | O82: =A82&"|"&B82&"|"&C82&"|"&D82&"|"&E82&"|"&F82&"|"&G82&"|"&H82&"|"&I82&"|"&J82&"|"&K82&"|"&L82&"|"&M82&"|"&N82 -> ORD11831|2025-08-27|15:32|C0747|Hyderabad Dum Biryani|Hyderabad|Biryani|2|275|20|DC|Delivered|18|4 | P82: =IF(COUNTIF($O$2:O82,O82)>1,"DUP","OK") -> OK | Q82: =COUNTBLANK(A82:N82) -> 0 | R82: =IF(A82="",0,COUNTIFS($A$2:$A$3058,A82,$P$2:$P$3058,"OK")) -> 1 | S82: =IF(OR(A82="",P82="DUP",R82<2),"",IF(Q82=_xlfn.MINIFS($Q$2:$Q$3058,$A$2:$A$3058,A82,$P$2:$P$3058,"OK"),"KEEP","DROP")) | T82: =IF(A82="",1,0) -> 0 | U82: =IF(D82="",1,0) -> 0 | V82: =IF(E82="",1,0) -> 0 | W82: =IF(OR(H82<1,H82>10),1,0) -> 0 | X82: =IF(OR(I82<=0,I82>1500),1,0) -> 0 | Y82: =IF(J82>H82*I82,1,0) -> 0 | Z82: =IF(AND(N82<>"",OR(N82<1,N82>5)),1,0) -> 0 | AA82: =IF(AND(M82<>"",OR(M82<5,M82>180)),1,0) -> 0 | AB82: =IF(P82="DUP","Exact duplicate row",IF(T82=1,"Missing Order ID",IF(S82="DROP","Duplicate Order ID (less complete row)",IF(U82=1,"Missing Customer ID",IF(V82=1,"Missing Restaurant name",IF(W82=1,"Invalid/outlier quantity",IF(X82=1,"Invalid/outlier unit price",IF(Y82=1,"Discount greater than order value","")))))))) | AC82: =IF(AB82="","KEEP","DROP") -> KEEP | AD82: =IF(TRIM(F82)="",IFERROR(INDEX(Map_Tables!$I$4:$I$37,MATCH(TRIM(E82),Map_Tables!$G$4:$G$37,0)),""),IFERROR(INDEX(Map_Tables!$B$4:$B$18,MATCH(TRIM(F82),Map_Tables!$A$4:$A$18,0)),"CHECK")) -> Hyderabad | AE82: =IF(TRIM(E82)="","",IFERROR(INDEX(Map_Tables!$H$4:$H$37,MATCH(TRIM(E82),Map_Tables!$G$4:$G$37,0)),"CHECK")) -> Hyderabad Dum Biryani | AF82: =IF(TRIM(K82)="","Unknown",IFERROR(INDEX(Map_Tables!$E$4:$E$15,MATCH(TRIM(K82),Map_Tables!$D$4:$D$15,0)),"CHECK")) -> Debit Card | AG82: =IF(LEFT(LOWER(TRIM(L82)),6)="cancel","Cancelled","Delivered") -> Delivered | AH82: =IF(ISNUMBER(SEARCH("/",B82)),DATE(VALUE(RIGHT(B82,4)),VALUE(MID(B82,4,2)),VALUE(LEFT(B82,2))),IF(MID(B82,5,1)="-",DATE(VALUE(LEFT(B82,4)),VALUE(MID(B82,6,2)),VALUE(RIGHT(B82,2))),DATE(VALUE(RIGHT(B82,4)),MATCH(MID(B82,4,3),{"Jan","Feb","Mar","Apr","May","Jun","Jul","Aug","Sep","Oct","Nov","Dec"},0),VALUE(LEFT(B82,2))))) -> 45896
A83: ORD12117 | B83: 2025-09-29 | C83: 18:36 | D83: C0383 | E83: Momo Magic | F83: Delhi | G83: CHINESE | H83: 3 | I83: 170 | J83: 0 | K83: UPI | L83: Delivered | M83: 35 | N83: 5 | O83: =A83&"|"&B83&"|"&C83&"|"&D83&"|"&E83&"|"&F83&"|"&G83&"|"&H83&"|"&I83&"|"&J83&"|"&K83&"|"&L83&"|"&M83&"|"&N83 -> ORD12117|2025-09-29|18:36|C0383|Momo Magic|Delhi|CHINESE|3|170|0|UPI|Delivered|35|5 | P83: =IF(COUNTIF($O$2:O83,O83)>1,"DUP","OK") -> OK | Q83: =COUNTBLANK(A83:N83) -> 0 | R83: =IF(A83="",0,COUNTIFS($A$2:$A$3058,A83,$P$2:$P$3058,"OK")) -> 1 | S83: =IF(OR(A83="",P83="DUP",R83<2),"",IF(Q83=_xlfn.MINIFS($Q$2:$Q$3058,$A$2:$A$3058,A83,$P$2:$P$3058,"OK"),"KEEP","DROP")) | T83: =IF(A83="",1,0) -> 0 | U83: =IF(D83="",1,0) -> 0 | V83: =IF(E83="",1,0) -> 0 | W83: =IF(OR(H83<1,H83>10),1,0) -> 0 | X83: =IF(OR(I83<=0,I83>1500),1,0) -> 0 | Y83: =IF(J83>H83*I83,1,0) -> 0 | Z83: =IF(AND(N83<>"",OR(N83<1,N83>5)),1,0) -> 0 | AA83: =IF(AND(M83<>"",OR(M83<5,M83>180)),1,0) -> 0 | AB83: =IF(P83="DUP","Exact duplicate row",IF(T83=1,"Missing Order ID",IF(S83="DROP","Duplicate Order ID (less complete row)",IF(U83=1,"Missing Customer ID",IF(V83=1,"Missing Restaurant name",IF(W83=1,"Invalid/outlier quantity",IF(X83=1,"Invalid/outlier unit price",IF(Y83=1,"Discount greater than order value","")))))))) | AC83: =IF(AB83="","KEEP","DROP") -> KEEP | AD83: =IF(TRIM(F83)="",IFERROR(INDEX(Map_Tables!$I$4:$I$37,MATCH(TRIM(E83),Map_Tables!$G$4:$G$37,0)),""),IFERROR(INDEX(Map_Tables!$B$4:$B$18,MATCH(TRIM(F83),Map_Tables!$A$4:$A$18,0)),"CHECK")) -> Delhi | AE83: =IF(TRIM(E83)="","",IFERROR(INDEX(Map_Tables!$H$4:$H$37,MATCH(TRIM(E83),Map_Tables!$G$4:$G$37,0)),"CHECK")) -> Momo Magic | AF83: =IF(TRIM(K83)="","Unknown",IFERROR(INDEX(Map_Tables!$E$4:$E$15,MATCH(TRIM(K83),Map_Tables!$D$4:$D$15,0)),"CHECK")) -> UPI | AG83: =IF(LEFT(LOWER(TRIM(L83)),6)="cancel","Cancelled","Delivered") -> Delivered | AH83: =IF(ISNUMBER(SEARCH("/",B83)),DATE(VALUE(RIGHT(B83,4)),VALUE(MID(B83,4,2)),VALUE(LEFT(B83,2))),IF(MID(B83,5,1)="-",DATE(VALUE(LEFT(B83,4)),VALUE(MID(B83,6,2)),VALUE(RIGHT(B83,2))),DATE(VALUE(RIGHT(B83,4)),MATCH(MID(B83,4,3),{"Jan","Feb","Mar","Apr","May","Jun","Jul","Aug","Sep","Oct","Nov","Dec"},0),VALUE(LEFT(B83,2))))) -> 45929
A84: ORD11383 | B84: 2025-06-28 | C84: 11:02 | D84: C0459 | E84: Pune Burger Hub | F84: Pune | G84: Burgers | H84: 1 | I84: 225 | J84: 20 | K84: Credit Card | L84: Delivered | M84: 35 | N84: 4 | O84: =A84&"|"&B84&"|"&C84&"|"&D84&"|"&E84&"|"&F84&"|"&G84&"|"&H84&"|"&I84&"|"&J84&"|"&K84&"|"&L84&"|"&M84&"|"&N84 -> ORD11383|2025-06-28|11:02|C0459|Pune Burger Hub|Pune|Burgers|1|225|20|Credit Card|Delivered|35|4 | P84: =IF(COUNTIF($O$2:O84,O84)>1,"DUP","OK") -> OK | Q84: =COUNTBLANK(A84:N84) -> 0 | R84: =IF(A84="",0,COUNTIFS($A$2:$A$3058,A84,$P$2:$P$3058,"OK")) -> 1 | S84: =IF(OR(A84="",P84="DUP",R84<2),"",IF(Q84=_xlfn.MINIFS($Q$2:$Q$3058,$A$2:$A$3058,A84,$P$2:$P$3058,"OK"),"KEEP","DROP")) | T84: =IF(A84="",1,0) -> 0 | U84: =IF(D84="",1,0) -> 0 | V84: =IF(E84="",1,0) -> 0 | W84: =IF(OR(H84<1,H84>10),1,0) -> 0 | X84: =IF(OR(I84<=0,I84>1500),1,0) -> 0 | Y84: =IF(J84>H84*I84,1,0) -> 0 | Z84: =IF(AND(N84<>"",OR(N84<1,N84>5)),1,0) -> 0 | AA84: =IF(AND(M84<>"",OR(M84<5,M84>180)),1,0) -> 0 | AB84: =IF(P84="DUP","Exact duplicate row",IF(T84=1,"Missing Order ID",IF(S84="DROP","Duplicate Order ID (less complete row)",IF(U84=1,"Missing Customer ID",IF(V84=1,"Missing Restaurant name",IF(W84=1,"Invalid/outlier quantity",IF(X84=1,"Invalid/outlier unit price",IF(Y84=1,"Discount greater than order value","")))))))) | AC84: =IF(AB84="","KEEP","DROP") -> KEEP | AD84: =IF(TRIM(F84)="",IFERROR(INDEX(Map_Tables!$I$4:$I$37,MATCH(TRIM(E84),Map_Tables!$G$4:$G$37,0)),""),IFERROR(INDEX(Map_Tables!$B$4:$B$18,MATCH(TRIM(F84),Map_Tables!$A$4:$A$18,0)),"CHECK")) -> Pune | AE84: =IF(TRIM(E84)="","",IFERROR(INDEX(Map_Tables!$H$4:$H$37,MATCH(TRIM(E84),Map_Tables!$G$4:$G$37,0)),"CHECK")) -> Pune Burger Hub | AF84: =IF(TRIM(K84)="","Unknown",IFERROR(INDEX(Map_Tables!$E$4:$E$15,MATCH(TRIM(K84),Map_Tables!$D$4:$D$15,0)),"CHECK")) -> Credit Card | AG84: =IF(LEFT(LOWER(TRIM(L84)),6)="cancel","Cancelled","Delivered") -> Delivered | AH84: =IF(ISNUMBER(SEARCH("/",B84)),DATE(VALUE(RIGHT(B84,4)),VALUE(MID(B84,4,2)),VALUE(LEFT(B84,2))),IF(MID(B84,5,1)="-",DATE(VALUE(LEFT(B84,4)),VALUE(MID(B84,6,2)),VALUE(RIGHT(B84,2))),DATE(VALUE(RIGHT(B84,4)),MATCH(MID(B84,4,3),{"Jan","Feb","Mar","Apr","May","Jun","Jul","Aug","Sep","Oct","Nov","Dec"},0),VALUE(LEFT(B84,2))))) -> 45836
A85: ORD12038 | B85: 2025-09-20 | C85: 20:37 | D85: C1155 | E85: Mumbai Pizza Co | F85: Bombay | G85: Pizza | H85: 3 | I85: 395 | J85: 0 | K85: UPI | L85: Delivered | M85: 36 | N85: 5 | O85: =A85&"|"&B85&"|"&C85&"|"&D85&"|"&E85&"|"&F85&"|"&G85&"|"&H85&"|"&I85&"|"&J85&"|"&K85&"|"&L85&"|"&M85&"|"&N85 -> ORD12038|2025-09-20|20:37|C1155|Mumbai Pizza Co|Bombay|Pizza|3|395|0|UPI|Delivered|36|5 | P85: =IF(COUNTIF($O$2:O85,O85)>1,"DUP","OK") -> OK | Q85: =COUNTBLANK(A85:N85) -> 0 | R85: =IF(A85="",0,COUNTIFS($A$2:$A$3058,A85,$P$2:$P$3058,"OK")) -> 1 | S85: =IF(OR(A85="",P85="DUP",R85<2),"",IF(Q85=_xlfn.MINIFS($Q$2:$Q$3058,$A$2:$A$3058,A85,$P$2:$P$3058,"OK"),"KEEP","DROP")) | T85: =IF(A85="",1,0) -> 0 | U85: =IF(D85="",1,0) -> 0 | V85: =IF(E85="",1,0) -> 0 | W85: =IF(OR(H85<1,H85>10),1,0) -> 0 | X85: =IF(OR(I85<=0,I85>1500),1,0) -> 0 | Y85: =IF(J85>H85*I85,1,0) -> 0 | Z85: =IF(AND(N85<>"",OR(N85<1,N85>5)),1,0) -> 0 | AA85: =IF(AND(M85<>"",OR(M85<5,M85>180)),1,0) -> 0 | AB85: =IF(P85="DUP","Exact duplicate row",IF(T85=1,"Missing Order ID",IF(S85="DROP","Duplicate Order ID (less complete row)",IF(U85=1,"Missing Customer ID",IF(V85=1,"Missing Restaurant name",IF(W85=1,"Invalid/outlier quantity",IF(X85=1,"Invalid/outlier unit price",IF(Y85=1,"Discount greater than order value","")))))))) | AC85: =IF(AB85="","KEEP","DROP") -> KEEP | AD85: =IF(TRIM(F85)="",IFERROR(INDEX(Map_Tables!$I$4:$I$37,MATCH(TRIM(E85),Map_Tables!$G$4:$G$37,0)),""),IFERROR(INDEX(Map_Tables!$B$4:$B$18,MATCH(TRIM(F85),Map_Tables!$A$4:$A$18,0)),"CHECK")) -> Mumbai | AE85: =IF(TRIM(E85)="","",IFERROR(INDEX(Map_Tables!$H$4:$H$37,MATCH(TRIM(E85),Map_Tables!$G$4:$G$37,0)),"CHECK")) -> Mumbai Pizza Co | AF85: =IF(TRIM(K85)="","Unknown",IFERROR(INDEX(Map_Tables!$E$4:$E$15,MATCH(TRIM(K85),Map_Tables!$D$4:$D$15,0)),"CHECK")) -> UPI | AG85: =IF(LEFT(LOWER(TRIM(L85)),6)="cancel","Cancelled","Delivered") -> Delivered | AH85: =IF(ISNUMBER(SEARCH("/",B85)),DATE(VALUE(RIGHT(B85,4)),VALUE(MID(B85,4,2)),VALUE(LEFT(B85,2))),IF(MID(B85,5,1)="-",DATE(VALUE(LEFT(B85,4)),VALUE(MID(B85,6,2)),VALUE(RIGHT(B85,2))),DATE(VALUE(RIGHT(B85,4)),MATCH(MID(B85,4,3),{"Jan","Feb","Mar","Apr","May","Jun","Jul","Aug","Sep","Oct","Nov","Dec"},0),VALUE(LEFT(B85,2))))) -> 45920
A86: ORD12102 | B86: 2025-09-28 | C86: 11:51 | D86: C0110 | E86: Curry Leaf Kitchen | F86: Mumbai | G86: North Indian | H86: 2 | I86: 260 | J86: 30 | K86: Credit Card | L86: Delivered | M86: 37 | N86: 3 | O86: =A86&"|"&B86&"|"&C86&"|"&D86&"|"&E86&"|"&F86&"|"&G86&"|"&H86&"|"&I86&"|"&J86&"|"&K86&"|"&L86&"|"&M86&"|"&N86 -> ORD12102|2025-09-28|11:51|C0110|Curry Leaf Kitchen|Mumbai|North Indian|2|260|30|Credit Card|Delivered|37|3 | P86: =IF(COUNTIF($O$2:O86,O86)>1,"DUP","OK") -> OK | Q86: =COUNTBLANK(A86:N86) -> 0 | R86: =IF(A86="",0,COUNTIFS($A$2:$A$3058,A86,$P$2:$P$3058,"OK")) -> 1 | S86: =IF(OR(A86="",P86="DUP",R86<2),"",IF(Q86=_xlfn.MINIFS($Q$2:$Q$3058,$A$2:$A$3058,A86,$P$2:$P$3058,"OK"),"KEEP","DROP")) | T86: =IF(A86="",1,0) -> 0 | U86: =IF(D86="",1,0) -> 0 | V86: =IF(E86="",1,0) -> 0 | W86: =IF(OR(H86<1,H86>10),1,0) -> 0 | X86: =IF(OR(I86<=0,I86>1500),1,0) -> 0 | Y86: =IF(J86>H86*I86,1,0) -> 0 | Z86: =IF(AND(N86<>"",OR(N86<1,N86>5)),1,0) -> 0 | AA86: =IF(AND(M86<>"",OR(M86<5,M86>180)),1,0) -> 0 | AB86: =IF(P86="DUP","Exact duplicate row",IF(T86=1,"Missing Order ID",IF(S86="DROP","Duplicate Order ID (less complete row)",IF(U86=1,"Missing Customer ID",IF(V86=1,"Missing Restaurant name",IF(W86=1,"Invalid/outlier quantity",IF(X86=1,"Invalid/outlier unit price",IF(Y86=1,"Discount greater than order value","")))))))) | AC86: =IF(AB86="","KEEP","DROP") -> KEEP | AD86: =IF(TRIM(F86)="",IFERROR(INDEX(Map_Tables!$I$4:$I$37,MATCH(TRIM(E86),Map_Tables!$G$4:$G$37,0)),""),IFERROR(INDEX(Map_Tables!$B$4:$B$18,MATCH(TRIM(F86),Map_Tables!$A$4:$A$18,0)),"CHECK")) -> Mumbai | AE86: =IF(TRIM(E86)="","",IFERROR(INDEX(Map_Tables!$H$4:$H$37,MATCH(TRIM(E86),Map_Tables!$G$4:$G$37,0)),"CHECK")) -> Curry Leaf Kitchen | AF86: =IF(TRIM(K86)="","Unknown",IFERROR(INDEX(Map_Tables!$E$4:$E$15,MATCH(TRIM(K86),Map_Tables!$D$4:$D$15,0)),"CHECK")) -> Credit Card | AG86: =IF(LEFT(LOWER(TRIM(L86)),6)="cancel","Cancelled","Delivered") -> Delivered | AH86: =IF(ISNUMBER(SEARCH("/",B86)),DATE(VALUE(RIGHT(B86,4)),VALUE(MID(B86,4,2)),VALUE(LEFT(B86,2))),IF(MID(B86,5,1)="-",DATE(VALUE(LEFT(B86,4)),VALUE(MID(B86,6,2)),VALUE(RIGHT(B86,2))),DATE(VALUE(RIGHT(B86,4)),MATCH(MID(B86,4,3),{"Jan","Feb","Mar","Apr","May","Jun","Jul","Aug","Sep","Oct","Nov","Dec"},0),VALUE(LEFT(B86,2))))) -> 45928
